Workbook
Name lstLocation: #REF!
Name lstOwnerAM: #REF!
Name lstOwnerComm: #REF!
Name lstStatus: #REF!
Name lstType: #REF!

Sheet 🏠 HOME
B2: FROM · PRICE LIST TRACKER
B3: ="Real estate development portfolio · Last Updated 28 june 2026" -> Real estate development portfolio · Last Updated 28 june 2026
B5: QUICK NAVIGATION
B7: VILAMOURA · 13 projects
B8: ▸ Nobilus | F8: ▸ Natura Village 4 | J8: ▸ Natura Village 7 | N8: ▸ Natura Village 9
B9: ▸ The Nine | F9: ▸ Terracota | J9: ▸ Rivus | N9: ▸ Fairways
B10: ▸ Estalagem das Cegonhas | F10: ▸ Springs - At the Els | J10: ▸ Zestia | N10: ▸ The Uncommon
B11: ▸ Botanica
B13: ALGARVE · 4 projects
B14: ▸ Sutaya | F14: ▸ Azuya | J14: ▸ Palmares | N14: ▸ Monte Rei
B16: LISBON & NORTH · 2 projects
B17: ▸ Aroeira Collections | F17: ▸ Vale Pisão Grand Park

Sheet Overview
B2: Portfolio Overview | H2: SELECT REGION → | I2: All regions | L2: {="Showing "&SUMPRODUCT((($I$2="All regions")+($X$7:$X$23=$I$2)>0)*(($I$4="All statuses")+($Y$7:$Y$23=$I$4)>0))&" of "&COUNTA($B$7:$B$23)} -> Showing 17 of 17 | Q2: Selected Project Status | R2: Units
B4: =COUNTA($B$7:$B$23)&" developments · one curation" -> 17 developments · one curation | H4: SELECT STATUS → | I4: All statuses | L4: developments match your filters | Q4: Available | R4: =E34 -> 15 | AA4: All regions | AC4: All statuses
Q5: Reserved | R5: =G34 -> 5
B6: Project | C6: Status | D6: Location | E6: Type | F6: Conclusion | G6: Units | H6: Available | I6: Pre-Reserved & Reserved | J6: PSPA | K6: Deeded | L6: Other | M6: % Sold | N6: GDV Asking (€M) | O6: Deeded Value (€M) | Q6: Under Contract | R6: =I34 -> 0 | X6: Region | Y6: Sales Status | AA6: Vilamoura | AC6: Active
B7: Natura Village | C7: =IFERROR(TRIM(_xlfn.XLOOKUP($B7,DATABASE_Table[Development],DATABASE_Table[Selling Status],"—")),"—") -> DEED | D7: {=IFERROR(INDEX(_xlfn._xlws.FILTER(DATABASE_Table[Location],(DATABASE_Table[Development]=$B7)*(DATABASE_Table[Location]<>"")),1),IFERROR(_xlfn.XLOOKUP($B7,DATABASE_Table[Development],DATABASE_Table[Local],"—"),"—"))} -> Vilamoura, Algarve | E7: {=IFERROR(INDEX(_xlfn._xlws.FILTER(DATABASE_Table[Typology],(DATABASE_Table[Development]=$B7)*(DATABASE_Table[Typology]<>"")),1),"—")} -> V3 | F7: {=IFERROR(INDEX(_xlfn._xlws.FILTER(DATABASE_Table[Delivery Expected],(DATABASE_Table[Development]=$B7)*(DATABASE_Table[Delivery Expected]<>"")),1),"—")} -> — | G7: =COUNTIF(DATABASE_Table[Development],$B7) -> 38 | H7: {=SUMPRODUCT((DATABASE_Table[Development]=$B7)*(TRIM(DATABASE_Table[Selling Status])="AVAILABLE"))} -> 8 | I7: {=SUMPRODUCT((DATABASE_Table[Development]=$B7)*((TRIM(DATABASE_Table[Selling Status])="RESERVED")+(TRIM(DATABASE_Table[Selling Status])="PRE-RESERVED")))} -> 4 | J7: {=SUMPRODUCT((DATABASE_Table[Development]=$B7)*(LEFT(TRIM(DATABASE_Table[Selling Status]),4)="PSPA"))} -> 3 | K7: {=SUMPRODUCT((DATABASE_Table[Development]=$B7)*(TRIM(DATABASE_Table[Selling Status])="DEED"))} -> 23 | L7: {=SUMPRODUCT((DATABASE_Table[Development]=$B7)*((TRIM(DATABASE_Table[Selling Status])="NOT FOR SALE")+(LEFT(TRIM(DATABASE_Table[Selling Status]),4)="UPON")))} -> 0 | M7: =IFERROR((I7+J7+K7)/(G7-L7),0) -> 0.78947368 | N7: =SUMIF(DATABASE_Table[Development],$B7,DATABASE_Table[Current Asking price( Total)])/1000000 -> 37.7745 | O7: {=SUMPRODUCT((DATABASE_Table[Development]=$B7)*(TRIM(DATABASE_Table[Selling Status])="DEED SIGNED")*DATABASE_Table[Sell price (RE Asset)])/1000000} -> 0 | Q7: Deeded | R7: =K34 -> 0 | X7: {=IFERROR(_xlfn.SWITCH(_xlfn.XLOOKUP($B7,DATABASE_Table[Development],DATABASE_Table[Local],"Center"),"Vilamoura","Vilamoura","Algarve","Algarve","North","North","Center"),"Center")} -> Vilamoura | Y7: {=_xlfn.IFS(G7=0,"—",M7>=0.999,"Sold Out",(I7+J7+K7)=0,"Coming Soon",TRUE,"Active")} -> Active | AA7: Algarve | AC7: Sold Out
B8: The Nine | C8: =IFERROR(TRIM(_xlfn.XLOOKUP($B8,DATABASE_Table[Development],DATABASE_Table[Selling Status],"—")),"—") -> DEED | D8: {=IFERROR(INDEX(_xlfn._xlws.FILTER(DATABASE_Table[Location],(DATABASE_Table[Development]=$B8)*(DATABASE_Table[Location]<>"")),1),IFERROR(_xlfn.XLOOKUP($B8,DATABASE_Table[Development],DATABASE_Table[Local],"—"),"—"))} -> Vilamoura, Algarve | E8: {=IFERROR(INDEX(_xlfn._xlws.FILTER(DATABASE_Table[Typology],(DATABASE_Table[Development]=$B8)*(DATABASE_Table[Typology]<>"")),1),"—")} -> T3 | F8: {=IFERROR(INDEX(_xlfn._xlws.FILTER(DATABASE_Table[Delivery Expected],(DATABASE_Table[Development]=$B8)*(DATABASE_Table[Delivery Expected]<>"")),1),"—")} -> — | G8: =COUNTIF(DATABASE_Table[Development],$B8) -> 48 | H8: {=SUMPRODUCT((DATABASE_Table[Development]=$B8)*(TRIM(DATABASE_Table[Selling Status])="AVAILABLE"))} -> 0 | I8: {=SUMPRODUCT((DATABASE_Table[Development]=$B8)*((TRIM(DATABASE_Table[Selling Status])="RESERVED")+(TRIM(DATABASE_Table[Selling Status])="PRE-RESERVED")))} -> 0 | J8: {=SUMPRODUCT((DATABASE_Table[Development]=$B8)*(LEFT(TRIM(DATABASE_Table[Selling Status]),4)="PSPA"))} -> 0 | K8: {=SUMPRODUCT((DATABASE_Table[Development]=$B8)*(TRIM(DATABASE_Table[Selling Status])="DEED"))} -> 48 | L8: {=SUMPRODUCT((DATABASE_Table[Development]=$B8)*((TRIM(DATABASE_Table[Selling Status])="NOT FOR SALE")+(LEFT(TRIM(DATABASE_Table[Selling Status]),4)="UPON")))} -> 0 | M8: =IFERROR((I8+J8+K8)/(G8-L8),0) -> 1 | N8: =SUMIF(DATABASE_Table[Development],$B8,DATABASE_Table[Current Asking price( Total)])/1000000 -> 32.79 | O8: {=SUMPRODUCT((DATABASE_Table[Development]=$B8)*(TRIM(DATABASE_Table[Selling Status])="DEED SIGNED")*DATABASE_Table[Sell price (RE Asset)])/1000000} -> 0 | Q8: Other | R8: =_xlfn.XLOOKUP($E$31,$B$7:$B$23,$L$7:$L$23,0) -> 25 | X8: {=IFERROR(_xlfn.SWITCH(_xlfn.XLOOKUP($B8,DATABASE_Table[Development],DATABASE_Table[Local],"Center"),"Vilamoura","Vilamoura","Algarve","Algarve","North","North","Center"),"Center")} -> Vilamoura | Y8: {=_xlfn.IFS(G8=0,"—",M8>=0.999,"Sold Out",(I8+J8+K8)=0,"Coming Soon",TRUE,"Active")} -> Sold Out | AA8: Center | AC8: Coming Soon
B9: MOURAGOLFE | C9: =IFERROR(TRIM(_xlfn.XLOOKUP($B9,DATABASE_Table[Development],DATABASE_Table[Selling Status],"—")),"—") -> DEED | D9: {=IFERROR(INDEX(_xlfn._xlws.FILTER(DATABASE_Table[Location],(DATABASE_Table[Development]=$B9)*(DATABASE_Table[Location]<>"")),1),IFERROR(_xlfn.XLOOKUP($B9,DATABASE_Table[Development],DATABASE_Table[Local],"—"),"—"))} -> Vilamoura | E9: {=IFERROR(INDEX(_xlfn._xlws.FILTER(DATABASE_Table[Typology],(DATABASE_Table[Development]=$B9)*(DATABASE_Table[Typology]<>"")),1),"—")} -> Plot | F9: {=IFERROR(INDEX(_xlfn._xlws.FILTER(DATABASE_Table[Delivery Expected],(DATABASE_Table[Development]=$B9)*(DATABASE_Table[Delivery Expected]<>"")),1),"—")} -> — | G9: =COUNTIF(DATABASE_Table[Development],$B9) -> 13 | H9: {=SUMPRODUCT((DATABASE_Table[Development]=$B9)*(TRIM(DATABASE_Table[Selling Status])="AVAILABLE"))} -> 0 | I9: {=SUMPRODUCT((DATABASE_Table[Development]=$B9)*((TRIM(DATABASE_Table[Selling Status])="RESERVED")+(TRIM(DATABASE_Table[Selling Status])="PRE-RESERVED")))} -> 0 | J9: {=SUMPRODUCT((DATABASE_Table[Development]=$B9)*(LEFT(TRIM(DATABASE_Table[Selling Status]),4)="PSPA"))} -> 1 | K9: {=SUMPRODUCT((DATABASE_Table[Development]=$B9)*(TRIM(DATABASE_Table[Selling Status])="DEED"))} -> 12 | L9: {=SUMPRODUCT((DATABASE_Table[Development]=$B9)*((TRIM(DATABASE_Table[Selling Status])="NOT FOR SALE")+(LEFT(TRIM(DATABASE_Table[Selling Status]),4)="UPON")))} -> 0 | M9: =IFERROR((I9+J9+K9)/(G9-L9),0) -> 1 | N9: =SUMIF(DATABASE_Table[Development],$B9,DATABASE_Table[Current Asking price( Total)])/1000000 -> 8.665 | O9: {=SUMPRODUCT((DATABASE_Table[Development]=$B9)*(TRIM(DATABASE_Table[Selling Status])="DEED SIGNED")*DATABASE_Table[Sell price (RE Asset)])/1000000} -> 0 | X9: {=IFERROR(_xlfn.SWITCH(_xlfn.XLOOKUP($B9,DATABASE_Table[Development],DATABASE_Table[Local],"Center"),"Vilamoura","Vilamoura","Algarve","Algarve","North","North","Center"),"Center")} -> Vilamoura | Y9: {=_xlfn.IFS(G9=0,"—",M9>=0.999,"Sold Out",(I9+J9+K9)=0,"Coming Soon",TRUE,"Active")} -> Sold Out | AA9: North
B10: Terracota | C10: =IFERROR(TRIM(_xlfn.XLOOKUP($B10,DATABASE_Table[Development],DATABASE_Table[Selling Status],"—")),"—") -> PSPA | D10: {=IFERROR(INDEX(_xlfn._xlws.FILTER(DATABASE_Table[Location],(DATABASE_Table[Development]=$B10)*(DATABASE_Table[Location]<>"")),1),IFERROR(_xlfn.XLOOKUP($B10,DATABASE_Table[Development],DATABASE_Table[Local],"—"),"—"))} -> Vilamoura, Algarve | E10: {=IFERROR(INDEX(_xlfn._xlws.FILTER(DATABASE_Table[Typology],(DATABASE_Table[Development]=$B10)*(DATABASE_Table[Typology]<>"")),1),"—")} -> T3 | F10: {=IFERROR(INDEX(_xlfn._xlws.FILTER(DATABASE_Table[Delivery Expected],(DATABASE_Table[Development]=$B10)*(DATABASE_Table[Delivery Expected]<>"")),1),"—")} -> — | G10: =COUNTIF(DATABASE_Table[Development],$B10) -> 87 | H10: {=SUMPRODUCT((DATABASE_Table[Development]=$B10)*(TRIM(DATABASE_Table[Selling Status])="AVAILABLE"))} -> 12 | I10: {=SUMPRODUCT((DATABASE_Table[Development]=$B10)*((TRIM(DATABASE_Table[Selling Status])="RESERVED")+(TRIM(DATABASE_Table[Selling Status])="PRE-RESERVED")))} -> 3 | J10: {=SUMPRODUCT((DATABASE_Table[Development]=$B10)*(LEFT(TRIM(DATABASE_Table[Selling Status]),4)="PSPA"))} -> 72 | K10: {=SUMPRODUCT((DATABASE_Table[Development]=$B10)*(TRIM(DATABASE_Table[Selling Status])="DEED"))} -> 0 | L10: {=SUMPRODUCT((DATABASE_Table[Development]=$B10)*((TRIM(DATABASE_Table[Selling Status])="NOT FOR SALE")+(LEFT(TRIM(DATABASE_Table[Selling Status]),4)="UPON")))} -> 0 | M10: =IFERROR((I10+J10+K10)/(G10-L10),0) -> 0.86206897 | N10: =SUMIF(DATABASE_Table[Development],$B10,DATABASE_Table[Current Asking price( Total)])/1000000 -> 52.35185 | O10: {=SUMPRODUCT((DATABASE_Table[Development]=$B10)*(TRIM(DATABASE_Table[Selling Status])="DEED SIGNED")*DATABASE_Table[Sell price (RE Asset)])/1000000} -> 0 | X10: {=IFERROR(_xlfn.SWITCH(_xlfn.XLOOKUP($B10,DATABASE_Table[Development],DATABASE_Table[Local],"Center"),"Vilamoura","Vilamoura","Algarve","Algarve","North","North","Center"),"Center")} -> Vilamoura | Y10: {=_xlfn.IFS(G10=0,"—",M10>=0.999,"Sold Out",(I10+J10+K10)=0,"Coming Soon",TRUE,"Active")} -> Active
B11: Nobilus | C11: =IFERROR(TRIM(_xlfn.XLOOKUP($B11,DATABASE_Table[Development],DATABASE_Table[Selling Status],"—")),"—") -> PSPA | D11: {=IFERROR(INDEX(_xlfn._xlws.FILTER(DATABASE_Table[Location],(DATABASE_Table[Development]=$B11)*(DATABASE_Table[Location]<>"")),1),IFERROR(_xlfn.XLOOKUP($B11,DATABASE_Table[Development],DATABASE_Table[Local],"—"),"—"))} -> Vilamoura, Algarve | E11: {=IFERROR(INDEX(_xlfn._xlws.FILTER(DATABASE_Table[Typology],(DATABASE_Table[Development]=$B11)*(DATABASE_Table[Typology]<>"")),1),"—")} -> T2 | F11: {=IFERROR(INDEX(_xlfn._xlws.FILTER(DATABASE_Table[Delivery Expected],(DATABASE_Table[Development]=$B11)*(DATABASE_Table[Delivery Expected]<>"")),1),"—")} -> — | G11: =COUNTIF(DATABASE_Table[Development],$B11) -> 47 | H11: {=SUMPRODUCT((DATABASE_Table[Development]=$B11)*(TRIM(DATABASE_Table[Selling Status])="AVAILABLE"))} -> 33 | I11: {=SUMPRODUCT((DATABASE_Table[Development]=$B11)*((TRIM(DATABASE_Table[Selling Status])="RESERVED")+(TRIM(DATABASE_Table[Selling Status])="PRE-RESERVED")))} -> 0 | J11: {=SUMPRODUCT((DATABASE_Table[Development]=$B11)*(LEFT(TRIM(DATABASE_Table[Selling Status]),4)="PSPA"))} -> 14 | K11: {=SUMPRODUCT((DATABASE_Table[Development]=$B11)*(TRIM(DATABASE_Table[Selling Status])="DEED"))} -> 0 | L11: {=SUMPRODUCT((DATABASE_Table[Development]=$B11)*((TRIM(DATABASE_Table[Selling Status])="NOT FOR SALE")+(LEFT(TRIM(DATABASE_Table[Selling Status]),4)="UPON")))} -> 0 | M11: =IFERROR((I11+J11+K11)/(G11-L11),0) -> 0.29787234 | N11: =SUMIF(DATABASE_Table[Development],$B11,DATABASE_Table[Current Asking price( Total)])/1000000 -> 45.4265 | O11: {=SUMPRODUCT((DATABASE_Table[Development]=$B11)*(TRIM(DATABASE_Table[Selling Status])="DEED SIGNED")*DATABASE_Table[Sell price (RE Asset)])/1000000} -> 0 | Q11: Comparison | R11: % Sold | U11: Comparison | V11: GDV (€M) | X11: {=IFERROR(_xlfn.SWITCH(_xlfn.XLOOKUP($B11,DATABASE_Table[Development],DATABASE_Table[Local],"Center"),"Vilamoura","Vilamoura","Algarve","Algarve","North","North","Center"),"Center")} -> Vilamoura | Y11: {=_xlfn.IFS(G11=0,"—",M11>=0.999,"Sold Out",(I11+J11+K11)=0,"Coming Soon",TRUE,"Active")} -> Active
B12: Zestia | C12: =IFERROR(TRIM(_xlfn.XLOOKUP($B12,DATABASE_Table[Development],DATABASE_Table[Selling Status],"—")),"—") -> AVAILABLE | D12: {=IFERROR(INDEX(_xlfn._xlws.FILTER(DATABASE_Table[Location],(DATABASE_Table[Development]=$B12)*(DATABASE_Table[Location]<>"")),1),IFERROR(_xlfn.XLOOKUP($B12,DATABASE_Table[Development],DATABASE_Table[Local],"—"),"—"))} -> Vilamoura, Algarve | E12: {=IFERROR(INDEX(_xlfn._xlws.FILTER(DATABASE_Table[Typology],(DATABASE_Table[Development]=$B12)*(DATABASE_Table[Typology]<>"")),1),"—")} -> T2 | F12: {=IFERROR(INDEX(_xlfn._xlws.FILTER(DATABASE_Table[Delivery Expected],(DATABASE_Table[Development]=$B12)*(DATABASE_Table[Delivery Expected]<>"")),1),"—")} -> — | G12: =COUNTIF(DATABASE_Table[Development],$B12) -> 62 | H12: {=SUMPRODUCT((DATABASE_Table[Development]=$B12)*(TRIM(DATABASE_Table[Selling Status])="AVAILABLE"))} -> 55 | I12: {=SUMPRODUCT((DATABASE_Table[Development]=$B12)*((TRIM(DATABASE_Table[Selling Status])="RESERVED")+(TRIM(DATABASE_Table[Selling Status])="PRE-RESERVED")))} -> 0 | J12: {=SUMPRODUCT((DATABASE_Table[Development]=$B12)*(LEFT(TRIM(DATABASE_Table[Selling Status]),4)="PSPA"))} -> 7 | K12: {=SUMPRODUCT((DATABASE_Table[Development]=$B12)*(TRIM(DATABASE_Table[Selling Status])="DEED"))} -> 0 | L12: {=SUMPRODUCT((DATABASE_Table[Development]=$B12)*((TRIM(DATABASE_Table[Selling Status])="NOT FOR SALE")+(LEFT(TRIM(DATABASE_Table[Selling Status]),4)="UPON")))} -> 0 | M12: =IFERROR((I12+J12+K12)/(G12-L12),0) -> 0.11290323 | N12: =SUMIF(DATABASE_Table[Development],$B12,DATABASE_Table[Current Asking price( Total)])/1000000 -> 54.5 | O12: {=SUMPRODUCT((DATABASE_Table[Development]=$B12)*(TRIM(DATABASE_Table[Selling Status])="DEED SIGNED")*DATABASE_Table[Sell price (RE Asset)])/1000000} -> 0 | Q12: =$E$31 -> Vale Pisão Grand Park | R12: =M34 -> 0.25 | U12: =$E$31 -> Vale Pisão Grand Park | V12: =N34 -> 37.42 | X12: {=IFERROR(_xlfn.SWITCH(_xlfn.XLOOKUP($B12,DATABASE_Table[Development],DATABASE_Table[Local],"Center"),"Vilamoura","Vilamoura","Algarve","Algarve","North","North","Center"),"Center")} -> Vilamoura | Y12: {=_xlfn.IFS(G12=0,"—",M12>=0.999,"Sold Out",(I12+J12+K12)=0,"Coming Soon",TRUE,"Active")} -> Active
B13: VM PARQUE | C13: =IFERROR(TRIM(_xlfn.XLOOKUP($B13,DATABASE_Table[Development],DATABASE_Table[Selling Status],"—")),"—") -> DEED | D13: {=IFERROR(INDEX(_xlfn._xlws.FILTER(DATABASE_Table[Location],(DATABASE_Table[Development]=$B13)*(DATABASE_Table[Location]<>"")),1),IFERROR(_xlfn.XLOOKUP($B13,DATABASE_Table[Development],DATABASE_Table[Local],"—"),"—"))} -> Vilamoura | E13: {=IFERROR(INDEX(_xlfn._xlws.FILTER(DATABASE_Table[Typology],(DATABASE_Table[Development]=$B13)*(DATABASE_Table[Typology]<>"")),1),"—")} -> V2 | F13: {=IFERROR(INDEX(_xlfn._xlws.FILTER(DATABASE_Table[Delivery Expected],(DATABASE_Table[Development]=$B13)*(DATABASE_Table[Delivery Expected]<>"")),1),"—")} -> — | G13: =COUNTIF(DATABASE_Table[Development],$B13) -> 40 | H13: {=SUMPRODUCT((DATABASE_Table[Development]=$B13)*(TRIM(DATABASE_Table[Selling Status])="AVAILABLE"))} -> 0 | I13: {=SUMPRODUCT((DATABASE_Table[Development]=$B13)*((TRIM(DATABASE_Table[Selling Status])="RESERVED")+(TRIM(DATABASE_Table[Selling Status])="PRE-RESERVED")))} -> 0 | J13: {=SUMPRODUCT((DATABASE_Table[Development]=$B13)*(LEFT(TRIM(DATABASE_Table[Selling Status]),4)="PSPA"))} -> 0 | K13: {=SUMPRODUCT((DATABASE_Table[Development]=$B13)*(TRIM(DATABASE_Table[Selling Status])="DEED"))} -> 40 | L13: {=SUMPRODUCT((DATABASE_Table[Development]=$B13)*((TRIM(DATABASE_Table[Selling Status])="NOT FOR SALE")+(LEFT(TRIM(DATABASE_Table[Selling Status]),4)="UPON")))} -> 0 | M13: =IFERROR((I13+J13+K13)/(G13-L13),0) -> 1 | N13: =SUMIF(DATABASE_Table[Development],$B13,DATABASE_Table[Current Asking price( Total)])/1000000 -> 43.05197 | O13: {=SUMPRODUCT((DATABASE_Table[Development]=$B13)*(TRIM(DATABASE_Table[Selling Status])="DEED SIGNED")*DATABASE_Table[Sell price (RE Asset)])/1000000} -> 0 | Q13: =_xlfn.XLOOKUP($E$31,$B$7:$B$23,$X$7:$X$23)&" Avg" -> North Avg | R13: =IFERROR(AVERAGEIF($X$7:$X$23,_xlfn.XLOOKUP($E$31,$B$7:$B$23,$X$7:$X$23),$M$7:$M$23),0) -> 0.25 | U13: =_xlfn.XLOOKUP($E$31,$B$7:$B$23,$X$7:$X$23)&" Avg" -> North Avg | V13: =IFERROR(AVERAGEIF($X$7:$X$23,_xlfn.XLOOKUP($E$31,$B$7:$B$23,$X$7:$X$23),$N$7:$N$23),0) -> 37.42 | X13: {=IFERROR(_xlfn.SWITCH(_xlfn.XLOOKUP($B13,DATABASE_Table[Development],DATABASE_Table[Local],"Center"),"Vilamoura","Vilamoura","Algarve","Algarve","North","North","Center"),"Center")} -> Vilamoura | Y13: {=_xlfn.IFS(G13=0,"—",M13>=0.999,"Sold Out",(I13+J13+K13)=0,"Coming Soon",TRUE,"Active")} -> Sold Out
B14: Springs - At the Els | C14: =IFERROR(TRIM(_xlfn.XLOOKUP($B14,DATABASE_Table[Development],DATABASE_Table[Selling Status],"—")),"—") -> AVAILABLE | D14: {=IFERROR(INDEX(_xlfn._xlws.FILTER(DATABASE_Table[Location],(DATABASE_Table[Development]=$B14)*(DATABASE_Table[Location]<>"")),1),IFERROR(_xlfn.XLOOKUP($B14,DATABASE_Table[Development],DATABASE_Table[Local],"—"),"—"))} -> Vilamoura, Algarve | E14: {=IFERROR(INDEX(_xlfn._xlws.FILTER(DATABASE_Table[Typology],(DATABASE_Table[Development]=$B14)*(DATABASE_Table[Typology]<>"")),1),"—")} -> Plot | F14: {=IFERROR(INDEX(_xlfn._xlws.FILTER(DATABASE_Table[Delivery Expected],(DATABASE_Table[Development]=$B14)*(DATABASE_Table[Delivery Expected]<>"")),1),"—")} -> — | G14: =COUNTIF(DATABASE_Table[Development],$B14) -> 101 | H14: {=SUMPRODUCT((DATABASE_Table[Development]=$B14)*(TRIM(DATABASE_Table[Selling Status])="AVAILABLE"))} -> 92 | I14: {=SUMPRODUCT((DATABASE_Table[Development]=$B14)*((TRIM(DATABASE_Table[Selling Status])="RESERVED")+(TRIM(DATABASE_Table[Selling Status])="PRE-RESERVED")))} -> 3 | J14: {=SUMPRODUCT((DATABASE_Table[Development]=$B14)*(LEFT(TRIM(DATABASE_Table[Selling Status]),4)="PSPA"))} -> 6 | K14: {=SUMPRODUCT((DATABASE_Table[Development]=$B14)*(TRIM(DATABASE_Table[Selling Status])="DEED"))} -> 0 | L14: {=SUMPRODUCT((DATABASE_Table[Development]=$B14)*((TRIM(DATABASE_Table[Selling Status])="NOT FOR SALE")+(LEFT(TRIM(DATABASE_Table[Selling Status]),4)="UPON")))} -> 0 | M14: =IFERROR((I14+J14+K14)/(G14-L14),0) -> 0.089108911 | N14: =SUMIF(DATABASE_Table[Development],$B14,DATABASE_Table[Current Asking price( Total)])/1000000 -> 183.77 | O14: {=SUMPRODUCT((DATABASE_Table[Development]=$B14)*(TRIM(DATABASE_Table[Selling Status])="DEED SIGNED")*DATABASE_Table[Sell price (RE Asset)])/1000000} -> 0 | Q14: Portfolio Avg | R14: =$M$24 -> 0.36222628 | U14: Portfolio Avg | V14: =AVERAGE($N$7:$N$23) -> 77.328269 | X14: {=IFERROR(_xlfn.SWITCH(_xlfn.XLOOKUP($B14,DATABASE_Table[Development],DATABASE_Table[Local],"Center"),"Vilamoura","Vilamoura","Algarve","Algarve","North","North","Center"),"Center")} -> Vilamoura | Y14: {=_xlfn.IFS(G14=0,"—",M14>=0.999,"Sold Out",(I14+J14+K14)=0,"Coming Soon",TRUE,"Active")} -> Active
B15: Botanica | C15: =IFERROR(TRIM(_xlfn.XLOOKUP($B15,DATABASE_Table[Development],DATABASE_Table[Selling Status],"—")),"—") -> RESERVED | D15: {=IFERROR(INDEX(_xlfn._xlws.FILTER(DATABASE_Table[Location],(DATABASE_Table[Development]=$B15)*(DATABASE_Table[Location]<>"")),1),IFERROR(_xlfn.XLOOKUP($B15,DATABASE_Table[Development],DATABASE_Table[Local],"—"),"—"))} -> Vilamoura, Algarve | E15: {=IFERROR(INDEX(_xlfn._xlws.FILTER(DATABASE_Table[Typology],(DATABASE_Table[Development]=$B15)*(DATABASE_Table[Typology]<>"")),1),"—")} -> T2 | F15: {=IFERROR(INDEX(_xlfn._xlws.FILTER(DATABASE_Table[Delivery Expected],(DATABASE_Table[Development]=$B15)*(DATABASE_Table[Delivery Expected]<>"")),1),"—")} -> — | G15: =COUNTIF(DATABASE_Table[Development],$B15) -> 55 | H15: {=SUMPRODUCT((DATABASE_Table[Development]=$B15)*(TRIM(DATABASE_Table[Selling Status])="AVAILABLE"))} -> 33 | I15: {=SUMPRODUCT((DATABASE_Table[Development]=$B15)*((TRIM(DATABASE_Table[Selling Status])="RESERVED")+(TRIM(DATABASE_Table[Selling Status])="PRE-RESERVED")))} -> 15 | J15: {=SUMPRODUCT((DATABASE_Table[Development]=$B15)*(LEFT(TRIM(DATABASE_Table[Selling Status]),4)="PSPA"))} -> 7 | K15: {=SUMPRODUCT((DATABASE_Table[Development]=$B15)*(TRIM(DATABASE_Table[Selling Status])="DEED"))} -> 0 | L15: {=SUMPRODUCT((DATABASE_Table[Development]=$B15)*((TRIM(DATABASE_Table[Selling Status])="NOT FOR SALE")+(LEFT(TRIM(DATABASE_Table[Selling Status]),4)="UPON")))} -> 0 | M15: =IFERROR((I15+J15+K15)/(G15-L15),0) -> 0.4 | N15: =SUMIF(DATABASE_Table[Development],$B15,DATABASE_Table[Current Asking price( Total)])/1000000 -> 73.6235 | O15: {=SUMPRODUCT((DATABASE_Table[Development]=$B15)*(TRIM(DATABASE_Table[Selling Status])="DEED SIGNED")*DATABASE_Table[Sell price (RE Asset)])/1000000} -> 0 | X15: {=IFERROR(_xlfn.SWITCH(_xlfn.XLOOKUP($B15,DATABASE_Table[Development],DATABASE_Table[Local],"Center"),"Vilamoura","Vilamoura","Algarve","Algarve","North","North","Center"),"Center")} -> Vilamoura | Y15: {=_xlfn.IFS(G15=0,"—",M15>=0.999,"Sold Out",(I15+J15+K15)=0,"Coming Soon",TRUE,"Active")} -> Active
B16: The Uncommon | C16: =IFERROR(TRIM(_xlfn.XLOOKUP($B16,DATABASE_Table[Development],DATABASE_Table[Selling Status],"—")),"—") -> AVAILABLE | D16: {=IFERROR(INDEX(_xlfn._xlws.FILTER(DATABASE_Table[Location],(DATABASE_Table[Development]=$B16)*(DATABASE_Table[Location]<>"")),1),IFERROR(_xlfn.XLOOKUP($B16,DATABASE_Table[Development],DATABASE_Table[Local],"—"),"—"))} -> Vilamoura, Algarve | E16: {=IFERROR(INDEX(_xlfn._xlws.FILTER(DATABASE_Table[Typology],(DATABASE_Table[Development]=$B16)*(DATABASE_Table[Typology]<>"")),1),"—")} -> T3 | F16: {=IFERROR(INDEX(_xlfn._xlws.FILTER(DATABASE_Table[Delivery Expected],(DATABASE_Table[Development]=$B16)*(DATABASE_Table[Delivery Expected]<>"")),1),"—")} -> — | G16: =COUNTIF(DATABASE_Table[Development],$B16) -> 92 | H16: {=SUMPRODUCT((DATABASE_Table[Development]=$B16)*(TRIM(DATABASE_Table[Selling Status])="AVAILABLE"))} -> 89 | I16: {=SUMPRODUCT((DATABASE_Table[Development]=$B16)*((TRIM(DATABASE_Table[Selling Status])="RESERVED")+(TRIM(DATABASE_Table[Selling Status])="PRE-RESERVED")))} -> 1 | J16: {=SUMPRODUCT((DATABASE_Table[Development]=$B16)*(LEFT(TRIM(DATABASE_Table[Selling Status]),4)="PSPA"))} -> 2 | K16: {=SUMPRODUCT((DATABASE_Table[Development]=$B16)*(TRIM(DATABASE_Table[Selling Status])="DEED"))} -> 0 | L16: {=SUMPRODUCT((DATABASE_Table[Development]=$B16)*((TRIM(DATABASE_Table[Selling Status])="NOT FOR SALE")+(LEFT(TRIM(DATABASE_Table[Selling Status]),4)="UPON")))} -> 0 | M16: =IFERROR((I16+J16+K16)/(G16-L16),0) -> 0.032608696 | N16: =SUMIF(DATABASE_Table[Development],$B16,DATABASE_Table[Current Asking price( Total)])/1000000 -> 125.53 | O16: {=SUMPRODUCT((DATABASE_Table[Development]=$B16)*(TRIM(DATABASE_Table[Selling Status])="DEED SIGNED")*DATABASE_Table[Sell price (RE Asset)])/1000000} -> 0 | X16: {=IFERROR(_xlfn.SWITCH(_xlfn.XLOOKUP($B16,DATABASE_Table[Development],DATABASE_Table[Local],"Center"),"Vilamoura","Vilamoura","Algarve","Algarve","North","North","Center"),"Center")} -> Vilamoura | Y16: {=_xlfn.IFS(G16=0,"—",M16>=0.999,"Sold Out",(I16+J16+K16)=0,"Coming Soon",TRUE,"Active")} -> Active
B17: Rivus | C17: =IFERROR(TRIM(_xlfn.XLOOKUP($B17,DATABASE_Table[Development],DATABASE_Table[Selling Status],"—")),"—") -> AVAILABLE | D17: {=IFERROR(INDEX(_xlfn._xlws.FILTER(DATABASE_Table[Location],(DATABASE_Table[Development]=$B17)*(DATABASE_Table[Location]<>"")),1),IFERROR(_xlfn.XLOOKUP($B17,DATABASE_Table[Development],DATABASE_Table[Local],"—"),"—"))} -> Vilamoura, Algarve | E17: {=IFERROR(INDEX(_xlfn._xlws.FILTER(DATABASE_Table[Typology],(DATABASE_Table[Development]=$B17)*(DATABASE_Table[Typology]<>"")),1),"—")} -> T2 | F17: {=IFERROR(INDEX(_xlfn._xlws.FILTER(DATABASE_Table[Delivery Expected],(DATABASE_Table[Development]=$B17)*(DATABASE_Table[Delivery Expected]<>"")),1),"—")} -> — | G17: =COUNTIF(DATABASE_Table[Development],$B17) -> 39 | H17: {=SUMPRODUCT((DATABASE_Table[Development]=$B17)*(TRIM(DATABASE_Table[Selling Status])="AVAILABLE"))} -> 16 | I17: {=SUMPRODUCT((DATABASE_Table[Development]=$B17)*((TRIM(DATABASE_Table[Selling Status])="RESERVED")+(TRIM(DATABASE_Table[Selling Status])="PRE-RESERVED")))} -> 16 | J17: {=SUMPRODUCT((DATABASE_Table[Development]=$B17)*(LEFT(TRIM(DATABASE_Table[Selling Status]),4)="PSPA"))} -> 7 | K17: {=SUMPRODUCT((DATABASE_Table[Development]=$B17)*(TRIM(DATABASE_Table[Selling Status])="DEED"))} -> 0 | L17: {=SUMPRODUCT((DATABASE_Table[Development]=$B17)*((TRIM(DATABASE_Table[Selling Status])="NOT FOR SALE")+(LEFT(TRIM(DATABASE_Table[Selling Status]),4)="UPON")))} -> 0 | M17: =IFERROR((I17+J17+K17)/(G17-L17),0) -> 0.58974359 | N17: =SUMIF(DATABASE_Table[Development],$B17,DATABASE_Table[Current Asking price( Total)])/1000000 -> 35.56 | O17: {=SUMPRODUCT((DATABASE_Table[Development]=$B17)*(TRIM(DATABASE_Table[Selling Status])="DEED SIGNED")*DATABASE_Table[Sell price (RE Asset)])/1000000} -> 0 | X17: {=IFERROR(_xlfn.SWITCH(_xlfn.XLOOKUP($B17,DATABASE_Table[Development],DATABASE_Table[Local],"Center"),"Vilamoura","Vilamoura","Algarve","Algarve","North","North","Center"),"Center")} -> Vilamoura | Y17: {=_xlfn.IFS(G17=0,"—",M17>=0.999,"Sold Out",(I17+J17+K17)=0,"Coming Soon",TRUE,"Active")} -> Active
B18: Sutaya | C18: =IFERROR(TRIM(_xlfn.XLOOKUP($B18,DATABASE_Table[Development],DATABASE_Table[Selling Status],"—")),"—") -> AVAILABLE | D18: {=IFERROR(INDEX(_xlfn._xlws.FILTER(DATABASE_Table[Location],(DATABASE_Table[Development]=$B18)*(DATABASE_Table[Location]<>"")),1),IFERROR(_xlfn.XLOOKUP($B18,DATABASE_Table[Development],DATABASE_Table[Local],"—"),"—"))} -> Quinta do Lago, Algarve | E18: {=IFERROR(INDEX(_xlfn._xlws.FILTER(DATABASE_Table[Typology],(DATABASE_Table[Development]=$B18)*(DATABASE_Table[Typology]<>"")),1),"—")} -> T3 | F18: {=IFERROR(INDEX(_xlfn._xlws.FILTER(DATABASE_Table[Delivery Expected],(DATABASE_Table[Development]=$B18)*(DATABASE_Table[Delivery Expected]<>"")),1),"—")} -> TBD | G18: =COUNTIF(DATABASE_Table[Development],$B18) -> 16 | H18: {=SUMPRODUCT((DATABASE_Table[Development]=$B18)*(TRIM(DATABASE_Table[Selling Status])="AVAILABLE"))} -> 13 | I18: {=SUMPRODUCT((DATABASE_Table[Development]=$B18)*((TRIM(DATABASE_Table[Selling Status])="RESERVED")+(TRIM(DATABASE_Table[Selling Status])="PRE-RESERVED")))} -> 3 | J18: {=SUMPRODUCT((DATABASE_Table[Development]=$B18)*(LEFT(TRIM(DATABASE_Table[Selling Status]),4)="PSPA"))} -> 0 | K18: {=SUMPRODUCT((DATABASE_Table[Development]=$B18)*(TRIM(DATABASE_Table[Selling Status])="DEED"))} -> 0 | L18: {=SUMPRODUCT((DATABASE_Table[Development]=$B18)*((TRIM(DATABASE_Table[Selling Status])="NOT FOR SALE")+(LEFT(TRIM(DATABASE_Table[Selling Status]),4)="UPON")))} -> 0 | M18: =IFERROR((I18+J18+K18)/(G18-L18),0) -> 0.1875 | N18: =SUMIF(DATABASE_Table[Development],$B18,DATABASE_Table[Current Asking price( Total)])/1000000 -> 94.8 | O18: {=SUMPRODUCT((DATABASE_Table[Development]=$B18)*(TRIM(DATABASE_Table[Selling Status])="DEED SIGNED")*DATABASE_Table[Sell price (RE Asset)])/1000000} -> 0 | X18: {=IFERROR(_xlfn.SWITCH(_xlfn.XLOOKUP($B18,DATABASE_Table[Development],DATABASE_Table[Local],"Center"),"Vilamoura","Vilamoura","Algarve","Algarve","North","North","Center"),"Center")} -> Algarve | Y18: {=_xlfn.IFS(G18=0,"—",M18>=0.999,"Sold Out",(I18+J18+K18)=0,"Coming Soon",TRUE,"Active")} -> Active
B19: Azuya | C19: =IFERROR(TRIM(_xlfn.XLOOKUP($B19,DATABASE_Table[Development],DATABASE_Table[Selling Status],"—")),"—") -> AVAILABLE | D19: {=IFERROR(INDEX(_xlfn._xlws.FILTER(DATABASE_Table[Location],(DATABASE_Table[Development]=$B19)*(DATABASE_Table[Location]<>"")),1),IFERROR(_xlfn.XLOOKUP($B19,DATABASE_Table[Development],DATABASE_Table[Local],"—"),"—"))} -> Ancão, Algarve | E19: {=IFERROR(INDEX(_xlfn._xlws.FILTER(DATABASE_Table[Typology],(DATABASE_Table[Development]=$B19)*(DATABASE_Table[Typology]<>"")),1),"—")} -> T3 Duplex | F19: {=IFERROR(INDEX(_xlfn._xlws.FILTER(DATABASE_Table[Delivery Expected],(DATABASE_Table[Development]=$B19)*(DATABASE_Table[Delivery Expected]<>"")),1),"—")} -> 46752 | G19: =COUNTIF(DATABASE_Table[Development],$B19) -> 16 | H19: {=SUMPRODUCT((DATABASE_Table[Development]=$B19)*(TRIM(DATABASE_Table[Selling Status])="AVAILABLE"))} -> 14 | I19: {=SUMPRODUCT((DATABASE_Table[Development]=$B19)*((TRIM(DATABASE_Table[Selling Status])="RESERVED")+(TRIM(DATABASE_Table[Selling Status])="PRE-RESERVED")))} -> 1 | J19: {=SUMPRODUCT((DATABASE_Table[Development]=$B19)*(LEFT(TRIM(DATABASE_Table[Selling Status]),4)="PSPA"))} -> 1 | K19: {=SUMPRODUCT((DATABASE_Table[Development]=$B19)*(TRIM(DATABASE_Table[Selling Status])="DEED"))} -> 0 | L19: {=SUMPRODUCT((DATABASE_Table[Development]=$B19)*((TRIM(DATABASE_Table[Selling Status])="NOT FOR SALE")+(LEFT(TRIM(DATABASE_Table[Selling Status]),4)="UPON")))} -> 0 | M19: =IFERROR((I19+J19+K19)/(G19-L19),0) -> 0.125 | N19: =SUMIF(DATABASE_Table[Development],$B19,DATABASE_Table[Current Asking price( Total)])/1000000 -> 39.31 | O19: {=SUMPRODUCT((DATABASE_Table[Development]=$B19)*(TRIM(DATABASE_Table[Selling Status])="DEED SIGNED")*DATABASE_Table[Sell price (RE Asset)])/1000000} -> 0 | X19: {=IFERROR(_xlfn.SWITCH(_xlfn.XLOOKUP($B19,DATABASE_Table[Development],DATABASE_Table[Local],"Center"),"Vilamoura","Vilamoura","Algarve","Algarve","North","North","Center"),"Center")} -> Algarve | Y19: {=_xlfn.IFS(G19=0,"—",M19>=0.999,"Sold Out",(I19+J19+K19)=0,"Coming Soon",TRUE,"Active")} -> Active
B20: Palmares | C20: =IFERROR(TRIM(_xlfn.XLOOKUP($B20,DATABASE_Table[Development],DATABASE_Table[Selling Status],"—")),"—") -> AVAILABLE | D20: {=IFERROR(INDEX(_xlfn._xlws.FILTER(DATABASE_Table[Location],(DATABASE_Table[Development]=$B20)*(DATABASE_Table[Location]<>"")),1),IFERROR(_xlfn.XLOOKUP($B20,DATABASE_Table[Development],DATABASE_Table[Local],"—"),"—"))} -> Lagos, Algarve | E20: {=IFERROR(INDEX(_xlfn._xlws.FILTER(DATABASE_Table[Typology],(DATABASE_Table[Development]=$B20)*(DATABASE_Table[Typology]<>"")),1),"—")} -> Plot | F20: {=IFERROR(INDEX(_xlfn._xlws.FILTER(DATABASE_Table[Delivery Expected],(DATABASE_Table[Development]=$B20)*(DATABASE_Table[Delivery Expected]<>"")),1),"—")} -> 46843 | G20: =COUNTIF(DATABASE_Table[Development],$B20) -> 113 | H20: {=SUMPRODUCT((DATABASE_Table[Development]=$B20)*(TRIM(DATABASE_Table[Selling Status])="AVAILABLE"))} -> 71 | I20: {=SUMPRODUCT((DATABASE_Table[Development]=$B20)*((TRIM(DATABASE_Table[Selling Status])="RESERVED")+(TRIM(DATABASE_Table[Selling Status])="PRE-RESERVED")))} -> 6 | J20: {=SUMPRODUCT((DATABASE_Table[Development]=$B20)*(LEFT(TRIM(DATABASE_Table[Selling Status]),4)="PSPA"))} -> 33 | K20: {=SUMPRODUCT((DATABASE_Table[Development]=$B20)*(TRIM(DATABASE_Table[Selling Status])="DEED"))} -> 3 | L20: {=SUMPRODUCT((DATABASE_Table[Development]=$B20)*((TRIM(DATABASE_Table[Selling Status])="NOT FOR SALE")+(LEFT(TRIM(DATABASE_Table[Selling Status]),4)="UPON")))} -> 0 | M20: =IFERROR((I20+J20+K20)/(G20-L20),0) -> 0.37168142 | N20: =SUMIF(DATABASE_Table[Development],$B20,DATABASE_Table[Current Asking price( Total)])/1000000 -> 151.85725 | O20: {=SUMPRODUCT((DATABASE_Table[Development]=$B20)*(TRIM(DATABASE_Table[Selling Status])="DEED SIGNED")*DATABASE_Table[Sell price (RE Asset)])/1000000} -> 0 | X20: {=IFERROR(_xlfn.SWITCH(_xlfn.XLOOKUP($B20,DATABASE_Table[Development],DATABASE_Table[Local],"Center"),"Vilamoura","Vilamoura","Algarve","Algarve","North","North","Center"),"Center")} -> Algarve | Y20: {=_xlfn.IFS(G20=0,"—",M20>=0.999,"Sold Out",(I20+J20+K20)=0,"Coming Soon",TRUE,"Active")} -> Active
B21: Monte Rei | C21: =IFERROR(TRIM(_xlfn.XLOOKUP($B21,DATABASE_Table[Development],DATABASE_Table[Selling Status],"—")),"—") -> AVAILABLE | D21: {=IFERROR(INDEX(_xlfn._xlws.FILTER(DATABASE_Table[Location],(DATABASE_Table[Development]=$B21)*(DATABASE_Table[Location]<>"")),1),IFERROR(_xlfn.XLOOKUP($B21,DATABASE_Table[Development],DATABASE_Table[Local],"—"),"—"))} -> Vila Nova de Cacela, Algarve | E21: {=IFERROR(INDEX(_xlfn._xlws.FILTER(DATABASE_Table[Typology],(DATABASE_Table[Development]=$B21)*(DATABASE_Table[Typology]<>"")),1),"—")} -> T3 | F21: {=IFERROR(INDEX(_xlfn._xlws.FILTER(DATABASE_Table[Delivery Expected],(DATABASE_Table[Development]=$B21)*(DATABASE_Table[Delivery Expected]<>"")),1),"—")} -> TBD | G21: =COUNTIF(DATABASE_Table[Development],$B21) -> 99 | H21: {=SUMPRODUCT((DATABASE_Table[Development]=$B21)*(TRIM(DATABASE_Table[Selling Status])="AVAILABLE"))} -> 95 | I21: {=SUMPRODUCT((DATABASE_Table[Development]=$B21)*((TRIM(DATABASE_Table[Selling Status])="RESERVED")+(TRIM(DATABASE_Table[Selling Status])="PRE-RESERVED")))} -> 4 | J21: {=SUMPRODUCT((DATABASE_Table[Development]=$B21)*(LEFT(TRIM(DATABASE_Table[Selling Status]),4)="PSPA"))} -> 0 | K21: {=SUMPRODUCT((DATABASE_Table[Development]=$B21)*(TRIM(DATABASE_Table[Selling Status])="DEED"))} -> 0 | L21: {=SUMPRODUCT((DATABASE_Table[Development]=$B21)*((TRIM(DATABASE_Table[Selling Status])="NOT FOR SALE")+(LEFT(TRIM(DATABASE_Table[Selling Status]),4)="UPON")))} -> 0 | M21: =IFERROR((I21+J21+K21)/(G21-L21),0) -> 0.04040404 | N21: =SUMIF(DATABASE_Table[Development],$B21,DATABASE_Table[Current Asking price( Total)])/1000000 -> 106.695 | O21: {=SUMPRODUCT((DATABASE_Table[Development]=$B21)*(TRIM(DATABASE_Table[Selling Status])="DEED SIGNED")*DATABASE_Table[Sell price (RE Asset)])/1000000} -> 0 | X21: {=IFERROR(_xlfn.SWITCH(_xlfn.XLOOKUP($B21,DATABASE_Table[Development],DATABASE_Table[Local],"Center"),"Vilamoura","Vilamoura","Algarve","Algarve","North","North","Center"),"Center")} -> Algarve | Y21: {=_xlfn.IFS(G21=0,"—",M21>=0.999,"Sold Out",(I21+J21+K21)=0,"Coming Soon",TRUE,"Active")} -> Active
B22: Aroeira Collections | C22: =IFERROR(TRIM(_xlfn.XLOOKUP($B22,DATABASE_Table[Development],DATABASE_Table[Selling Status],"—")),"—") -> PSPA | D22: {=IFERROR(INDEX(_xlfn._xlws.FILTER(DATABASE_Table[Location],(DATABASE_Table[Development]=$B22)*(DATABASE_Table[Location]<>"")),1),IFERROR(_xlfn.XLOOKUP($B22,DATABASE_Table[Development],DATABASE_Table[Local],"—"),"—"))} -> Herdade da Aroeira, Almada | E22: {=IFERROR(INDEX(_xlfn._xlws.FILTER(DATABASE_Table[Typology],(DATABASE_Table[Development]=$B22)*(DATABASE_Table[Typology]<>"")),1),"—")} -> T2 | F22: {=IFERROR(INDEX(_xlfn._xlws.FILTER(DATABASE_Table[Delivery Expected],(DATABASE_Table[Development]=$B22)*(DATABASE_Table[Delivery Expected]<>"")),1),"—")} -> 47118 | G22: =COUNTIF(DATABASE_Table[Development],$B22) -> 230 | H22: {=SUMPRODUCT((DATABASE_Table[Development]=$B22)*(TRIM(DATABASE_Table[Selling Status])="AVAILABLE"))} -> 153 | I22: {=SUMPRODUCT((DATABASE_Table[Development]=$B22)*((TRIM(DATABASE_Table[Selling Status])="RESERVED")+(TRIM(DATABASE_Table[Selling Status])="PRE-RESERVED")))} -> 25 | J22: {=SUMPRODUCT((DATABASE_Table[Development]=$B22)*(LEFT(TRIM(DATABASE_Table[Selling Status]),4)="PSPA"))} -> 32 | K22: {=SUMPRODUCT((DATABASE_Table[Development]=$B22)*(TRIM(DATABASE_Table[Selling Status])="DEED"))} -> 0 | L22: {=SUMPRODUCT((DATABASE_Table[Development]=$B22)*((TRIM(DATABASE_Table[Selling Status])="NOT FOR SALE")+(LEFT(TRIM(DATABASE_Table[Selling Status]),4)="UPON")))} -> 20 | M22: =IFERROR((I22+J22+K22)/(G22-L22),0) -> 0.27142857 | N22: =SUMIF(DATABASE_Table[Development],$B22,DATABASE_Table[Current Asking price( Total)])/1000000 -> 191.455 | O22: {=SUMPRODUCT((DATABASE_Table[Development]=$B22)*(TRIM(DATABASE_Table[Selling Status])="DEED SIGNED")*DATABASE_Table[Sell price (RE Asset)])/1000000} -> 0 | X22: {=IFERROR(_xlfn.SWITCH(_xlfn.XLOOKUP($B22,DATABASE_Table[Development],DATABASE_Table[Local],"Center"),"Vilamoura","Vilamoura","Algarve","Algarve","North","North","Center"),"Center")} -> Center | Y22: {=_xlfn.IFS(G22=0,"—",M22>=0.999,"Sold Out",(I22+J22+K22)=0,"Coming Soon",TRUE,"Active")} -> Active
B23: Vale Pisão Grand Park | C23: =IFERROR(TRIM(_xlfn.XLOOKUP($B23,DATABASE_Table[Development],DATABASE_Table[Selling Status],"—")),"—") -> AVAILABLE | D23: {=IFERROR(INDEX(_xlfn._xlws.FILTER(DATABASE_Table[Location],(DATABASE_Table[Development]=$B23)*(DATABASE_Table[Location]<>"")),1),IFERROR(_xlfn.XLOOKUP($B23,DATABASE_Table[Development],DATABASE_Table[Local],"—"),"—"))} -> Santo Tirso, Porto | E23: {=IFERROR(INDEX(_xlfn._xlws.FILTER(DATABASE_Table[Typology],(DATABASE_Table[Development]=$B23)*(DATABASE_Table[Typology]<>"")),1),"—")} -> V3 | F23: {=IFERROR(INDEX(_xlfn._xlws.FILTER(DATABASE_Table[Delivery Expected],(DATABASE_Table[Development]=$B23)*(DATABASE_Table[Delivery Expected]<>"")),1),"—")} -> 47208 | G23: =COUNTIF(DATABASE_Table[Development],$B23) -> 45 | H23: {=SUMPRODUCT((DATABASE_Table[Development]=$B23)*(TRIM(DATABASE_Table[Selling Status])="AVAILABLE"))} -> 15 | I23: {=SUMPRODUCT((DATABASE_Table[Development]=$B23)*((TRIM(DATABASE_Table[Selling Status])="RESERVED")+(TRIM(DATABASE_Table[Selling Status])="PRE-RESERVED")))} -> 5 | J23: {=SUMPRODUCT((DATABASE_Table[Development]=$B23)*(LEFT(TRIM(DATABASE_Table[Selling Status]),4)="PSPA"))} -> 0 | K23: {=SUMPRODUCT((DATABASE_Table[Development]=$B23)*(TRIM(DATABASE_Table[Selling Status])="DEED"))} -> 0 | L23: {=SUMPRODUCT((DATABASE_Table[Development]=$B23)*((TRIM(DATABASE_Table[Selling Status])="NOT FOR SALE")+(LEFT(TRIM(DATABASE_Table[Selling Status]),4)="UPON")))} -> 25 | M23: =IFERROR((I23+J23+K23)/(G23-L23),0) -> 0.25 | N23: =SUMIF(DATABASE_Table[Development],$B23,DATABASE_Table[Current Asking price( Total)])/1000000 -> 37.42 | O23: {=SUMPRODUCT((DATABASE_Table[Development]=$B23)*(TRIM(DATABASE_Table[Selling Status])="DEED SIGNED")*DATABASE_Table[Sell price (RE Asset)])/1000000} -> 0 | X23: {=IFERROR(_xlfn.SWITCH(_xlfn.XLOOKUP($B23,DATABASE_Table[Development],DATABASE_Table[Local],"Center"),"Vilamoura","Vilamoura","Algarve","Algarve","North","North","Center"),"Center")} -> North | Y23: {=_xlfn.IFS(G23=0,"—",M23>=0.999,"Sold Out",(I23+J23+K23)=0,"Coming Soon",TRUE,"Active")} -> Active
B24: TOTAL | G24: =SUM(G7:G23) -> 1141 | H24: =SUM(H7:H23) -> 699 | I24: =SUM(I7:I23) -> 86 | J24: =SUM(J7:J23) -> 185 | K24: =SUM(K7:K23) -> 126 | L24: =SUM(L7:L23) -> 45 | M24: =IFERROR((I24+J24+K24)/(G24-L24),0) -> 0.36222628 | N24: =SUM(N7:N23) -> 1314.5806 | O24: =SUM(O7:O23) -> 0
C25: TOTAL UNITS | E25: AVAILABLE | G25: RESERVED | I25: UNDER CONTRACT | K25: DEEDED | M25: % SOLD | N25: GDV (€M)
C26: =G24 -> 1141 | E26: =H24 -> 699 | G26: =I24 -> 86 | I26: =J24 -> 185 | K26: =K24 -> 126 | M26: =M24 -> 0.36222628 | N26: =N24 -> 1314.5806
Q27: Available | R27: =E34 -> 15
Q28: Reserved | R28: =G34 -> 5
C29: PROJECT SPOTLIGHT | Q29: Under Contract | R29: =I34 -> 0
Q30: Deeded | R30: =K34 -> 0
C31: SELECT PROJECT → | E31: Vale Pisão Grand Park | G31: ="📍 "&IFERROR(_xlfn.XLOOKUP($E$31,$B$7:$B$23,$D$7:$D$23),"—")&" · "&IFERROR(_xlfn.XLOOKUP($E$31,$B$7:$B$23,$E$7:$E$23),"—")&" · "&IFERROR(_xlfn.XLOOKUP($E$31,$B$7:$B$23,$X$7:$X$23),"—")&" region · Status: "&IFERROR(_xlfn.XLOOKUP($E$31,$B$7:$B$23,$Y$7:$Y$23),"—")&" · Completion: "&IFERROR(TEXT(_xlfn.XLOOKUP($E$31,$B$7:$B$23,$F$7:$F$23),"dd-mmm-yyyy"),_xlfn.XLOOKUP($E$31,$B$7:$B$23,$F$7:$F$23)) -> 📍 Santo Tirso, Porto · V3 · North region · Status: Active · Completion: 31-mar-yyyy
C33: TOTAL UNITS | E33: AVAILABLE | G33: RESERVED | I33: UNDER CONTRACT | K33: DEEDED | M33: % SOLD | N33: GDV (€M)
C34: =_xlfn.XLOOKUP($E$31,$B$7:$B$23,$G$7:$G$23,0) -> 45 | E34: =_xlfn.XLOOKUP($E$31,$B$7:$B$23,$H$7:$H$23,0) -> 15 | G34: =_xlfn.XLOOKUP($E$31,$B$7:$B$23,$I$7:$I$23,0) -> 5 | I34: =_xlfn.XLOOKUP($E$31,$B$7:$B$23,$J$7:$J$23,0) -> 0 | K34: =_xlfn.XLOOKUP($E$31,$B$7:$B$23,$K$7:$K$23,0) -> 0 | M34: =_xlfn.XLOOKUP($E$31,$B$7:$B$23,$M$7:$M$23,0) -> 0.25 | N34: =_xlfn.XLOOKUP($E$31,$B$7:$B$23,$N$7:$N$23,0) -> 37.42
C36: ANALYTICS

Sheet DATABASE
A1: Commercial ID | B1: Local | C1: Unit PH | D1: Location | E1: Typology | F1: Area Total [sqm] | G1: Storage [sqm] | H1: Parking Lots [#] | I1: Pool [#] | J1: Balconies [sqm] | K1: Garden [sqm] | L1: Patio [sqm] | M1: Terrace [sqm] | N1: Rooftop [sqm] | O1: Interior | P1: Exterior | Q1: Selling Status | R1: Inicial Asking Price (€) (RE Asset) | S1: Inicial Asking Price (€) (Total) | T1: Current Asking price( Total) | U1: Vista membership | V1: FF&E | W1: Current Asking price (RE Asset) | X1: Total Discunt | Y1: Sell price (Total) | Z1: Sell price (RE Asset) | AA1: PSPA Date | AB1: Delivery Expected | AC1: Owner Comercial | AD1: Owner Asset Management | AE1: Website | AF1: Positioning Statement | AG1: Amenities | AH1: Key-Selling Points | AI1: Architecture | AJ1: Development
A2: MR - Linked Villas | B2: Algarve | C2: T | D2: Vila Nova de Cacela, Algarve | E2: T3 | F2: 422.36 | G2: 45.06 | J2: 131.68 | O2: 245.62 | Q2: AVAILABLE | R2: =DATABASE_Table[[#This Row],[Inicial Asking Price (€) (Total)]]-DATABASE_Table[[#This Row],[Vista membership]]-DATABASE_Table[[#This Row],[FF&E]] -> 1160000 | S2: 1160000 | T2: 1160000 | W2: =DATABASE_Table[[#This Row],[Current Asking price( Total)]]-DATABASE_Table[[#This Row],[Vista membership]]-DATABASE_Table[[#This Row],[FF&E]] -> 1160000 | Z2: =DATABASE_Table[[#This Row],[Sell price (Total)]]-DATABASE_Table[[#This Row],[FF&E]]-DATABASE_Table[[#This Row],[Vista membership]] -> 0 | AB2: TBD | AC2: Sandra Viegas | AE2: https://www.monte-rei.com/ | AF2: Monte Rei Golf & Country Club is an ultra-exclusive resort in the Eastern Algarve, combining a Jack Nicklaus Signature golf course, Michelin-star dining, and luxury residences within a serene private estate — offering one of Europe’s most refined golf and lifestyle experiences. | AG2: Golfe 18 buracos, Ténis, Ginásio, Health Center, Piscinas Exteriores, Spa e Concierge, Restaurantes | AH2: O Monte Rei Golf & Country Club é um resort de luxo exclusivo situado em mais de 400 hectares de paisagem intacta no sotavento algarvio, oferecendo a viajantes exigentes e amantes do golfe um refúgio de tranquilidade, sofisticação e privacidade. Com o seu campo de golfe assinatura Jack Nicklaus, gastronomia de excelência, serviço personalizado e um ambiente sereno entre a serra e o Atlântico, o Monte Rei posiciona-se como “o melhor lugar para viver e jogar” — um retiro privado e seguro, longe do ritmo agitado do quotidiano. | AI2: TBD | AJ2: Monte Rei
A3: Aroeira - HOUSES | B3: Center | C3: 01B | D3: Herdade da Aroeira, Almada | E3: T2 | F3: 167 | H3: 1 | M3: 31 | N3: 20 | O3: 116 | Q3: PSPA | R3: =DATABASE_Table[[#This Row],[Inicial Asking Price (€) (Total)]]-DATABASE_Table[[#This Row],[Vista membership]]-DATABASE_Table[[#This Row],[FF&E]] -> 925000 | S3: 925000 | T3: 925000 | V3: 0 | W3: =DATABASE_Table[[#This Row],[Current Asking price( Total)]]-DATABASE_Table[[#This Row],[Vista membership]]-DATABASE_Table[[#This Row],[FF&E]] -> 925000 | X3: 0 | Y3: 925000 | Z3: =DATABASE_Table[[#This Row],[Sell price (Total)]]-DATABASE_Table[[#This Row],[FF&E]]-DATABASE_Table[[#This Row],[Vista membership]] -> 925000 | AA3: 45904 | AB3: 47118 | AC3: João Gameiro | AD3: Miguel Ribeiro | AE3: https://www.aroeiracollections.com/ | AF3: Aroeira Collections by Missoni: Elegance inspired by iconic design, set beside the renowned PGA golf course — where luxury living meets the rhythm of the coast. | AG3: Gym, Spa, Condo Pool, Private Pools, Tennis & Padel Courts, Outdoor Areas, Smart Home Technology, Private Parking, Reception, Missoni Interiors, PGA Golf Course | AH3: Primeiro grande projeto com uma marca de lifestyle/moda em Portugal - Missoni; Localização de excelência dentro da Herdade da Aroeira, a 30' de Lisboa e 10' das melhores praias do país; Design com contributo de arquitetos de renome; Excelente oportunidade de investimento; Junto ao campo de golfe PGA Aroeira; Diversas amenities como: Piscina interior e exterior, campos de tenis e padel, ginásio, spa e restaurante. | AI3: Ana Costa, João Favila, Pedro Domingos | AJ3: Aroeira Collections
A4: Aroeira - HOUSES | B4: Center | C4: 02B | D4: Herdade da Aroeira, Almada | E4: T2 | F4: 194.4 | H4: 1 | M4: 27 | N4: 30 | O4: 137.4 | Q4: PSPA | R4: =DATABASE_Table[[#This Row],[Inicial Asking Price (€) (Total)]]-DATABASE_Table[[#This Row],[Vista membership]]-DATABASE_Table[[#This Row],[FF&E]] -> 1105000 | S4: 1105000 | T4: 1105000 | V4: 0 | W4: =DATABASE_Table[[#This Row],[Current Asking price( Total)]]-DATABASE_Table[[#This Row],[Vista membership]]-DATABASE_Table[[#This Row],[FF&E]] -> 1105000 | X4: 0 | Y4: 1105000 | Z4: =DATABASE_Table[[#This Row],[Sell price (Total)]]-DATABASE_Table[[#This Row],[FF&E]]-DATABASE_Table[[#This Row],[Vista membership]] -> 1105000 | AA4: 45996 | AB4: 47118 | AC4: João Gameiro | AD4: Miguel Ribeiro | AE4: https://www.aroeiracollections.com/ | AF4: Aroeira Collections by Missoni: Elegance inspired by iconic design, set beside the renowned PGA golf course — where luxury living meets the rhythm of the coast. | AG4: Gym, Spa, Condo Pool, Private Pools, Tennis & Padel Courts, Outdoor Areas, Smart Home Technology, Private Parking, Reception, Missoni Interiors, PGA Golf Course | AH4: Primeiro grande projeto com uma marca de lifestyle/moda em Portugal - Missoni; Localização de excelência dentro da Herdade da Aroeira, a 30' de Lisboa e 10' das melhores praias do país; Design com contributo de arquitetos de renome; Excelente oportunidade de investimento; Junto ao campo de golfe PGA Aroeira; Diversas amenities como: Piscina interior e exterior, campos de tenis e padel, ginásio, spa e restaurante. | AI4: Ana Costa, João Favila, Pedro Domingos | AJ4: Aroeira Collections
A5: Aroeira - HOUSES | B5: Center | C5: 03B | D5: Herdade da Aroeira, Almada | E5: T2 | F5: 167 | H5: 1 | M5: 31 | N5: 20 | O5: 116 | Q5: PSPA | R5: =DATABASE_Table[[#This Row],[Inicial Asking Price (€) (Total)]]-DATABASE_Table[[#This Row],[Vista membership]]-DATABASE_Table[[#This Row],[FF&E]] -> 925000 | S5: 925000 | T5: 925000 | V5: 0 | W5: =DATABASE_Table[[#This Row],[Current Asking price( Total)]]-DATABASE_Table[[#This Row],[Vista membership]]-DATABASE_Table[[#This Row],[FF&E]] -> 925000 | X5: 0 | Y5: 925000 | Z5: =DATABASE_Table[[#This Row],[Sell price (Total)]]-DATABASE_Table[[#This Row],[FF&E]]-DATABASE_Table[[#This Row],[Vista membership]] -> 925000 | AA5: 45967 | AB5: 47118 | AC5: João Gameiro | AD5: Miguel Ribeiro | AE5: https://www.aroeiracollections.com/ | AF5: Aroeira Collections by Missoni: Elegance inspired by iconic design, set beside the renowned PGA golf course — where luxury living meets the rhythm of the coast. | AG5: Gym, Spa, Condo Pool, Private Pools, Tennis & Padel Courts, Outdoor Areas, Smart Home Technology, Private Parking, Reception, Missoni Interiors, PGA Golf Course | AH5: Primeiro grande projeto com uma marca de lifestyle/moda em Portugal - Missoni; Localização de excelência dentro da Herdade da Aroeira, a 30' de Lisboa e 10' das melhores praias do país; Design com contributo de arquitetos de renome; Excelente oportunidade de investimento; Junto ao campo de golfe PGA Aroeira; Diversas amenities como: Piscina interior e exterior, campos de tenis e padel, ginásio, spa e restaurante. | AI5: Ana Costa, João Favila, Pedro Domingos | AJ5: Aroeira Collections
A6: Aroeira - HOUSES | B6: Center | C6: 04B | D6: Herdade da Aroeira, Almada | E6: T2 | F6: 167 | H6: 1 | M6: 31 | N6: 20 | O6: 116 | Q6: PSPA | R6: =DATABASE_Table[[#This Row],[Inicial Asking Price (€) (Total)]]-DATABASE_Table[[#This Row],[Vista membership]]-DATABASE_Table[[#This Row],[FF&E]] -> 925000 | S6: 925000 | T6: 925000 | V6: 0 | W6: =DATABASE_Table[[#This Row],[Current Asking price( Total)]]-DATABASE_Table[[#This Row],[Vista membership]]-DATABASE_Table[[#This Row],[FF&E]] -> 925000 | X6: 0 | Y6: 925000 | Z6: =DATABASE_Table[[#This Row],[Sell price (Total)]]-DATABASE_Table[[#This Row],[FF&E]]-DATABASE_Table[[#This Row],[Vista membership]] -> 925000 | AA6: 45968 | AB6: 47118 | AC6: João Gameiro | AD6: Miguel Ribeiro | AE6: https://www.aroeiracollections.com/ | AF6: Aroeira Collections by Missoni: Elegance inspired by iconic design, set beside the renowned PGA golf course — where luxury living meets the rhythm of the coast. | AG6: Gym, Spa, Condo Pool, Private Pools, Tennis & Padel Courts, Outdoor Areas, Smart Home Technology, Private Parking, Reception, Missoni Interiors, PGA Golf Course | AH6: Primeiro grande projeto com uma marca de lifestyle/moda em Portugal - Missoni; Localização de excelência dentro da Herdade da Aroeira, a 30' de Lisboa e 10' das melhores praias do país; Design com contributo de arquitetos de renome; Excelente oportunidade de investimento; Junto ao campo de golfe PGA Aroeira; Diversas amenities como: Piscina interior e exterior, campos de tenis e padel, ginásio, spa e restaurante. | AI6: Ana Costa, João Favila, Pedro Domingos | AJ6: Aroeira Collections
A7: Aroeira - HOTEL APARTMENTS | B7: Center | C7: 143A | D7: Herdade da Aroeira, Almada | E7: 1-BR | F7: 56.5 | H7: 1 | J7: 5 | O7: 51.5 | Q7: RESERVED | R7: =DATABASE_Table[[#This Row],[Inicial Asking Price (€) (Total)]]-DATABASE_Table[[#This Row],[Vista membership]]-DATABASE_Table[[#This Row],[FF&E]] -> 1915000 | S7: 1950000 | T7: 370000 | V7: 35000 | W7: =DATABASE_Table[[#This Row],[Current Asking price( Total)]]-DATABASE_Table[[#This Row],[Vista membership]]-DATABASE_Table[[#This Row],[FF&E]] -> 335000 | X7: 0 | Y7: 370000 | Z7: =DATABASE_Table[[#This Row],[Sell price (Total)]]-DATABASE_Table[[#This Row],[FF&E]]-DATABASE_Table[[#This Row],[Vista membership]] -> 335000 | AA7: 46104 | AB7: 47118 | AC7: João Gameiro | AD7: Miguel Ribeiro | AE7: https://www.aroeiracollections.com/ | AF7: Aroeira Collections by Missoni: Elegance inspired by iconic design, set beside the renowned PGA golf course — where luxury living meets the rhythm of the coast. | AG7: Gym, Spa, Condo Pool, Private Pools, Tennis & Padel Courts, Outdoor Areas, Smart Home Technology, Private Parking, Reception, Missoni Interiors, PGA Golf Course | AH7: Primeiro grande projeto com uma marca de lifestyle/moda em Portugal - Missoni; Localização de excelência dentro da Herdade da Aroeira, a 30' de Lisboa e 10' das melhores praias do país; Design com contributo de arquitetos de renome; Excelente oportunidade de investimento; Junto ao campo de golfe PGA Aroeira; Diversas amenities como: Piscina interior e exterior, campos de tenis e padel, ginásio, spa e restaurante. | AI7: Ana Costa, João Favila, Pedro Domingos | AJ7: Aroeira Collections
A8: Aroeira - HOTEL APARTMENTS | B8: Center | C8: 144A | D8: Herdade da Aroeira, Almada | E8: 1-BR | F8: 56.5 | H8: 1 | J8: 5 | O8: 51.5 | Q8: RESERVED | R8: =DATABASE_Table[[#This Row],[Inicial Asking Price (€) (Total)]]-DATABASE_Table[[#This Row],[Vista membership]]-DATABASE_Table[[#This Row],[FF&E]] -> 1715000 | S8: 1750000 | T8: 370000 | V8: 35000 | W8: =DATABASE_Table[[#This Row],[Current Asking price( Total)]]-DATABASE_Table[[#This Row],[Vista membership]]-DATABASE_Table[[#This Row],[FF&E]] -> 335000 | X8: 0 | Y8: 370000 | Z8: =DATABASE_Table[[#This Row],[Sell price (Total)]]-DATABASE_Table[[#This Row],[FF&E]]-DATABASE_Table[[#This Row],[Vista membership]] -> 335000 | AA8: 46052 | AB8: 47118 | AC8: João Gameiro | AD8: Miguel Ribeiro | AE8: https://www.aroeiracollections.com/ | AF8: Aroeira Collections by Missoni: Elegance inspired by iconic design, set beside the renowned PGA golf course — where luxury living meets the rhythm of the coast. | AG8: Gym, Spa, Condo Pool, Private Pools, Tennis & Padel Courts, Outdoor Areas, Smart Home Technology, Private Parking, Reception, Missoni Interiors, PGA Golf Course | AH8: Primeiro grande projeto com uma marca de lifestyle/moda em Portugal - Missoni; Localização de excelência dentro da Herdade da Aroeira, a 30' de Lisboa e 10' das melhores praias do país; Design com contributo de arquitetos de renome; Excelente oportunidade de investimento; Junto ao campo de golfe PGA Aroeira; Diversas amenities como: Piscina interior e exterior, campos de tenis e padel, ginásio, spa e restaurante. | AI8: Ana Costa, João Favila, Pedro Domingos | AJ8: Aroeira Collections
A9: Aroeira - HOTEL APARTMENTS | B9: Center | C9: 134A | D9: Herdade da Aroeira, Almada | E9: 1-BR | F9: 56.5 | H9: 1 | J9: 5 | O9: 51.5 | Q9: RESERVED | R9: =DATABASE_Table[[#This Row],[Inicial Asking Price (€) (Total)]]-DATABASE_Table[[#This Row],[Vista membership]]-DATABASE_Table[[#This Row],[FF&E]] -> 1715000 | S9: 1750000 | T9: 370000 | V9: 35000 | W9: =DATABASE_Table[[#This Row],[Current Asking price( Total)]]-DATABASE_Table[[#This Row],[Vista membership]]-DATABASE_Table[[#This Row],[FF&E]] -> 335000 | X9: 0.02 | Y9: 362600 | Z9: =DATABASE_Table[[#This Row],[Sell price (Total)]]-DATABASE_Table[[#This Row],[FF&E]]-DATABASE_Table[[#This Row],[Vista membership]] -> 327600 | AA9: 46118 | AB9: 47118 | AC9: João Gameiro | AD9: Miguel Ribeiro | AE9: https://www.aroeiracollections.com/ | AF9: Aroeira Collections by Missoni: Elegance inspired by iconic design, set beside the renowned PGA golf course — where luxury living meets the rhythm of the coast. | AG9: Gym, Spa, Condo Pool, Private Pools, Tennis & Padel Courts, Outdoor Areas, Smart Home Technology, Private Parking, Reception, Missoni Interiors, PGA Golf Course | AH9: Primeiro grande projeto com uma marca de lifestyle/moda em Portugal - Missoni; Localização de excelência dentro da Herdade da Aroeira, a 30' de Lisboa e 10' das melhores praias do país; Design com contributo de arquitetos de renome; Excelente oportunidade de investimento; Junto ao campo de golfe PGA Aroeira; Diversas amenities como: Piscina interior e exterior, campos de tenis e padel, ginásio, spa e restaurante. | AI9: Ana Costa, João Favila, Pedro Domingos | AJ9: Aroeira Collections
A10: Aroeira - HOTEL APARTMENTS | B10: Center | C10: 137A | D10: Herdade da Aroeira, Almada | E10: 1-BR | F10: 56.5 | H10: 1 | J10: 5 | O10: 51.5 | Q10: RESERVED | R10: =DATABASE_Table[[#This Row],[Inicial Asking Price (€) (Total)]]-DATABASE_Table[[#This Row],[Vista membership]]-DATABASE_Table[[#This Row],[FF&E]] -> 1815000 | S10: 1850000 | T10: 370000 | V10: 35000 | W10: =DATABASE_Table[[#This Row],[Current Asking price( Total)]]-DATABASE_Table[[#This Row],[Vista membership]]-DATABASE_Table[[#This Row],[FF&E]] -> 335000 | X10: 0.02 | Y10: 362600 | Z10: =DATABASE_Table[[#This Row],[Sell price (Total)]]-DATABASE_Table[[#This Row],[FF&E]]-DATABASE_Table[[#This Row],[Vista membership]] -> 327600 | AA10: 46118 | AB10: 47118 | AC10: João Gameiro | AD10: Miguel Ribeiro | AE10: https://www.aroeiracollections.com/ | AF10: Aroeira Collections by Missoni: Elegance inspired by iconic design, set beside the renowned PGA golf course — where luxury living meets the rhythm of the coast. | AG10: Gym, Spa, Condo Pool, Private Pools, Tennis & Padel Courts, Outdoor Areas, Smart Home Technology, Private Parking, Reception, Missoni Interiors, PGA Golf Course | AH10: Primeiro grande projeto com uma marca de lifestyle/moda em Portugal - Missoni; Localização de excelência dentro da Herdade da Aroeira, a 30' de Lisboa e 10' das melhores praias do país; Design com contributo de arquitetos de renome; Excelente oportunidade de investimento; Junto ao campo de golfe PGA Aroeira; Diversas amenities como: Piscina interior e exterior, campos de tenis e padel, ginásio, spa e restaurante. | AI10: Ana Costa, João Favila, Pedro Domingos | AJ10: Aroeira Collections
A11: Aroeira - HOTEL APARTMENTS | B11: Center | C11: 236A | D11: Herdade da Aroeira, Almada | E11: 1-BR | F11: 56.5 | H11: 1 | J11: 5 | O11: 51.5 | Q11: PRE-RESERVED | R11: =DATABASE_Table[[#This Row],[Inicial Asking Price (€) (Total)]]-DATABASE_Table[[#This Row],[Vista membership]]-DATABASE_Table[[#This Row],[FF&E]] -> 1915000 | S11: 1950000 | T11: 390000 | V11: 35000 | W11: =DATABASE_Table[[#This Row],[Current Asking price( Total)]]-DATABASE_Table[[#This Row],[Vista membership]]-DATABASE_Table[[#This Row],[FF&E]] -> 355000 | X11: 0 | Y11: 390000 | Z11: =DATABASE_Table[[#This Row],[Sell price (Total)]]-DATABASE_Table[[#This Row],[FF&E]]-DATABASE_Table[[#This Row],[Vista membership]] -> 355000 | AA11: 46142 | AB11: 47118 | AC11: João Gameiro | AD11: Miguel Ribeiro | AE11: https://www.aroeiracollections.com/ | AF11: Aroeira Collections by Missoni: Elegance inspired by iconic design, set beside the renowned PGA golf course — where luxury living meets the rhythm of the coast. | AG11: Gym, Spa, Condo Pool, Private Pools, Tennis & Padel Courts, Outdoor Areas, Smart Home Technology, Private Parking, Reception, Missoni Interiors, PGA Golf Course | AH11: Primeiro grande projeto com uma marca de lifestyle/moda em Portugal - Missoni; Localização de excelência dentro da Herdade da Aroeira, a 30' de Lisboa e 10' das melhores praias do país; Design com contributo de arquitetos de renome; Excelente oportunidade de investimento; Junto ao campo de golfe PGA Aroeira; Diversas amenities como: Piscina interior e exterior, campos de tenis e padel, ginásio, spa e restaurante. | AI11: Ana Costa, João Favila, Pedro Domingos | AJ11: Aroeira Collections
A12: Aroeira - HOTEL APARTMENTS | B12: Center | C12: 139A | D12: Herdade da Aroeira, Almada | E12: 1-BR | F12: 60.2 | H12: 1 | J12: 3.9 | O12: 56.3 | Q12: RESERVED | R12: =DATABASE_Table[[#This Row],[Inicial Asking Price (€) (Total)]]-DATABASE_Table[[#This Row],[Vista membership]]-DATABASE_Table[[#This Row],[FF&E]] -> 2065000 | S12: 2100000 | T12: 390000 | V12: 35000 | W12: =DATABASE_Table[[#This Row],[Current Asking price( Total)]]-DATABASE_Table[[#This Row],[Vista membership]]-DATABASE_Table[[#This Row],[FF&E]] -> 355000 | X12: 0 | Y12: 390000 | Z12: =DATABASE_Table[[#This Row],[Sell price (Total)]]-DATABASE_Table[[#This Row],[FF&E]]-DATABASE_Table[[#This Row],[Vista membership]] -> 355000 | AA12: 46098 | AB12: 47118 | AC12: João Gameiro | AD12: Miguel Ribeiro | AE12: https://www.aroeiracollections.com/ | AF12: Aroeira Collections by Missoni: Elegance inspired by iconic design, set beside the renowned PGA golf course — where luxury living meets the rhythm of the coast. | AG12: Gym, Spa, Condo Pool, Private Pools, Tennis & Padel Courts, Outdoor Areas, Smart Home Technology, Private Parking, Reception, Missoni Interiors, PGA Golf Course | AH12: Primeiro grande projeto com uma marca de lifestyle/moda em Portugal - Missoni; Localização de excelência dentro da Herdade da Aroeira, a 30' de Lisboa e 10' das melhores praias do país; Design com contributo de arquitetos de renome; Excelente oportunidade de investimento; Junto ao campo de golfe PGA Aroeira; Diversas amenities como: Piscina interior e exterior, campos de tenis e padel, ginásio, spa e restaurante. | AI12: Ana Costa, João Favila, Pedro Domingos | AJ12: Aroeira Collections
A13: Aroeira - HOTEL APARTMENTS | B13: Center | C13: 140A | D13: Herdade da Aroeira, Almada | E13: 1-BR | F13: 60.2 | H13: 1 | J13: 3.9 | O13: 56.3 | Q13: RESERVED | R13: =DATABASE_Table[[#This Row],[Inicial Asking Price (€) (Total)]]-DATABASE_Table[[#This Row],[Vista membership]]-DATABASE_Table[[#This Row],[FF&E]] -> 2865000 | S13: 2900000 | T13: 390000 | V13: 35000 | W13: =DATABASE_Table[[#This Row],[Current Asking price( Total)]]-DATABASE_Table[[#This Row],[Vista membership]]-DATABASE_Table[[#This Row],[FF&E]] -> 355000 | X13: 0 | Y13: 390000 | Z13: =DATABASE_Table[[#This Row],[Sell price (Total)]]-DATABASE_Table[[#This Row],[FF&E]]-DATABASE_Table[[#This Row],[Vista membership]] -> 355000 | AA13: 46085 | AB13: 47118 | AC13: João Gameiro | AD13: Miguel Ribeiro | AE13: https://www.aroeiracollections.com/ | AF13: Aroeira Collections by Missoni: Elegance inspired by iconic design, set beside the renowned PGA golf course — where luxury living meets the rhythm of the coast. | AG13: Gym, Spa, Condo Pool, Private Pools, Tennis & Padel Courts, Outdoor Areas, Smart Home Technology, Private Parking, Reception, Missoni Interiors, PGA Golf Course | AH13: Primeiro grande projeto com uma marca de lifestyle/moda em Portugal - Missoni; Localização de excelência dentro da Herdade da Aroeira, a 30' de Lisboa e 10' das melhores praias do país; Design com contributo de arquitetos de renome; Excelente oportunidade de investimento; Junto ao campo de golfe PGA Aroeira; Diversas amenities como: Piscina interior e exterior, campos de tenis e padel, ginásio, spa e restaurante. | AI13: Ana Costa, João Favila, Pedro Domingos | AJ13: Aroeira Collections
A14: Aroeira - HOTEL APARTMENTS | B14: Center | C14: 141A | D14: Herdade da Aroeira, Almada | E14: 1-BR | F14: 60.2 | H14: 1 | J14: 3.9 | O14: 56.3 | Q14: RESERVED | R14: =DATABASE_Table[[#This Row],[Inicial Asking Price (€) (Total)]]-DATABASE_Table[[#This Row],[Vista membership]]-DATABASE_Table[[#This Row],[FF&E]] -> 2265000 | S14: 2300000 | T14: 390000 | V14: 35000 | W14: =DATABASE_Table[[#This Row],[Current Asking price( Total)]]-DATABASE_Table[[#This Row],[Vista membership]]-DATABASE_Table[[#This Row],[FF&E]] -> 355000 | X14: 0 | Y14: 390000 | Z14: =DATABASE_Table[[#This Row],[Sell price (Total)]]-DATABASE_Table[[#This Row],[FF&E]]-DATABASE_Table[[#This Row],[Vista membership]] -> 355000 | AA14: 46129 | AB14: 47118 | AC14: João Gameiro | AD14: Miguel Ribeiro | AE14: https://www.aroeiracollections.com/ | AF14: Aroeira Collections by Missoni: Elegance inspired by iconic design, set beside the renowned PGA golf course — where luxury living meets the rhythm of the coast. | AG14: Gym, Spa, Condo Pool, Private Pools, Tennis & Padel Courts, Outdoor Areas, Smart Home Technology, Private Parking, Reception, Missoni Interiors, PGA Golf Course | AH14: Primeiro grande projeto com uma marca de lifestyle/moda em Portugal - Missoni; Localização de excelência dentro da Herdade da Aroeira, a 30' de Lisboa e 10' das melhores praias do país; Design com contributo de arquitetos de renome; Excelente oportunidade de investimento; Junto ao campo de golfe PGA Aroeira; Diversas amenities como: Piscina interior e exterior, campos de tenis e padel, ginásio, spa e restaurante. | AI14: Ana Costa, João Favila, Pedro Domingos | AJ14: Aroeira Collections
A15: Aroeira - HOTEL APARTMENTS | B15: Center | C15: 142A | D15: Herdade da Aroeira, Almada | E15: 1-BR | F15: 60.2 | H15: 1 | J15: 3.9 | O15: 56.3 | Q15: RESERVED | R15: =DATABASE_Table[[#This Row],[Inicial Asking Price (€) (Total)]]-DATABASE_Table[[#This Row],[Vista membership]]-DATABASE_Table[[#This Row],[FF&E]] -> 2265000 | S15: 2300000 | T15: 390000 | V15: 35000 | W15: =DATABASE_Table[[#This Row],[Current Asking price( Total)]]-DATABASE_Table[[#This Row],[Vista membership]]-DATABASE_Table[[#This Row],[FF&E]] -> 355000 | X15: 0 | Y15: 390000 | Z15: =DATABASE_Table[[#This Row],[Sell price (Total)]]-DATABASE_Table[[#This Row],[FF&E]]-DATABASE_Table[[#This Row],[Vista membership]] -> 355000 | AA15: 46129 | AB15: 47118 | AC15: João Gameiro | AD15: Miguel Ribeiro | AE15: https://www.aroeiracollections.com/ | AF15: Aroeira Collections by Missoni: Elegance inspired by iconic design, set beside the renowned PGA golf course — where luxury living meets the rhythm of the coast. | AG15: Gym, Spa, Condo Pool, Private Pools, Tennis & Padel Courts, Outdoor Areas, Smart Home Technology, Private Parking, Reception, Missoni Interiors, PGA Golf Course | AH15: Primeiro grande projeto com uma marca de lifestyle/moda em Portugal - Missoni; Localização de excelência dentro da Herdade da Aroeira, a 30' de Lisboa e 10' das melhores praias do país; Design com contributo de arquitetos de renome; Excelente oportunidade de investimento; Junto ao campo de golfe PGA Aroeira; Diversas amenities como: Piscina interior e exterior, campos de tenis e padel, ginásio, spa e restaurante. | AI15: Ana Costa, João Favila, Pedro Domingos | AJ15: Aroeira Collections
A16: Aroeira - HOTEL APARTMENTS | B16: Center | C16: 235A | D16: Herdade da Aroeira, Almada | E16: 1-BR | F16: 56.5 | H16: 1 | J16: 5 | O16: 51.5 | Q16: RESERVED | R16: =DATABASE_Table[[#This Row],[Inicial Asking Price (€) (Total)]]-DATABASE_Table[[#This Row],[Vista membership]]-DATABASE_Table[[#This Row],[FF&E]] -> 2365000 | S16: 2400000 | T16: 390000 | V16: 35000 | W16: =DATABASE_Table[[#This Row],[Current Asking price( Total)]]-DATABASE_Table[[#This Row],[Vista membership]]-DATABASE_Table[[#This Row],[FF&E]] -> 355000 | X16: 0 | Y16: 390000 | Z16: =DATABASE_Table[[#This Row],[Sell price (Total)]]-DATABASE_Table[[#This Row],[FF&E]]-DATABASE_Table[[#This Row],[Vista membership]] -> 355000 | AA16: 46126 | AB16: 47118 | AC16: João Gameiro | AD16: Miguel Ribeiro | AE16: https://www.aroeiracollections.com/ | AF16: Aroeira Collections by Missoni: Elegance inspired by iconic design, set beside the renowned PGA golf course — where luxury living meets the rhythm of the coast. | AG16: Gym, Spa, Condo Pool, Private Pools, Tennis & Padel Courts, Outdoor Areas, Smart Home Technology, Private Parking, Reception, Missoni Interiors, PGA Golf Course | AH16: Primeiro grande projeto com uma marca de lifestyle/moda em Portugal - Missoni; Localização de excelência dentro da Herdade da Aroeira, a 30' de Lisboa e 10' das melhores praias do país; Design com contributo de arquitetos de renome; Excelente oportunidade de investimento; Junto ao campo de golfe PGA Aroeira; Diversas amenities como: Piscina interior e exterior, campos de tenis e padel, ginásio, spa e restaurante. | AI16: Ana Costa, João Favila, Pedro Domingos | AJ16: Aroeira Collections
A17: Aroeira - HOTEL APARTMENTS | B17: Center | C17: 138A | D17: Herdade da Aroeira, Almada | E17: 1-BR | F17: 60.2 | H17: 1 | J17: 3.9 | O17: 56.3 | Q17: AVAILABLE | R17: =DATABASE_Table[[#This Row],[Inicial Asking Price (€) (Total)]]-DATABASE_Table[[#This Row],[Vista membership]]-DATABASE_Table[[#This Row],[FF&E]] -> 2665000 | S17: 2700000 | T17: 390000 | V17: 35000 | W17: =DATABASE_Table[[#This Row],[Current Asking price( Total)]]-DATABASE_Table[[#This Row],[Vista membership]]-DATABASE_Table[[#This Row],[FF&E]] -> 355000 | Z17: =DATABASE_Table[[#This Row],[Sell price (Total)]]-DATABASE_Table[[#This Row],[FF&E]]-DATABASE_Table[[#This Row],[Vista membership]] -> -35000 | AB17: 47118 | AC17: João Gameiro | AD17: Miguel Ribeiro | AE17: https://www.aroeiracollections.com/ | AF17: Aroeira Collections by Missoni: Elegance inspired by iconic design, set beside the renowned PGA golf course — where luxury living meets the rhythm of the coast. | AG17: Gym, Spa, Condo Pool, Private Pools, Tennis & Padel Courts, Outdoor Areas, Smart Home Technology, Private Parking, Reception, Missoni Interiors, PGA Golf Course | AH17: Primeiro grande projeto com uma marca de lifestyle/moda em Portugal - Missoni; Localização de excelência dentro da Herdade da Aroeira, a 30' de Lisboa e 10' das melhores praias do país; Design com contributo de arquitetos de renome; Excelente oportunidade de investimento; Junto ao campo de golfe PGA Aroeira; Diversas amenities como: Piscina interior e exterior, campos de tenis e padel, ginásio, spa e restaurante. | AI17: Ana Costa, João Favila, Pedro Domingos | AJ17: Aroeira Collections
A18: Aroeira - HOTEL APARTMENTS | B18: Center | C18: 234A | D18: Herdade da Aroeira, Almada | E18: 1-BR | F18: 56.5 | H18: 1 | J18: 5 | O18: 51.5 | Q18: AVAILABLE | R18: =DATABASE_Table[[#This Row],[Inicial Asking Price (€) (Total)]]-DATABASE_Table[[#This Row],[Vista membership]]-DATABASE_Table[[#This Row],[FF&E]] -> 2575000 | S18: 2610000 | T18: 390000 | V18: 35000 | W18: =DATABASE_Table[[#This Row],[Current Asking price( Total)]]-DATABASE_Table[[#This Row],[Vista membership]]-DATABASE_Table[[#This Row],[FF&E]] -> 355000 | Z18: =DATABASE_Table[[#This Row],[Sell price (Total)]]-DATABASE_Table[[#This Row],[FF&E]]-DATABASE_Table[[#This Row],[Vista membership]] -> -35000 | AB18: 47118 | AC18: João Gameiro | AD18: Miguel Ribeiro | AE18: https://www.aroeiracollections.com/ | AF18: Aroeira Collections by Missoni: Elegance inspired by iconic design, set beside the renowned PGA golf course — where luxury living meets the rhythm of the coast. | AG18: Gym, Spa, Condo Pool, Private Pools, Tennis & Padel Courts, Outdoor Areas, Smart Home Technology, Private Parking, Reception, Missoni Interiors, PGA Golf Course | AH18: Primeiro grande projeto com uma marca de lifestyle/moda em Portugal - Missoni; Localização de excelência dentro da Herdade da Aroeira, a 30' de Lisboa e 10' das melhores praias do país; Design com contributo de arquitetos de renome; Excelente oportunidade de investimento; Junto ao campo de golfe PGA Aroeira; Diversas amenities como: Piscina interior e exterior, campos de tenis e padel, ginásio, spa e restaurante. | AI18: Ana Costa, João Favila, Pedro Domingos | AJ18: Aroeira Collections
A19: Aroeira - HOTEL APARTMENTS | B19: Center | C19: 237A | D19: Herdade da Aroeira, Almada | E19: 1-BR | F19: 56.5 | H19: 1 | J19: 5 | O19: 51.5 | Q19: AVAILABLE | R19: =DATABASE_Table[[#This Row],[Inicial Asking Price (€) (Total)]]-DATABASE_Table[[#This Row],[Vista membership]]-DATABASE_Table[[#This Row],[FF&E]] -> 1305000 | S19: 1340000 | T19: 390000 | V19: 35000 | W19: =DATABASE_Table[[#This Row],[Current Asking price( Total)]]-DATABASE_Table[[#This Row],[Vista membership]]-DATABASE_Table[[#This Row],[FF&E]] -> 355000 | Z19: =DATABASE_Table[[#This Row],[Sell price (Total)]]-DATABASE_Table[[#This Row],[FF&E]]-DATABASE_Table[[#This Row],[Vista membership]] -> -35000 | AB19: 47118 | AC19: João Gameiro | AD19: Miguel Ribeiro | AE19: https://www.aroeiracollections.com/ | AF19: Aroeira Collections by Missoni: Elegance inspired by iconic design, set beside the renowned PGA golf course — where luxury living meets the rhythm of the coast. | AG19: Gym, Spa, Condo Pool, Private Pools, Tennis & Padel Courts, Outdoor Areas, Smart Home Technology, Private Parking, Reception, Missoni Interiors, PGA Golf Course | AH19: Primeiro grande projeto com uma marca de lifestyle/moda em Portugal - Missoni; Localização de excelência dentro da Herdade da Aroeira, a 30' de Lisboa e 10' das melhores praias do país; Design com contributo de arquitetos de renome; Excelente oportunidade de investimento; Junto ao campo de golfe PGA Aroeira; Diversas amenities como: Piscina interior e exterior, campos de tenis e padel, ginásio, spa e restaurante. | AI19: Ana Costa, João Favila, Pedro Domingos | AJ19: Aroeira Collections
A20: Aroeira - HOTEL APARTMENTS | B20: Center | C20: 243A | D20: Herdade da Aroeira, Almada | E20: 1-BR | F20: 56.5 | H20: 1 | J20: 5 | O20: 51.5 | Q20: AVAILABLE | R20: =DATABASE_Table[[#This Row],[Inicial Asking Price (€) (Total)]]-DATABASE_Table[[#This Row],[Vista membership]]-DATABASE_Table[[#This Row],[FF&E]] -> 715000 | S20: 750000 | T20: 390000 | V20: 35000 | W20: =DATABASE_Table[[#This Row],[Current Asking price( Total)]]-DATABASE_Table[[#This Row],[Vista membership]]-DATABASE_Table[[#This Row],[FF&E]] -> 355000 | Z20: =DATABASE_Table[[#This Row],[Sell price (Total)]]-DATABASE_Table[[#This Row],[FF&E]]-DATABASE_Table[[#This Row],[Vista membership]] -> -35000 | AB20: 47118 | AC20: João Gameiro | AD20: Miguel Ribeiro | AE20: https://www.aroeiracollections.com/ | AF20: Aroeira Collections by Missoni: Elegance inspired by iconic design, set beside the renowned PGA golf course — where luxury living meets the rhythm of the coast. | AG20: Gym, Spa, Condo Pool, Private Pools, Tennis & Padel Courts, Outdoor Areas, Smart Home Technology, Private Parking, Reception, Missoni Interiors, PGA Golf Course | AH20: Primeiro grande projeto com uma marca de lifestyle/moda em Portugal - Missoni; Localização de excelência dentro da Herdade da Aroeira, a 30' de Lisboa e 10' das melhores praias do país; Design com contributo de arquitetos de renome; Excelente oportunidade de investimento; Junto ao campo de golfe PGA Aroeira; Diversas amenities como: Piscina interior e exterior, campos de tenis e padel, ginásio, spa e restaurante. | AI20: Ana Costa, João Favila, Pedro Domingos | AJ20: Aroeira Collections
A21: Aroeira - HOTEL APARTMENTS | B21: Center | C21: 244A | D21: Herdade da Aroeira, Almada | E21: 1-BR | F21: 56.5 | H21: 1 | J21: 5 | O21: 51.5 | Q21: AVAILABLE | R21: =DATABASE_Table[[#This Row],[Inicial Asking Price (€) (Total)]]-DATABASE_Table[[#This Row],[Vista membership]]-DATABASE_Table[[#This Row],[FF&E]] -> 865000 | S21: 900000 | T21: 390000 | V21: 35000 | W21: =DATABASE_Table[[#This Row],[Current Asking price( Total)]]-DATABASE_Table[[#This Row],[Vista membership]]-DATABASE_Table[[#This Row],[FF&E]] -> 355000 | Z21: =DATABASE_Table[[#This Row],[Sell price (Total)]]-DATABASE_Table[[#This Row],[FF&E]]-DATABASE_Table[[#This Row],[Vista membership]] -> -35000 | AB21: 47118 | AC21: João Gameiro | AD21: Miguel Ribeiro | AE21: https://www.aroeiracollections.com/ | AF21: Aroeira Collections by Missoni: Elegance inspired by iconic design, set beside the renowned PGA golf course — where luxury living meets the rhythm of the coast. | AG21: Gym, Spa, Condo Pool, Private Pools, Tennis & Padel Courts, Outdoor Areas, Smart Home Technology, Private Parking, Reception, Missoni Interiors, PGA Golf Course | AH21: Primeiro grande projeto com uma marca de lifestyle/moda em Portugal - Missoni; Localização de excelência dentro da Herdade da Aroeira, a 30' de Lisboa e 10' das melhores praias do país; Design com contributo de arquitetos de renome; Excelente oportunidade de investimento; Junto ao campo de golfe PGA Aroeira; Diversas amenities como: Piscina interior e exterior, campos de tenis e padel, ginásio, spa e restaurante. | AI21: Ana Costa, João Favila, Pedro Domingos | AJ21: Aroeira Collections
A22: Aroeira - HOTEL APARTMENTS | B22: Center | C22: 245A | D22: Herdade da Aroeira, Almada | E22: 1-BR | F22: 56.5 | H22: 1 | J22: 5 | O22: 51.5 | Q22: AVAILABLE | R22: =DATABASE_Table[[#This Row],[Inicial Asking Price (€) (Total)]]-DATABASE_Table[[#This Row],[Vista membership]]-DATABASE_Table[[#This Row],[FF&E]] -> 965000 | S22: 1000000 | T22: 390000 | V22: 35000 | W22: =DATABASE_Table[[#This Row],[Current Asking price( Total)]]-DATABASE_Table[[#This Row],[Vista membership]]-DATABASE_Table[[#This Row],[FF&E]] -> 355000 | Z22: =DATABASE_Table[[#This Row],[Sell price (Total)]]-DATABASE_Table[[#This Row],[FF&E]]-DATABASE_Table[[#This Row],[Vista membership]] -> -35000 | AB22: 47118 | AC22: João Gameiro | AD22: Miguel Ribeiro | AE22: https://www.aroeiracollections.com/ | AF22: Aroeira Collections by Missoni: Elegance inspired by iconic design, set beside the renowned PGA golf course — where luxury living meets the rhythm of the coast. | AG22: Gym, Spa, Condo Pool, Private Pools, Tennis & Padel Courts, Outdoor Areas, Smart Home Technology, Private Parking, Reception, Missoni Interiors, PGA Golf Course | AH22: Primeiro grande projeto com uma marca de lifestyle/moda em Portugal - Missoni; Localização de excelência dentro da Herdade da Aroeira, a 30' de Lisboa e 10' das melhores praias do país; Design com contributo de arquitetos de renome; Excelente oportunidade de investimento; Junto ao campo de golfe PGA Aroeira; Diversas amenities como: Piscina interior e exterior, campos de tenis e padel, ginásio, spa e restaurante. | AI22: Ana Costa, João Favila, Pedro Domingos | AJ22: Aroeira Collections
A23: Aroeira - HOTEL APARTMENTS | B23: Center | C23: 246A | D23: Herdade da Aroeira, Almada | E23: 1-BR | F23: 56.5 | H23: 1 | J23: 5 | O23: 51.5 | Q23: AVAILABLE | R23: =DATABASE_Table[[#This Row],[Inicial Asking Price (€) (Total)]]-DATABASE_Table[[#This Row],[Vista membership]]-DATABASE_Table[[#This Row],[FF&E]] -> 825000 | S23: 860000 | T23: 390000 | V23: 35000 | W23: =DATABASE_Table[[#This Row],[Current Asking price( Total)]]-DATABASE_Table[[#This Row],[Vista membership]]-DATABASE_Table[[#This Row],[FF&E]] -> 355000 | Z23: =DATABASE_Table[[#This Row],[Sell price (Total)]]-DATABASE_Table[[#This Row],[FF&E]]-DATABASE_Table[[#This Row],[Vista membership]] -> -35000 | AB23: 47118 | AC23: João Gameiro | AD23: Miguel Ribeiro | AE23: https://www.aroeiracollections.com/ | AF23: Aroeira Collections by Missoni: Elegance inspired by iconic design, set beside the renowned PGA golf course — where luxury living meets the rhythm of the coast. | AG23: Gym, Spa, Condo Pool, Private Pools, Tennis & Padel Courts, Outdoor Areas, Smart Home Technology, Private Parking, Reception, Missoni Interiors, PGA Golf Course | AH23: Primeiro grande projeto com uma marca de lifestyle/moda em Portugal - Missoni; Localização de excelência dentro da Herdade da Aroeira, a 30' de Lisboa e 10' das melhores praias do país; Design com contributo de arquitetos de renome; Excelente oportunidade de investimento; Junto ao campo de golfe PGA Aroeira; Diversas amenities como: Piscina interior e exterior, campos de tenis e padel, ginásio, spa e restaurante. | AI23: Ana Costa, João Favila, Pedro Domingos | AJ23: Aroeira Collections
A24: Aroeira - HOTEL APARTMENTS | B24: Center | C24: 334A | D24: Herdade da Aroeira, Almada | E24: 1-BR | F24: 56.5 | H24: 1 | J24: 5 | O24: 51.5 | Q24: RESERVED | R24: =DATABASE_Table[[#This Row],[Inicial Asking Price (€) (Total)]]-DATABASE_Table[[#This Row],[Vista membership]]-DATABASE_Table[[#This Row],[FF&E]] -> 1115000 | S24: 1150000 | T24: 405000 | V24: 35000 | W24: =DATABASE_Table[[#This Row],[Current Asking price( Total)]]-DATABASE_Table[[#This Row],[Vista membership]]-DATABASE_Table[[#This Row],[FF&E]] -> 370000 | X24: 0.012345679 | Y24: 400000 | Z24: =DATABASE_Table[[#This Row],[Sell price (Total)]]-DATABASE_Table[[#This Row],[FF&E]]-DATABASE_Table[[#This Row],[Vista membership]] -> 365000 | AA24: 46137 | AB24: 47118 | AC24: João Gameiro | AD24: Miguel Ribeiro | AE24: https://www.aroeiracollections.com/ | AF24: Aroeira Collections by Missoni: Elegance inspired by iconic design, set beside the renowned PGA golf course — where luxury living meets the rhythm of the coast. | AG24: Gym, Spa, Condo Pool, Private Pools, Tennis & Padel Courts, Outdoor Areas, Smart Home Technology, Private Parking, Reception, Missoni Interiors, PGA Golf Course | AH24: Primeiro grande projeto com uma marca de lifestyle/moda em Portugal - Missoni; Localização de excelência dentro da Herdade da Aroeira, a 30' de Lisboa e 10' das melhores praias do país; Design com contributo de arquitetos de renome; Excelente oportunidade de investimento; Junto ao campo de golfe PGA Aroeira; Diversas amenities como: Piscina interior e exterior, campos de tenis e padel, ginásio, spa e restaurante. | AI24: Ana Costa, João Favila, Pedro Domingos | AJ24: Aroeira Collections
A25: Aroeira - HOTEL APARTMENTS | B25: Center | C25: 335A | D25: Herdade da Aroeira, Almada | E25: 1-BR | F25: 56.5 | H25: 1 | J25: 5 | O25: 51.5 | Q25: AVAILABLE | R25: =DATABASE_Table[[#This Row],[Inicial Asking Price (€) (Total)]]-DATABASE_Table[[#This Row],[Vista membership]]-DATABASE_Table[[#This Row],[FF&E]] -> 635000 | S25: 670000 | T25: 405000 | V25: 35000 | W25: =DATABASE_Table[[#This Row],[Current Asking price( Total)]]-DATABASE_Table[[#This Row],[Vista membership]]-DATABASE_Table[[#This Row],[FF&E]] -> 370000 | Z25: =DATABASE_Table[[#This Row],[Sell price (Total)]]-DATABASE_Table[[#This Row],[FF&E]]-DATABASE_Table[[#This Row],[Vista membership]] -> -35000 | AB25: 47118 | AC25: João Gameiro | AD25: Miguel Ribeiro | AE25: https://www.aroeiracollections.com/ | AF25: Aroeira Collections by Missoni: Elegance inspired by iconic design, set beside the renowned PGA golf course — where luxury living meets the rhythm of the coast. | AG25: Gym, Spa, Condo Pool, Private Pools, Tennis & Padel Courts, Outdoor Areas, Smart Home Technology, Private Parking, Reception, Missoni Interiors, PGA Golf Course | AH25: Primeiro grande projeto com uma marca de lifestyle/moda em Portugal - Missoni; Localização de excelência dentro da Herdade da Aroeira, a 30' de Lisboa e 10' das melhores praias do país; Design com contributo de arquitetos de renome; Excelente oportunidade de investimento; Junto ao campo de golfe PGA Aroeira; Diversas amenities como: Piscina interior e exterior, campos de tenis e padel, ginásio, spa e restaurante. | AI25: Ana Costa, João Favila, Pedro Domingos | AJ25: Aroeira Collections
A26: Aroeira - HOTEL APARTMENTS | B26: Center | C26: 336A | D26: Herdade da Aroeira, Almada | E26: 1-BR | F26: 56.5 | H26: 1 | J26: 5 | O26: 51.5 | Q26: AVAILABLE | R26: =DATABASE_Table[[#This Row],[Inicial Asking Price (€) (Total)]]-DATABASE_Table[[#This Row],[Vista membership]]-DATABASE_Table[[#This Row],[FF&E]] -> 895000 | S26: 930000 | T26: 405000 | V26: 35000 | W26: =DATABASE_Table[[#This Row],[Current Asking price( Total)]]-DATABASE_Table[[#This Row],[Vista membership]]-DATABASE_Table[[#This Row],[FF&E]] -> 370000 | Z26: =DATABASE_Table[[#This Row],[Sell price (Total)]]-DATABASE_Table[[#This Row],[FF&E]]-DATABASE_Table[[#This Row],[Vista membership]] -> -35000 | AB26: 47118 | AC26: João Gameiro | AD26: Miguel Ribeiro | AE26: https://www.aroeiracollections.com/ | AF26: Aroeira Collections by Missoni: Elegance inspired by iconic design, set beside the renowned PGA golf course — where luxury living meets the rhythm of the coast. | AG26: Gym, Spa, Condo Pool, Private Pools, Tennis & Padel Courts, Outdoor Areas, Smart Home Technology, Private Parking, Reception, Missoni Interiors, PGA Golf Course | AH26: Primeiro grande projeto com uma marca de lifestyle/moda em Portugal - Missoni; Localização de excelência dentro da Herdade da Aroeira, a 30' de Lisboa e 10' das melhores praias do país; Design com contributo de arquitetos de renome; Excelente oportunidade de investimento; Junto ao campo de golfe PGA Aroeira; Diversas amenities como: Piscina interior e exterior, campos de tenis e padel, ginásio, spa e restaurante. | AI26: Ana Costa, João Favila, Pedro Domingos | AJ26: Aroeira Collections
A27: Aroeira - HOTEL APARTMENTS | B27: Center | C27: 337A | D27: Herdade da Aroeira, Almada | E27: 1-BR | F27: 56.5 | H27: 1 | J27: 5 | O27: 51.5 | Q27: AVAILABLE | R27: =DATABASE_Table[[#This Row],[Inicial Asking Price (€) (Total)]]-DATABASE_Table[[#This Row],[Vista membership]]-DATABASE_Table[[#This Row],[FF&E]] -> 675000 | S27: 710000 | T27: 405000 | V27: 35000 | W27: =DATABASE_Table[[#This Row],[Current Asking price( Total)]]-DATABASE_Table[[#This Row],[Vista membership]]-DATABASE_Table[[#This Row],[FF&E]] -> 370000 | Z27: =DATABASE_Table[[#This Row],[Sell price (Total)]]-DATABASE_Table[[#This Row],[FF&E]]-DATABASE_Table[[#This Row],[Vista membership]] -> -35000 | AB27: 47118 | AC27: João Gameiro | AD27: Miguel Ribeiro | AE27: https://www.aroeiracollections.com/ | AF27: Aroeira Collections by Missoni: Elegance inspired by iconic design, set beside the renowned PGA golf course — where luxury living meets the rhythm of the coast. | AG27: Gym, Spa, Condo Pool, Private Pools, Tennis & Padel Courts, Outdoor Areas, Smart Home Technology, Private Parking, Reception, Missoni Interiors, PGA Golf Course | AH27: Primeiro grande projeto com uma marca de lifestyle/moda em Portugal - Missoni; Localização de excelência dentro da Herdade da Aroeira, a 30' de Lisboa e 10' das melhores praias do país; Design com contributo de arquitetos de renome; Excelente oportunidade de investimento; Junto ao campo de golfe PGA Aroeira; Diversas amenities como: Piscina interior e exterior, campos de tenis e padel, ginásio, spa e restaurante. | AI27: Ana Costa, João Favila, Pedro Domingos | AJ27: Aroeira Collections
A28: Aroeira - HOTEL APARTMENTS | B28: Center | C28: 343A | D28: Herdade da Aroeira, Almada | E28: 1-BR | F28: 56.5 | H28: 1 | J28: 5 | O28: 51.5 | Q28: AVAILABLE | R28: =DATABASE_Table[[#This Row],[Inicial Asking Price (€) (Total)]]-DATABASE_Table[[#This Row],[Vista membership]]-DATABASE_Table[[#This Row],[FF&E]] -> 665000 | S28: 700000 | T28: 405000 | V28: 35000 | W28: =DATABASE_Table[[#This Row],[Current Asking price( Total)]]-DATABASE_Table[[#This Row],[Vista membership]]-DATABASE_Table[[#This Row],[FF&E]] -> 370000 | Z28: =DATABASE_Table[[#This Row],[Sell price (Total)]]-DATABASE_Table[[#This Row],[FF&E]]-DATABASE_Table[[#This Row],[Vista membership]] -> -35000 | AB28: 47118 | AC28: João Gameiro | AD28: Miguel Ribeiro | AE28: https://www.aroeiracollections.com/ | AF28: Aroeira Collections by Missoni: Elegance inspired by iconic design, set beside the renowned PGA golf course — where luxury living meets the rhythm of the coast. | AG28: Gym, Spa, Condo Pool, Private Pools, Tennis & Padel Courts, Outdoor Areas, Smart Home Technology, Private Parking, Reception, Missoni Interiors, PGA Golf Course | AH28: Primeiro grande projeto com uma marca de lifestyle/moda em Portugal - Missoni; Localização de excelência dentro da Herdade da Aroeira, a 30' de Lisboa e 10' das melhores praias do país; Design com contributo de arquitetos de renome; Excelente oportunidade de investimento; Junto ao campo de golfe PGA Aroeira; Diversas amenities como: Piscina interior e exterior, campos de tenis e padel, ginásio, spa e restaurante. | AI28: Ana Costa, João Favila, Pedro Domingos | AJ28: Aroeira Collections
A29: Aroeira - HOTEL APARTMENTS | B29: Center | C29: 344A | D29: Herdade da Aroeira, Almada | E29: 1-BR | F29: 56.5 | H29: 1 | J29: 5 | O29: 51.5 | Q29: AVAILABLE | R29: =DATABASE_Table[[#This Row],[Inicial Asking Price (€) (Total)]]-DATABASE_Table[[#This Row],[Vista membership]]-DATABASE_Table[[#This Row],[FF&E]] -> 705000 | S29: 740000 | T29: 405000 | V29: 35000 | W29: =DATABASE_Table[[#This Row],[Current Asking price( Total)]]-DATABASE_Table[[#This Row],[Vista membership]]-DATABASE_Table[[#This Row],[FF&E]] -> 370000 | Z29: =DATABASE_Table[[#This Row],[Sell price (Total)]]-DATABASE_Table[[#This Row],[FF&E]]-DATABASE_Table[[#This Row],[Vista membership]] -> -35000 | AB29: 47118 | AC29: João Gameiro | AD29: Miguel Ribeiro | AE29: https://www.aroeiracollections.com/ | AF29: Aroeira Collections by Missoni: Elegance inspired by iconic design, set beside the renowned PGA golf course — where luxury living meets the rhythm of the coast. | AG29: Gym, Spa, Condo Pool, Private Pools, Tennis & Padel Courts, Outdoor Areas, Smart Home Technology, Private Parking, Reception, Missoni Interiors, PGA Golf Course | AH29: Primeiro grande projeto com uma marca de lifestyle/moda em Portugal - Missoni; Localização de excelência dentro da Herdade da Aroeira, a 30' de Lisboa e 10' das melhores praias do país; Design com contributo de arquitetos de renome; Excelente oportunidade de investimento; Junto ao campo de golfe PGA Aroeira; Diversas amenities como: Piscina interior e exterior, campos de tenis e padel, ginásio, spa e restaurante. | AI29: Ana Costa, João Favila, Pedro Domingos | AJ29: Aroeira Collections
A30: Aroeira - HOTEL APARTMENTS | B30: Center | C30: 345A | D30: Herdade da Aroeira, Almada | E30: 1-BR | F30: 56.5 | H30: 1 | J30: 5 | O30: 51.5 | Q30: AVAILABLE | R30: =DATABASE_Table[[#This Row],[Inicial Asking Price (€) (Total)]]-DATABASE_Table[[#This Row],[Vista membership]]-DATABASE_Table[[#This Row],[FF&E]] -> 915000 | S30: 950000 | T30: 405000 | V30: 35000 | W30: =DATABASE_Table[[#This Row],[Current Asking price( Total)]]-DATABASE_Table[[#This Row],[Vista membership]]-DATABASE_Table[[#This Row],[FF&E]] -> 370000 | Z30: =DATABASE_Table[[#This Row],[Sell price (Total)]]-DATABASE_Table[[#This Row],[FF&E]]-DATABASE_Table[[#This Row],[Vista membership]] -> -35000 | AB30: 47118 | AC30: João Gameiro | AD30: Miguel Ribeiro | AE30: https://www.aroeiracollections.com/ | AF30: Aroeira Collections by Missoni: Elegance inspired by iconic design, set beside the renowned PGA golf course — where luxury living meets the rhythm of the coast. | AG30: Gym, Spa, Condo Pool, Private Pools, Tennis & Padel Courts, Outdoor Areas, Smart Home Technology, Private Parking, Reception, Missoni Interiors, PGA Golf Course | AH30: Primeiro grande projeto com uma marca de lifestyle/moda em Portugal - Missoni; Localização de excelência dentro da Herdade da Aroeira, a 30' de Lisboa e 10' das melhores praias do país; Design com contributo de arquitetos de renome; Excelente oportunidade de investimento; Junto ao campo de golfe PGA Aroeira; Diversas amenities como: Piscina interior e exterior, campos de tenis e padel, ginásio, spa e restaurante. | AI30: Ana Costa, João Favila, Pedro Domingos | AJ30: Aroeira Collections
A31: Aroeira - HOTEL APARTMENTS | B31: Center | C31: 346A | D31: Herdade da Aroeira, Almada | E31: 1-BR | F31: 56.5 | H31: 1 | J31: 5 | O31: 51.5 | Q31: AVAILABLE | R31: =DATABASE_Table[[#This Row],[Inicial Asking Price (€) (Total)]]-DATABASE_Table[[#This Row],[Vista membership]]-DATABASE_Table[[#This Row],[FF&E]] -> 1055000 | S31: 1090000 | T31: 405000 | V31: 35000 | W31: =DATABASE_Table[[#This Row],[Current Asking price( Total)]]-DATABASE_Table[[#This Row],[Vista membership]]-DATABASE_Table[[#This Row],[FF&E]] -> 370000 | Z31: =DATABASE_Table[[#This Row],[Sell price (Total)]]-DATABASE_Table[[#This Row],[FF&E]]-DATABASE_Table[[#This Row],[Vista membership]] -> -35000 | AB31: 47118 | AC31: João Gameiro | AD31: Miguel Ribeiro | AE31: https://www.aroeiracollections.com/ | AF31: Aroeira Collections by Missoni: Elegance inspired by iconic design, set beside the renowned PGA golf course — where luxury living meets the rhythm of the coast. | AG31: Gym, Spa, Condo Pool, Private Pools, Tennis & Padel Courts, Outdoor Areas, Smart Home Technology, Private Parking, Reception, Missoni Interiors, PGA Golf Course | AH31: Primeiro grande projeto com uma marca de lifestyle/moda em Portugal - Missoni; Localização de excelência dentro da Herdade da Aroeira, a 30' de Lisboa e 10' das melhores praias do país; Design com contributo de arquitetos de renome; Excelente oportunidade de investimento; Junto ao campo de golfe PGA Aroeira; Diversas amenities como: Piscina interior e exterior, campos de tenis e padel, ginásio, spa e restaurante. | AI31: Ana Costa, João Favila, Pedro Domingos | AJ31: Aroeira Collections
A32: Aroeira - HOTEL APARTMENTS | B32: Center | C32: 130A | D32: Herdade da Aroeira, Almada | E32: 1-BR | F32: 60.2 | H32: 1 | J32: 3.9 | O32: 56.3 | Q32: RESERVED | R32: =DATABASE_Table[[#This Row],[Inicial Asking Price (€) (Total)]]-DATABASE_Table[[#This Row],[Vista membership]]-DATABASE_Table[[#This Row],[FF&E]] -> 985000 | S32: 1020000 | T32: 410000 | V32: 35000 | W32: =DATABASE_Table[[#This Row],[Current Asking price( Total)]]-DATABASE_Table[[#This Row],[Vista membership]]-DATABASE_Table[[#This Row],[FF&E]] -> 375000 | X32: 0 | Y32: 410000 | Z32: =DATABASE_Table[[#This Row],[Sell price (Total)]]-DATABASE_Table[[#This Row],[FF&E]]-DATABASE_Table[[#This Row],[Vista membership]] -> 375000 | AA32: 46120 | AB32: 47118 | AC32: João Gameiro | AD32: Miguel Ribeiro | AE32: https://www.aroeiracollections.com/ | AF32: Aroeira Collections by Missoni: Elegance inspired by iconic design, set beside the renowned PGA golf course — where luxury living meets the rhythm of the coast. | AG32: Gym, Spa, Condo Pool, Private Pools, Tennis & Padel Courts, Outdoor Areas, Smart Home Technology, Private Parking, Reception, Missoni Interiors, PGA Golf Course | AH32: Primeiro grande projeto com uma marca de lifestyle/moda em Portugal - Missoni; Localização de excelência dentro da Herdade da Aroeira, a 30' de Lisboa e 10' das melhores praias do país; Design com contributo de arquitetos de renome; Excelente oportunidade de investimento; Junto ao campo de golfe PGA Aroeira; Diversas amenities como: Piscina interior e exterior, campos de tenis e padel, ginásio, spa e restaurante. | AI32: Ana Costa, João Favila, Pedro Domingos | AJ32: Aroeira Collections
A33: Aroeira - HOTEL APARTMENTS | B33: Center | C33: 131A | D33: Herdade da Aroeira, Almada | E33: 1-BR | F33: 60.2 | H33: 1 | J33: 3.9 | O33: 56.3 | Q33: RESERVED | R33: =DATABASE_Table[[#This Row],[Inicial Asking Price (€) (Total)]]-DATABASE_Table[[#This Row],[Vista membership]]-DATABASE_Table[[#This Row],[FF&E]] -> 725000 | S33: 760000 | T33: 410000 | V33: 35000 | W33: =DATABASE_Table[[#This Row],[Current Asking price( Total)]]-DATABASE_Table[[#This Row],[Vista membership]]-DATABASE_Table[[#This Row],[FF&E]] -> 375000 | X33: 0 | Y33: 410000 | Z33: =DATABASE_Table[[#This Row],[Sell price (Total)]]-DATABASE_Table[[#This Row],[FF&E]]-DATABASE_Table[[#This Row],[Vista membership]] -> 375000 | AA33: 46112 | AB33: 47118 | AC33: João Gameiro | AD33: Miguel Ribeiro | AE33: https://www.aroeiracollections.com/ | AF33: Aroeira Collections by Missoni: Elegance inspired by iconic design, set beside the renowned PGA golf course — where luxury living meets the rhythm of the coast. | AG33: Gym, Spa, Condo Pool, Private Pools, Tennis & Padel Courts, Outdoor Areas, Smart Home Technology, Private Parking, Reception, Missoni Interiors, PGA Golf Course | AH33: Primeiro grande projeto com uma marca de lifestyle/moda em Portugal - Missoni; Localização de excelência dentro da Herdade da Aroeira, a 30' de Lisboa e 10' das melhores praias do país; Design com contributo de arquitetos de renome; Excelente oportunidade de investimento; Junto ao campo de golfe PGA Aroeira; Diversas amenities como: Piscina interior e exterior, campos de tenis e padel, ginásio, spa e restaurante. | AI33: Ana Costa, João Favila, Pedro Domingos | AJ33: Aroeira Collections
A34: Aroeira - HOTEL APARTMENTS | B34: Center | C34: 132A | D34: Herdade da Aroeira, Almada | E34: 1-BR | F34: 60.2 | H34: 1 | J34: 3.9 | O34: 56.3 | Q34: RESERVED | R34: =DATABASE_Table[[#This Row],[Inicial Asking Price (€) (Total)]]-DATABASE_Table[[#This Row],[Vista membership]]-DATABASE_Table[[#This Row],[FF&E]] -> 765000 | S34: 800000 | T34: 410000 | V34: 35000 | W34: =DATABASE_Table[[#This Row],[Current Asking price( Total)]]-DATABASE_Table[[#This Row],[Vista membership]]-DATABASE_Table[[#This Row],[FF&E]] -> 375000 | X34: 0 | Y34: 410000 | Z34: =DATABASE_Table[[#This Row],[Sell price (Total)]]-DATABASE_Table[[#This Row],[FF&E]]-DATABASE_Table[[#This Row],[Vista membership]] -> 375000 | AA34: 46112 | AB34: 47118 | AC34: João Gameiro | AD34: Miguel Ribeiro | AE34: https://www.aroeiracollections.com/ | AF34: Aroeira Collections by Missoni: Elegance inspired by iconic design, set beside the renowned PGA golf course — where luxury living meets the rhythm of the coast. | AG34: Gym, Spa, Condo Pool, Private Pools, Tennis & Padel Courts, Outdoor Areas, Smart Home Technology, Private Parking, Reception, Missoni Interiors, PGA Golf Course | AH34: Primeiro grande projeto com uma marca de lifestyle/moda em Portugal - Missoni; Localização de excelência dentro da Herdade da Aroeira, a 30' de Lisboa e 10' das melhores praias do país; Design com contributo de arquitetos de renome; Excelente oportunidade de investimento; Junto ao campo de golfe PGA Aroeira; Diversas amenities como: Piscina interior e exterior, campos de tenis e padel, ginásio, spa e restaurante. | AI34: Ana Costa, João Favila, Pedro Domingos | AJ34: Aroeira Collections
A35: Aroeira - HOTEL APARTMENTS | B35: Center | C35: 133A | D35: Herdade da Aroeira, Almada | E35: 1-BR | F35: 60.2 | H35: 1 | J35: 3.9 | O35: 56.3 | Q35: RESERVED | R35: =DATABASE_Table[[#This Row],[Inicial Asking Price (€) (Total)]]-DATABASE_Table[[#This Row],[Vista membership]]-DATABASE_Table[[#This Row],[FF&E]] -> 885000 | S35: 920000 | T35: 410000 | V35: 35000 | W35: =DATABASE_Table[[#This Row],[Current Asking price( Total)]]-DATABASE_Table[[#This Row],[Vista membership]]-DATABASE_Table[[#This Row],[FF&E]] -> 375000 | X35: 0 | Y35: 410000 | Z35: =DATABASE_Table[[#This Row],[Sell price (Total)]]-DATABASE_Table[[#This Row],[FF&E]]-DATABASE_Table[[#This Row],[Vista membership]] -> 375000 | AA35: 46146 | AB35: 47118 | AC35: João Gameiro | AD35: Miguel Ribeiro | AE35: https://www.aroeiracollections.com/ | AF35: Aroeira Collections by Missoni: Elegance inspired by iconic design, set beside the renowned PGA golf course — where luxury living meets the rhythm of the coast. | AG35: Gym, Spa, Condo Pool, Private Pools, Tennis & Padel Courts, Outdoor Areas, Smart Home Technology, Private Parking, Reception, Missoni Interiors, PGA Golf Course | AH35: Primeiro grande projeto com uma marca de lifestyle/moda em Portugal - Missoni; Localização de excelência dentro da Herdade da Aroeira, a 30' de Lisboa e 10' das melhores praias do país; Design com contributo de arquitetos de renome; Excelente oportunidade de investimento; Junto ao campo de golfe PGA Aroeira; Diversas amenities como: Piscina interior e exterior, campos de tenis e padel, ginásio, spa e restaurante. | AI35: Ana Costa, João Favila, Pedro Domingos | AJ35: Aroeira Collections
A36: Aroeira - HOTEL APARTMENTS | B36: Center | C36: 129A | D36: Herdade da Aroeira, Almada | E36: 1-BR | F36: 60.2 | H36: 1 | J36: 3.9 | O36: 56.3 | Q36: AVAILABLE | R36: =DATABASE_Table[[#This Row],[Inicial Asking Price (€) (Total)]]-DATABASE_Table[[#This Row],[Vista membership]]-DATABASE_Table[[#This Row],[FF&E]] -> 1245000 | S36: 1280000 | T36: 410000 | V36: 35000 | W36: =DATABASE_Table[[#This Row],[Current Asking price( Total)]]-DATABASE_Table[[#This Row],[Vista membership]]-DATABASE_Table[[#This Row],[FF&E]] -> 375000 | Z36: =DATABASE_Table[[#This Row],[Sell price (Total)]]-DATABASE_Table[[#This Row],[FF&E]]-DATABASE_Table[[#This Row],[Vista membership]] -> -35000 | AB36: 47118 | AC36: João Gameiro | AD36: Miguel Ribeiro | AE36: https://www.aroeiracollections.com/ | AF36: Aroeira Collections by Missoni: Elegance inspired by iconic design, set beside the renowned PGA golf course — where luxury living meets the rhythm of the coast. | AG36: Gym, Spa, Condo Pool, Private Pools, Tennis & Padel Courts, Outdoor Areas, Smart Home Technology, Private Parking, Reception, Missoni Interiors, PGA Golf Course | AH36: Primeiro grande projeto com uma marca de lifestyle/moda em Portugal - Missoni; Localização de excelência dentro da Herdade da Aroeira, a 30' de Lisboa e 10' das melhores praias do país; Design com contributo de arquitetos de renome; Excelente oportunidade de investimento; Junto ao campo de golfe PGA Aroeira; Diversas amenities como: Piscina interior e exterior, campos de tenis e padel, ginásio, spa e restaurante. | AI36: Ana Costa, João Favila, Pedro Domingos | AJ36: Aroeira Collections
A37: Aroeira - HOTEL APARTMENTS | B37: Center | C37: 238A | D37: Herdade da Aroeira, Almada | E37: 1-BR | F37: 60.2 | H37: 1 | J37: 3.9 | O37: 56.3 | Q37: AVAILABLE | R37: =DATABASE_Table[[#This Row],[Inicial Asking Price (€) (Total)]]-DATABASE_Table[[#This Row],[Vista membership]]-DATABASE_Table[[#This Row],[FF&E]] -> 825000 | S37: 860000 | T37: 410000 | V37: 35000 | W37: =DATABASE_Table[[#This Row],[Current Asking price( Total)]]-DATABASE_Table[[#This Row],[Vista membership]]-DATABASE_Table[[#This Row],[FF&E]] -> 375000 | Z37: =DATABASE_Table[[#This Row],[Sell price (Total)]]-DATABASE_Table[[#This Row],[FF&E]]-DATABASE_Table[[#This Row],[Vista membership]] -> -35000 | AB37: 47118 | AC37: João Gameiro | AD37: Miguel Ribeiro | AE37: https://www.aroeiracollections.com/ | AF37: Aroeira Collections by Missoni: Elegance inspired by iconic design, set beside the renowned PGA golf course — where luxury living meets the rhythm of the coast. | AG37: Gym, Spa, Condo Pool, Private Pools, Tennis & Padel Courts, Outdoor Areas, Smart Home Technology, Private Parking, Reception, Missoni Interiors, PGA Golf Course | AH37: Primeiro grande projeto com uma marca de lifestyle/moda em Portugal - Missoni; Localização de excelência dentro da Herdade da Aroeira, a 30' de Lisboa e 10' das melhores praias do país; Design com contributo de arquitetos de renome; Excelente oportunidade de investimento; Junto ao campo de golfe PGA Aroeira; Diversas amenities como: Piscina interior e exterior, campos de tenis e padel, ginásio, spa e restaurante. | AI37: Ana Costa, João Favila, Pedro Domingos | AJ37: Aroeira Collections
A38: Aroeira - HOTEL APARTMENTS | B38: Center | C38: 239A | D38: Herdade da Aroeira, Almada | E38: 1-BR | F38: 60.2 | H38: 1 | J38: 3.9 | O38: 56.3 | Q38: AVAILABLE | R38: =DATABASE_Table[[#This Row],[Inicial Asking Price (€) (Total)]]-DATABASE_Table[[#This Row],[Vista membership]]-DATABASE_Table[[#This Row],[FF&E]] -> 745000 | S38: 780000 | T38: 410000 | V38: 35000 | W38: =DATABASE_Table[[#This Row],[Current Asking price( Total)]]-DATABASE_Table[[#This Row],[Vista membership]]-DATABASE_Table[[#This Row],[FF&E]] -> 375000 | Z38: =DATABASE_Table[[#This Row],[Sell price (Total)]]-DATABASE_Table[[#This Row],[FF&E]]-DATABASE_Table[[#This Row],[Vista membership]] -> -35000 | AB38: 47118 | AC38: João Gameiro | AD38: Miguel Ribeiro | AE38: https://www.aroeiracollections.com/ | AF38: Aroeira Collections by Missoni: Elegance inspired by iconic design, set beside the renowned PGA golf course — where luxury living meets the rhythm of the coast. | AG38: Gym, Spa, Condo Pool, Private Pools, Tennis & Padel Courts, Outdoor Areas, Smart Home Technology, Private Parking, Reception, Missoni Interiors, PGA Golf Course | AH38: Primeiro grande projeto com uma marca de lifestyle/moda em Portugal - Missoni; Localização de excelência dentro da Herdade da Aroeira, a 30' de Lisboa e 10' das melhores praias do país; Design com contributo de arquitetos de renome; Excelente oportunidade de investimento; Junto ao campo de golfe PGA Aroeira; Diversas amenities como: Piscina interior e exterior, campos de tenis e padel, ginásio, spa e restaurante. | AI38: Ana Costa, João Favila, Pedro Domingos | AJ38: Aroeira Collections
A39: Aroeira - HOTEL APARTMENTS | B39: Center | C39: 240A | D39: Herdade da Aroeira, Almada | E39: 1-BR | F39: 60.2 | H39: 1 | J39: 3.9 | O39: 56.3 | Q39: AVAILABLE | R39: =DATABASE_Table[[#This Row],[Inicial Asking Price (€) (Total)]]-DATABASE_Table[[#This Row],[Vista membership]]-DATABASE_Table[[#This Row],[FF&E]] -> 635000 | S39: 670000 | T39: 410000 | V39: 35000 | W39: =DATABASE_Table[[#This Row],[Current Asking price( Total)]]-DATABASE_Table[[#This Row],[Vista membership]]-DATABASE_Table[[#This Row],[FF&E]] -> 375000 | Z39: =DATABASE_Table[[#This Row],[Sell price (Total)]]-DATABASE_Table[[#This Row],[FF&E]]-DATABASE_Table[[#This Row],[Vista membership]] -> -35000 | AB39: 47118 | AC39: João Gameiro | AD39: Miguel Ribeiro | AE39: https://www.aroeiracollections.com/ | AF39: Aroeira Collections by Missoni: Elegance inspired by iconic design, set beside the renowned PGA golf course — where luxury living meets the rhythm of the coast. | AG39: Gym, Spa, Condo Pool, Private Pools, Tennis & Padel Courts, Outdoor Areas, Smart Home Technology, Private Parking, Reception, Missoni Interiors, PGA Golf Course | AH39: Primeiro grande projeto com uma marca de lifestyle/moda em Portugal - Missoni; Localização de excelência dentro da Herdade da Aroeira, a 30' de Lisboa e 10' das melhores praias do país; Design com contributo de arquitetos de renome; Excelente oportunidade de investimento; Junto ao campo de golfe PGA Aroeira; Diversas amenities como: Piscina interior e exterior, campos de tenis e padel, ginásio, spa e restaurante. | AI39: Ana Costa, João Favila, Pedro Domingos | AJ39: Aroeira Collections
A40: Aroeira - HOTEL APARTMENTS | B40: Center | C40: 241A | D40: Herdade da Aroeira, Almada | E40: 1-BR | F40: 60.2 | H40: 1 | J40: 3.9 | O40: 56.3 | Q40: AVAILABLE | R40: =DATABASE_Table[[#This Row],[Inicial Asking Price (€) (Total)]]-DATABASE_Table[[#This Row],[Vista membership]]-DATABASE_Table[[#This Row],[FF&E]] -> 1005000 | S40: 1040000 | T40: 410000 | V40: 35000 | W40: =DATABASE_Table[[#This Row],[Current Asking price( Total)]]-DATABASE_Table[[#This Row],[Vista membership]]-DATABASE_Table[[#This Row],[FF&E]] -> 375000 | Z40: =DATABASE_Table[[#This Row],[Sell price (Total)]]-DATABASE_Table[[#This Row],[FF&E]]-DATABASE_Table[[#This Row],[Vista membership]] -> -35000 | AB40: 47118 | AC40: João Gameiro | AD40: Miguel Ribeiro | AE40: https://www.aroeiracollections.com/ | AF40: Aroeira Collections by Missoni: Elegance inspired by iconic design, set beside the renowned PGA golf course — where luxury living meets the rhythm of the coast. | AG40: Gym, Spa, Condo Pool, Private Pools, Tennis & Padel Courts, Outdoor Areas, Smart Home Technology, Private Parking, Reception, Missoni Interiors, PGA Golf Course | AH40: Primeiro grande projeto com uma marca de lifestyle/moda em Portugal - Missoni; Localização de excelência dentro da Herdade da Aroeira, a 30' de Lisboa e 10' das melhores praias do país; Design com contributo de arquitetos de renome; Excelente oportunidade de investimento; Junto ao campo de golfe PGA Aroeira; Diversas amenities como: Piscina interior e exterior, campos de tenis e padel, ginásio, spa e restaurante. | AI40: Ana Costa, João Favila, Pedro Domingos | AJ40: Aroeira Collections
A41: Aroeira - HOTEL APARTMENTS | B41: Center | C41: 242A | D41: Herdade da Aroeira, Almada | E41: 1-BR | F41: 60.2 | H41: 1 | J41: 3.9 | O41: 56.3 | Q41: AVAILABLE | R41: =DATABASE_Table[[#This Row],[Inicial Asking Price (€) (Total)]]-DATABASE_Table[[#This Row],[Vista membership]]-DATABASE_Table[[#This Row],[FF&E]] -> 715000 | S41: 750000 | T41: 410000 | V41: 35000 | W41: =DATABASE_Table[[#This Row],[Current Asking price( Total)]]-DATABASE_Table[[#This Row],[Vista membership]]-DATABASE_Table[[#This Row],[FF&E]] -> 375000 | Z41: =DATABASE_Table[[#This Row],[Sell price (Total)]]-DATABASE_Table[[#This Row],[FF&E]]-DATABASE_Table[[#This Row],[Vista membership]] -> -35000 | AB41: 47118 | AC41: João Gameiro | AD41: Miguel Ribeiro | AE41: https://www.aroeiracollections.com/ | AF41: Aroeira Collections by Missoni: Elegance inspired by iconic design, set beside the renowned PGA golf course — where luxury living meets the rhythm of the coast. | AG41: Gym, Spa, Condo Pool, Private Pools, Tennis & Padel Courts, Outdoor Areas, Smart Home Technology, Private Parking, Reception, Missoni Interiors, PGA Golf Course | AH41: Primeiro grande projeto com uma marca de lifestyle/moda em Portugal - Missoni; Localização de excelência dentro da Herdade da Aroeira, a 30' de Lisboa e 10' das melhores praias do país; Design com contributo de arquitetos de renome; Excelente oportunidade de investimento; Junto ao campo de golfe PGA Aroeira; Diversas amenities como: Piscina interior e exterior, campos de tenis e padel, ginásio, spa e restaurante. | AI41: Ana Costa, João Favila, Pedro Domingos | AJ41: Aroeira Collections
A42: Aroeira - VILLAS | B42: Center | C42: 05D | D42: Herdade da Aroeira, Almada | E42: T4 | F42: 559 | H42: 2 | I42: 1 | M42: 196 | N42: 65 | O42: 298 | Q42: PSPA | R42: =DATABASE_Table[[#This Row],[Inicial Asking Price (€) (Total)]]-DATABASE_Table[[#This Row],[Vista membership]]-DATABASE_Table[[#This Row],[FF&E]] -> 2500000 | S42: 2570000 | T42: 2570000 | V42: 70000 | W42: =DATABASE_Table[[#This Row],[Current Asking price( Total)]]-DATABASE_Table[[#This Row],[Vista membership]]-DATABASE_Table[[#This Row],[FF&E]] -> 2500000 | X42: 0 | Y42: 2570000 | Z42: =DATABASE_Table[[#This Row],[Sell price (Total)]]-DATABASE_Table[[#This Row],[FF&E]]-DATABASE_Table[[#This Row],[Vista membership]] -> 2500000 | AA42: 46093 | AB42: 47118 | AC42: João Gameiro | AD42: Miguel Ribeiro | AE42: https://www.aroeiracollections.com/ | AF42: Aroeira Collections by Missoni: Elegance inspired by iconic design, set beside the renowned PGA golf course — where luxury living meets the rhythm of the coast. | AG42: Gym, Spa, Condo Pool, Private Pools, Tennis & Padel Courts, Outdoor Areas, Smart Home Technology, Private Parking, Reception, Missoni Interiors, PGA Golf Course | AH42: Primeiro grande projeto com uma marca de lifestyle/moda em Portugal - Missoni; Localização de excelência dentro da Herdade da Aroeira, a 30' de Lisboa e 10' das melhores praias do país; Design com contributo de arquitetos de renome; Excelente oportunidade de investimento; Junto ao campo de golfe PGA Aroeira; Diversas amenities como: Piscina interior e exterior, campos de tenis e padel, ginásio, spa e restaurante. | AI42: Ana Costa, João Favila, Pedro Domingos | AJ42: Aroeira Collections
A43: Aroeira - HOTEL APARTMENTS | B43: Center | C43: 102A | D43: Herdade da Aroeira, Almada | E43: 1-BR | F43: 65 | H43: 1 | J43: 8.7 | O43: 56.3 | Q43: AVAILABLE | R43: =DATABASE_Table[[#This Row],[Inicial Asking Price (€) (Total)]]-DATABASE_Table[[#This Row],[Vista membership]]-DATABASE_Table[[#This Row],[FF&E]] -> 805000 | S43: 840000 | T43: 415000 | V43: 35000 | W43: =DATABASE_Table[[#This Row],[Current Asking price( Total)]]-DATABASE_Table[[#This Row],[Vista membership]]-DATABASE_Table[[#This Row],[FF&E]] -> 380000 | Z43: =DATABASE_Table[[#This Row],[Sell price (Total)]]-DATABASE_Table[[#This Row],[FF&E]]-DATABASE_Table[[#This Row],[Vista membership]] -> -35000 | AB43: 47118 | AC43: João Gameiro | AD43: Miguel Ribeiro | AE43: https://www.aroeiracollections.com/ | AF43: Aroeira Collections by Missoni: Elegance inspired by iconic design, set beside the renowned PGA golf course — where luxury living meets the rhythm of the coast. | AG43: Gym, Spa, Condo Pool, Private Pools, Tennis & Padel Courts, Outdoor Areas, Smart Home Technology, Private Parking, Reception, Missoni Interiors, PGA Golf Course | AH43: Primeiro grande projeto com uma marca de lifestyle/moda em Portugal - Missoni; Localização de excelência dentro da Herdade da Aroeira, a 30' de Lisboa e 10' das melhores praias do país; Design com contributo de arquitetos de renome; Excelente oportunidade de investimento; Junto ao campo de golfe PGA Aroeira; Diversas amenities como: Piscina interior e exterior, campos de tenis e padel, ginásio, spa e restaurante. | AI43: Ana Costa, João Favila, Pedro Domingos | AJ43: Aroeira Collections
A44: Aroeira - HOTEL APARTMENTS | B44: Center | C44: 104A | D44: Herdade da Aroeira, Almada | E44: 1-BR | F44: 65 | H44: 1 | J44: 8.7 | O44: 56.3 | Q44: AVAILABLE | R44: =DATABASE_Table[[#This Row],[Inicial Asking Price (€) (Total)]]-DATABASE_Table[[#This Row],[Vista membership]]-DATABASE_Table[[#This Row],[FF&E]] -> 915000 | S44: 950000 | T44: 415000 | V44: 35000 | W44: =DATABASE_Table[[#This Row],[Current Asking price( Total)]]-DATABASE_Table[[#This Row],[Vista membership]]-DATABASE_Table[[#This Row],[FF&E]] -> 380000 | Z44: =DATABASE_Table[[#This Row],[Sell price (Total)]]-DATABASE_Table[[#This Row],[FF&E]]-DATABASE_Table[[#This Row],[Vista membership]] -> -35000 | AB44: 47118 | AC44: João Gameiro | AD44: Miguel Ribeiro | AE44: https://www.aroeiracollections.com/ | AF44: Aroeira Collections by Missoni: Elegance inspired by iconic design, set beside the renowned PGA golf course — where luxury living meets the rhythm of the coast. | AG44: Gym, Spa, Condo Pool, Private Pools, Tennis & Padel Courts, Outdoor Areas, Smart Home Technology, Private Parking, Reception, Missoni Interiors, PGA Golf Course | AH44: Primeiro grande projeto com uma marca de lifestyle/moda em Portugal - Missoni; Localização de excelência dentro da Herdade da Aroeira, a 30' de Lisboa e 10' das melhores praias do país; Design com contributo de arquitetos de renome; Excelente oportunidade de investimento; Junto ao campo de golfe PGA Aroeira; Diversas amenities como: Piscina interior e exterior, campos de tenis e padel, ginásio, spa e restaurante. | AI44: Ana Costa, João Favila, Pedro Domingos | AJ44: Aroeira Collections
A45: Aroeira - HOTEL APARTMENTS | B45: Center | C45: 105A | D45: Herdade da Aroeira, Almada | E45: 1-BR | F45: 65 | H45: 1 | J45: 8.7 | O45: 56.3 | Q45: AVAILABLE | R45: =DATABASE_Table[[#This Row],[Inicial Asking Price (€) (Total)]]-DATABASE_Table[[#This Row],[Vista membership]]-DATABASE_Table[[#This Row],[FF&E]] -> 755000 | S45: 790000 | T45: 415000 | V45: 35000 | W45: =DATABASE_Table[[#This Row],[Current Asking price( Total)]]-DATABASE_Table[[#This Row],[Vista membership]]-DATABASE_Table[[#This Row],[FF&E]] -> 380000 | Z45: =DATABASE_Table[[#This Row],[Sell price (Total)]]-DATABASE_Table[[#This Row],[FF&E]]-DATABASE_Table[[#This Row],[Vista membership]] -> -35000 | AB45: 47118 | AC45: João Gameiro | AD45: Miguel Ribeiro | AE45: https://www.aroeiracollections.com/ | AF45: Aroeira Collections by Missoni: Elegance inspired by iconic design, set beside the renowned PGA golf course — where luxury living meets the rhythm of the coast. | AG45: Gym, Spa, Condo Pool, Private Pools, Tennis & Padel Courts, Outdoor Areas, Smart Home Technology, Private Parking, Reception, Missoni Interiors, PGA Golf Course | AH45: Primeiro grande projeto com uma marca de lifestyle/moda em Portugal - Missoni; Localização de excelência dentro da Herdade da Aroeira, a 30' de Lisboa e 10' das melhores praias do país; Design com contributo de arquitetos de renome; Excelente oportunidade de investimento; Junto ao campo de golfe PGA Aroeira; Diversas amenities como: Piscina interior e exterior, campos de tenis e padel, ginásio, spa e restaurante. | AI45: Ana Costa, João Favila, Pedro Domingos | AJ45: Aroeira Collections
A46: Aroeira - HOTEL APARTMENTS | B46: Center | C46: 106A | D46: Herdade da Aroeira, Almada | E46: 1-BR | F46: 65 | H46: 1 | J46: 8.7 | O46: 56.3 | Q46: AVAILABLE | R46: =DATABASE_Table[[#This Row],[Inicial Asking Price (€) (Total)]]-DATABASE_Table[[#This Row],[Vista membership]]-DATABASE_Table[[#This Row],[FF&E]] -> 855000 | S46: 890000 | T46: 415000 | V46: 35000 | W46: =DATABASE_Table[[#This Row],[Current Asking price( Total)]]-DATABASE_Table[[#This Row],[Vista membership]]-DATABASE_Table[[#This Row],[FF&E]] -> 380000 | Z46: =DATABASE_Table[[#This Row],[Sell price (Total)]]-DATABASE_Table[[#This Row],[FF&E]]-DATABASE_Table[[#This Row],[Vista membership]] -> -35000 | AB46: 47118 | AC46: João Gameiro | AD46: Miguel Ribeiro | AE46: https://www.aroeiracollections.com/ | AF46: Aroeira Collections by Missoni: Elegance inspired by iconic design, set beside the renowned PGA golf course — where luxury living meets the rhythm of the coast. | AG46: Gym, Spa, Condo Pool, Private Pools, Tennis & Padel Courts, Outdoor Areas, Smart Home Technology, Private Parking, Reception, Missoni Interiors, PGA Golf Course | AH46: Primeiro grande projeto com uma marca de lifestyle/moda em Portugal - Missoni; Localização de excelência dentro da Herdade da Aroeira, a 30' de Lisboa e 10' das melhores praias do país; Design com contributo de arquitetos de renome; Excelente oportunidade de investimento; Junto ao campo de golfe PGA Aroeira; Diversas amenities como: Piscina interior e exterior, campos de tenis e padel, ginásio, spa e restaurante. | AI46: Ana Costa, João Favila, Pedro Domingos | AJ46: Aroeira Collections
A47: Aroeira - HOTEL APARTMENTS | B47: Center | C47: 107A | D47: Herdade da Aroeira, Almada | E47: 1-BR | F47: 65 | H47: 1 | J47: 8.7 | O47: 56.3 | Q47: AVAILABLE | R47: =DATABASE_Table[[#This Row],[Inicial Asking Price (€) (Total)]]-DATABASE_Table[[#This Row],[Vista membership]]-DATABASE_Table[[#This Row],[FF&E]] -> 825000 | S47: 860000 | T47: 415000 | V47: 35000 | W47: =DATABASE_Table[[#This Row],[Current Asking price( Total)]]-DATABASE_Table[[#This Row],[Vista membership]]-DATABASE_Table[[#This Row],[FF&E]] -> 380000 | Z47: =DATABASE_Table[[#This Row],[Sell price (Total)]]-DATABASE_Table[[#This Row],[FF&E]]-DATABASE_Table[[#This Row],[Vista membership]] -> -35000 | AB47: 47118 | AC47: João Gameiro | AD47: Miguel Ribeiro | AE47: https://www.aroeiracollections.com/ | AF47: Aroeira Collections by Missoni: Elegance inspired by iconic design, set beside the renowned PGA golf course — where luxury living meets the rhythm of the coast. | AG47: Gym, Spa, Condo Pool, Private Pools, Tennis & Padel Courts, Outdoor Areas, Smart Home Technology, Private Parking, Reception, Missoni Interiors, PGA Golf Course | AH47: Primeiro grande projeto com uma marca de lifestyle/moda em Portugal - Missoni; Localização de excelência dentro da Herdade da Aroeira, a 30' de Lisboa e 10' das melhores praias do país; Design com contributo de arquitetos de renome; Excelente oportunidade de investimento; Junto ao campo de golfe PGA Aroeira; Diversas amenities como: Piscina interior e exterior, campos de tenis e padel, ginásio, spa e restaurante. | AI47: Ana Costa, João Favila, Pedro Domingos | AJ47: Aroeira Collections
A48: Aroeira - HOTEL APARTMENTS | B48: Center | C48: 108A | D48: Herdade da Aroeira, Almada | E48: 1-BR | F48: 65 | H48: 1 | J48: 8.7 | O48: 56.3 | Q48: AVAILABLE | R48: =DATABASE_Table[[#This Row],[Inicial Asking Price (€) (Total)]]-DATABASE_Table[[#This Row],[Vista membership]]-DATABASE_Table[[#This Row],[FF&E]] -> 925000 | S48: 960000 | T48: 415000 | V48: 35000 | W48: =DATABASE_Table[[#This Row],[Current Asking price( Total)]]-DATABASE_Table[[#This Row],[Vista membership]]-DATABASE_Table[[#This Row],[FF&E]] -> 380000 | Z48: =DATABASE_Table[[#This Row],[Sell price (Total)]]-DATABASE_Table[[#This Row],[FF&E]]-DATABASE_Table[[#This Row],[Vista membership]] -> -35000 | AB48: 47118 | AC48: João Gameiro | AD48: Miguel Ribeiro | AE48: https://www.aroeiracollections.com/ | AF48: Aroeira Collections by Missoni: Elegance inspired by iconic design, set beside the renowned PGA golf course — where luxury living meets the rhythm of the coast. | AG48: Gym, Spa, Condo Pool, Private Pools, Tennis & Padel Courts, Outdoor Areas, Smart Home Technology, Private Parking, Reception, Missoni Interiors, PGA Golf Course | AH48: Primeiro grande projeto com uma marca de lifestyle/moda em Portugal - Missoni; Localização de excelência dentro da Herdade da Aroeira, a 30' de Lisboa e 10' das melhores praias do país; Design com contributo de arquitetos de renome; Excelente oportunidade de investimento; Junto ao campo de golfe PGA Aroeira; Diversas amenities como: Piscina interior e exterior, campos de tenis e padel, ginásio, spa e restaurante. | AI48: Ana Costa, João Favila, Pedro Domingos | AJ48: Aroeira Collections
A49: Palmares - Plots | B49: Algarve | C49: 101 | D49: Lagos, Algarve | E49: Plot | F49: 340 | O49: 340 | Q49: AVAILABLE | R49: =DATABASE_Table[[#This Row],[Inicial Asking Price (€) (Total)]]-DATABASE_Table[[#This Row],[Vista membership]]-DATABASE_Table[[#This Row],[FF&E]] -> 820000 | S49: 820000 | T49: 1600000 | W49: =DATABASE_Table[[#This Row],[Current Asking price( Total)]]-DATABASE_Table[[#This Row],[Vista membership]]-DATABASE_Table[[#This Row],[FF&E]] -> 1600000 | Y49: 1600000 | Z49: =DATABASE_Table[[#This Row],[Sell price (Total)]]-DATABASE_Table[[#This Row],[FF&E]]-DATABASE_Table[[#This Row],[Vista membership]] -> 1600000 | AB49: 46843 | AC49: Sandra Viegas | AD49: João Barra | José Guerreiro | AE49: https://www.palmaresliving.com/ | AF49: Palmares Ocean & Living : Where ocean breezes, world-class golf, and award-winning design converge to create a lifestyle beyond compare. | AG49: Gym, Spa, Condo Pool, Private Pools, Outdoor Areas, Private Parking, Reception, World Class Golf Course | AH49: Com projeto assinado pelos vencedores do Pritzker award RCR Arquitectes; Primeira linha de mar com Apartamentos de assinatura, villas e branded residences JW Marriott; Vistas previlegiadas para o mar; Oportunidade de rentabilizar o investimento com gestão turística profissional e full-service. | AI49: RCR | AJ49: Palmares
A50: Palmares - Plots | B50: Algarve | C50: 102 | D50: Lagos, Algarve | E50: Plot | F50: 500 | O50: 500 | Q50: AVAILABLE | R50: =DATABASE_Table[[#This Row],[Inicial Asking Price (€) (Total)]]-DATABASE_Table[[#This Row],[Vista membership]]-DATABASE_Table[[#This Row],[FF&E]] -> 800000 | S50: 800000 | T50: 1800000 | W50: =DATABASE_Table[[#This Row],[Current Asking price( Total)]]-DATABASE_Table[[#This Row],[Vista membership]]-DATABASE_Table[[#This Row],[FF&E]] -> 1800000 | Y50: 1800000 | Z50: =DATABASE_Table[[#This Row],[Sell price (Total)]]-DATABASE_Table[[#This Row],[FF&E]]-DATABASE_Table[[#This Row],[Vista membership]] -> 1800000 | AB50: 46843 | AC50: Sandra Viegas | AD50: João Barra | José Guerreiro | AE50: https://www.palmaresliving.com/ | AF50: Palmares Ocean & Living : Where ocean breezes, world-class golf, and award-winning design converge to create a lifestyle beyond compare. | AG50: Gym, Spa, Condo Pool, Private Pools, Outdoor Areas, Private Parking, Reception, World Class Golf Course | AH50: Com projeto assinado pelos vencedores do Pritzker award RCR Arquitectes; Primeira linha de mar com Apartamentos de assinatura, villas e branded residences JW Marriott; Vistas previlegiadas para o mar; Oportunidade de rentabilizar o investimento com gestão turística profissional e full-service. | AI50: RCR | AJ50: Palmares
A51: Palmares - Plots | B51: Algarve | C51: 103 | D51: Lagos, Algarve | E51: Plot | F51: 500 | O51: 500 | Q51: AVAILABLE | R51: =DATABASE_Table[[#This Row],[Inicial Asking Price (€) (Total)]]-DATABASE_Table[[#This Row],[Vista membership]]-DATABASE_Table[[#This Row],[FF&E]] -> 930000 | S51: 930000 | T51: 2400000 | W51: =DATABASE_Table[[#This Row],[Current Asking price( Total)]]-DATABASE_Table[[#This Row],[Vista membership]]-DATABASE_Table[[#This Row],[FF&E]] -> 2400000 | Y51: 2400000 | Z51: =DATABASE_Table[[#This Row],[Sell price (Total)]]-DATABASE_Table[[#This Row],[FF&E]]-DATABASE_Table[[#This Row],[Vista membership]] -> 2400000 | AB51: 46843 | AC51: Sandra Viegas | AD51: João Barra | José Guerreiro | AE51: https://www.palmaresliving.com/ | AF51: Palmares Ocean & Living : Where ocean breezes, world-class golf, and award-winning design converge to create a lifestyle beyond compare. | AG51: Gym, Spa, Condo Pool, Private Pools, Outdoor Areas, Private Parking, Reception, World Class Golf Course | AH51: Com projeto assinado pelos vencedores do Pritzker award RCR Arquitectes; Primeira linha de mar com Apartamentos de assinatura, villas e branded residences JW Marriott; Vistas previlegiadas para o mar; Oportunidade de rentabilizar o investimento com gestão turística profissional e full-service. | AI51: RCR | AJ51: Palmares
A52: Palmares - Signature Residences | B52: Algarve | C52: 10B | E52: T2 + 1 Duplex | F52: 345.42 | I52: 15.29 | M52: 85.2 | O52: 244.93 | Q52: AVAILABLE | R52: =DATABASE_Table[[#This Row],[Inicial Asking Price (€) (Total)]]-DATABASE_Table[[#This Row],[Vista membership]]-DATABASE_Table[[#This Row],[FF&E]] -> 2080000 | S52: 2080000 | T52: 2080000 | W52: =DATABASE_Table[[#This Row],[Current Asking price( Total)]]-DATABASE_Table[[#This Row],[Vista membership]]-DATABASE_Table[[#This Row],[FF&E]] -> 2080000 | Y52: 2080000 | Z52: =DATABASE_Table[[#This Row],[Sell price (Total)]]-DATABASE_Table[[#This Row],[FF&E]]-DATABASE_Table[[#This Row],[Vista membership]] -> 2080000 | AB52: 46843 | AJ52: Palmares
A53: Palmares - Signature Residences | B53: Algarve | C53: 11B | E53: T2 + 1Duplex | F53: 344.99 | I53: 15.13 | M53: 83.71 | O53: 246.15 | Q53: AVAILABLE | R53: =DATABASE_Table[[#This Row],[Inicial Asking Price (€) (Total)]]-DATABASE_Table[[#This Row],[Vista membership]]-DATABASE_Table[[#This Row],[FF&E]] -> 2060000 | S53: 2060000 | T53: 2060000 | W53: =DATABASE_Table[[#This Row],[Current Asking price( Total)]]-DATABASE_Table[[#This Row],[Vista membership]]-DATABASE_Table[[#This Row],[FF&E]] -> 2060000 | Y53: 2060000 | Z53: =DATABASE_Table[[#This Row],[Sell price (Total)]]-DATABASE_Table[[#This Row],[FF&E]]-DATABASE_Table[[#This Row],[Vista membership]] -> 2060000 | AB53: 46843 | AJ53: Palmares
A54: ELS | B54: Vilamoura | C54: 1 | D54: Vilamoura, Algarve | E54: Plot | F54: 295 | O54: 295 | Q54: AVAILABLE | R54: =DATABASE_Table[[#This Row],[Inicial Asking Price (€) (Total)]]-DATABASE_Table[[#This Row],[Vista membership]]-DATABASE_Table[[#This Row],[FF&E]] -> 2690000 | S54: 2690000 | T54: 2580000 | W54: =DATABASE_Table[[#This Row],[Current Asking price( Total)]]-DATABASE_Table[[#This Row],[Vista membership]]-DATABASE_Table[[#This Row],[FF&E]] -> 2580000 | Y54: 2580000 | Z54: =DATABASE_Table[[#This Row],[Sell price (Total)]]-DATABASE_Table[[#This Row],[FF&E]]-DATABASE_Table[[#This Row],[Vista membership]] -> 2580000 | AC54: Ana Damásio | AD54: Carla Veiga | AE54: Springs Els Club - *Vilamoura | AF54: The new chapter of Vilamoura begins here. Join the inner circle with Club access to golf, sport, equestrian & beach life. | AG54: Gym, Spa, Lazy River, Private Pools, Outdoor Areas, Smart Home Technology, Tennis Court, Clubhouse, Private Parking, Vista Membership | AH54: Projeto de excelência com vista direta para o Els Club, o campo de Golf mais exclusivo de Vilamoura; Club-house com piscina e lazy river; Spa e campos de tenis / padel disponíveis; Possibilidade de rentabilidade através de exploração turística com gestão profissional (Details) | AI54: Promontório | AJ54: Springs - At the Els
A55: THE UNCOMMON | B55: Vilamoura | C55: 1 | D55: Vilamoura, Algarve | E55: T3 | F55: 213.2 | H55: 1 | J55: 63.6 | O55: 149.6 | Q55: AVAILABLE | R55: =DATABASE_Table[[#This Row],[Inicial Asking Price (€) (Total)]]-DATABASE_Table[[#This Row],[Vista membership]]-DATABASE_Table[[#This Row],[FF&E]] -> 1860000 | S55: 1940000 | T55: 2020000 | U55: 50000 | V55: 30000 | W55: =DATABASE_Table[[#This Row],[Current Asking price( Total)]]-DATABASE_Table[[#This Row],[Vista membership]]-DATABASE_Table[[#This Row],[FF&E]] -> 1940000 | Y55: 2020000 | Z55: =DATABASE_Table[[#This Row],[Sell price (Total)]]-DATABASE_Table[[#This Row],[FF&E]]-DATABASE_Table[[#This Row],[Vista membership]] -> 1940000 | AC55: Ana Damásio | AD55: Eduardo Lopes | AE55: TBD | AF55: The Uncommon is a front-row sea view masterpiece in Vilamoura, where vibrant energy meets serene coastal living. With an exclusive design and elevated services, in this touristic and residential project every moment feels uniquely exceptional. | AG55: Condo Pool, Outdoor Areas, Underground Parking, Reception, Concierge, Vista Membership | AH55: Apartamentos com exploração turística profissional e possibilidade de uso pelos proprietários; Amenities de excelência; Vistas excepcionais e em primeira linha de mar; Rooftops com plunge pool privativos. | AI55: NLA | AJ55: The Uncommon
A56: ELS | B56: Vilamoura | C56: 10 | D56: Vilamoura, Algarve | E56: Plot | F56: 280 | O56: 280 | Q56: AVAILABLE | R56: =DATABASE_Table[[#This Row],[Inicial Asking Price (€) (Total)]]-DATABASE_Table[[#This Row],[Vista membership]]-DATABASE_Table[[#This Row],[FF&E]] -> 3180000 | S56: 3180000 | T56: 1350000 | W56: =DATABASE_Table[[#This Row],[Current Asking price( Total)]]-DATABASE_Table[[#This Row],[Vista membership]]-DATABASE_Table[[#This Row],[FF&E]] -> 1350000 | Y56: 1350000 | Z56: =DATABASE_Table[[#This Row],[Sell price (Total)]]-DATABASE_Table[[#This Row],[FF&E]]-DATABASE_Table[[#This Row],[Vista membership]] -> 1350000 | AC56: Ana Damásio | AD56: Carla Veiga | AE56: Springs Els Club - *Vilamoura | AF56: The new chapter of Vilamoura begins here. Join the inner circle with Club access to golf, sport, equestrian & beach life. | AG56: Gym, Spa, Lazy River, Private Pools, Outdoor Areas, Smart Home Technology, Tennis Court, Clubhouse, Private Parking, Vista Membership | AH56: Projeto de excelência com vista direta para o Els Club, o campo de Golf mais exclusivo de Vilamoura; Club-house com piscina e lazy river; Spa e campos de tenis / padel disponíveis; Possibilidade de rentabilidade através de exploração turística com gestão profissional (Details) | AI56: Promontório | AJ56: Springs - At the Els
A57: THE UNCOMMON | B57: Vilamoura | C57: 10 | D57: Vilamoura, Algarve | E57: T3 | F57: 222.7 | H57: 1 | J57: 82.9 | O57: 139.8 | Q57: AVAILABLE | R57: =DATABASE_Table[[#This Row],[Inicial Asking Price (€) (Total)]]-DATABASE_Table[[#This Row],[Vista membership]]-DATABASE_Table[[#This Row],[FF&E]] -> 2250000 | S57: 2330000 | T57: 2410000 | U57: 50000 | V57: 30000 | W57: =DATABASE_Table[[#This Row],[Current Asking price( Total)]]-DATABASE_Table[[#This Row],[Vista membership]]-DATABASE_Table[[#This Row],[FF&E]] -> 2330000 | Y57: 2410000 | Z57: =DATABASE_Table[[#This Row],[Sell price (Total)]]-DATABASE_Table[[#This Row],[FF&E]]-DATABASE_Table[[#This Row],[Vista membership]] -> 2330000 | AC57: Ana Damásio | AD57: Eduardo Lopes | AE57: TBD | AF57: The Uncommon is a front-row sea view masterpiece in Vilamoura, where vibrant energy meets serene coastal living. With an exclusive design and elevated services, in this touristic and residential project every moment feels uniquely exceptional. | AG57: Condo Pool, Outdoor Areas, Underground Parking, Reception, Concierge, Vista Membership | AH57: Apartamentos com exploração turística profissional e possibilidade de uso pelos proprietários; Amenities de excelência; Vistas excepcionais e em primeira linha de mar; Rooftops com plunge pool privativos. | AI57: NLA | AJ57: The Uncommon
A58: THE UNCOMMON | B58: Vilamoura | C58: 101 | D58: Vilamoura, Algarve | E58: T3 | F58: 183.9 | H58: 1 | J58: 34.3 | O58: 149.6 | Q58: AVAILABLE | R58: =DATABASE_Table[[#This Row],[Inicial Asking Price (€) (Total)]]-DATABASE_Table[[#This Row],[Vista membership]]-DATABASE_Table[[#This Row],[FF&E]] -> 1910000 | S58: 1990000 | T58: 2070000 | U58: 50000 | V58: 30000 | W58: =DATABASE_Table[[#This Row],[Current Asking price( Total)]]-DATABASE_Table[[#This Row],[Vista membership]]-DATABASE_Table[[#This Row],[FF&E]] -> 1990000 | Y58: 2070000 | Z58: =DATABASE_Table[[#This Row],[Sell price (Total)]]-DATABASE_Table[[#This Row],[FF&E]]-DATABASE_Table[[#This Row],[Vista membership]] -> 1990000 | AC58: Ana Damásio | AD58: Eduardo Lopes | AE58: TBD | AF58: The Uncommon is a front-row sea view masterpiece in Vilamoura, where vibrant energy meets serene coastal living. With an exclusive design and elevated services, in this touristic and residential project every moment feels uniquely exceptional. | AG58: Condo Pool, Outdoor Areas, Underground Parking, Reception, Concierge, Vista Membership | AH58: Apartamentos com exploração turística profissional e possibilidade de uso pelos proprietários; Amenities de excelência; Vistas excepcionais e em primeira linha de mar; Rooftops com plunge pool privativos. | AI58: NLA | AJ58: The Uncommon
A59: Aroeira - HOTEL APARTMENTS | B59: Center | C59: 229A | D59: Herdade da Aroeira, Almada | E59: 1-BR | F59: 60.2 | H59: 1 | J59: 3.9 | O59: 56.3 | Q59: AVAILABLE | R59: =DATABASE_Table[[#This Row],[Inicial Asking Price (€) (Total)]]-DATABASE_Table[[#This Row],[Vista membership]]-DATABASE_Table[[#This Row],[FF&E]] -> 390000 | S59: 425000 | T59: 425000 | V59: 35000 | W59: =DATABASE_Table[[#This Row],[Current Asking price( Total)]]-DATABASE_Table[[#This Row],[Vista membership]]-DATABASE_Table[[#This Row],[FF&E]] -> 390000 | Z59: =DATABASE_Table[[#This Row],[Sell price (Total)]]-DATABASE_Table[[#This Row],[FF&E]]-DATABASE_Table[[#This Row],[Vista membership]] -> -35000 | AB59: 47118 | AC59: João Gameiro | AD59: Miguel Ribeiro | AE59: https://www.aroeiracollections.com/ | AF59: Aroeira Collections by Missoni: Elegance inspired by iconic design, set beside the renowned PGA golf course — where luxury living meets the rhythm of the coast. | AG59: Gym, Spa, Condo Pool, Private Pools, Tennis & Padel Courts, Outdoor Areas, Smart Home Technology, Private Parking, Reception, Missoni Interiors, PGA Golf Course | AH59: Primeiro grande projeto com uma marca de lifestyle/moda em Portugal - Missoni; Localização de excelência dentro da Herdade da Aroeira, a 30' de Lisboa e 10' das melhores praias do país; Design com contributo de arquitetos de renome; Excelente oportunidade de investimento; Junto ao campo de golfe PGA Aroeira; Diversas amenities como: Piscina interior e exterior, campos de tenis e padel, ginásio, spa e restaurante. | AI59: Ana Costa, João Favila, Pedro Domingos | AJ59: Aroeira Collections
A60: Aroeira - HOTEL APARTMENTS | B60: Center | C60: 230A | D60: Herdade da Aroeira, Almada | E60: 1-BR | F60: 60.2 | H60: 1 | J60: 3.9 | O60: 56.3 | Q60: AVAILABLE | R60: =DATABASE_Table[[#This Row],[Inicial Asking Price (€) (Total)]]-DATABASE_Table[[#This Row],[Vista membership]]-DATABASE_Table[[#This Row],[FF&E]] -> 390000 | S60: 425000 | T60: 425000 | V60: 35000 | W60: =DATABASE_Table[[#This Row],[Current Asking price( Total)]]-DATABASE_Table[[#This Row],[Vista membership]]-DATABASE_Table[[#This Row],[FF&E]] -> 390000 | Z60: =DATABASE_Table[[#This Row],[Sell price (Total)]]-DATABASE_Table[[#This Row],[FF&E]]-DATABASE_Table[[#This Row],[Vista membership]] -> -35000 | AB60: 47118 | AC60: João Gameiro | AD60: Miguel Ribeiro | AE60: https://www.aroeiracollections.com/ | AF60: Aroeira Collections by Missoni: Elegance inspired by iconic design, set beside the renowned PGA golf course — where luxury living meets the rhythm of the coast. | AG60: Gym, Spa, Condo Pool, Private Pools, Tennis & Padel Courts, Outdoor Areas, Smart Home Technology, Private Parking, Reception, Missoni Interiors, PGA Golf Course | AH60: Primeiro grande projeto com uma marca de lifestyle/moda em Portugal - Missoni; Localização de excelência dentro da Herdade da Aroeira, a 30' de Lisboa e 10' das melhores praias do país; Design com contributo de arquitetos de renome; Excelente oportunidade de investimento; Junto ao campo de golfe PGA Aroeira; Diversas amenities como: Piscina interior e exterior, campos de tenis e padel, ginásio, spa e restaurante. | AI60: Ana Costa, João Favila, Pedro Domingos | AJ60: Aroeira Collections
A61: Aroeira - HOTEL APARTMENTS | B61: Center | C61: 231A | D61: Herdade da Aroeira, Almada | E61: 1-BR | F61: 60.2 | H61: 1 | J61: 3.9 | O61: 56.3 | Q61: AVAILABLE | R61: =DATABASE_Table[[#This Row],[Inicial Asking Price (€) (Total)]]-DATABASE_Table[[#This Row],[Vista membership]]-DATABASE_Table[[#This Row],[FF&E]] -> 390000 | S61: 425000 | T61: 425000 | V61: 35000 | W61: =DATABASE_Table[[#This Row],[Current Asking price( Total)]]-DATABASE_Table[[#This Row],[Vista membership]]-DATABASE_Table[[#This Row],[FF&E]] -> 390000 | Z61: =DATABASE_Table[[#This Row],[Sell price (Total)]]-DATABASE_Table[[#This Row],[FF&E]]-DATABASE_Table[[#This Row],[Vista membership]] -> -35000 | AB61: 47118 | AC61: João Gameiro | AD61: Miguel Ribeiro | AE61: https://www.aroeiracollections.com/ | AF61: Aroeira Collections by Missoni: Elegance inspired by iconic design, set beside the renowned PGA golf course — where luxury living meets the rhythm of the coast. | AG61: Gym, Spa, Condo Pool, Private Pools, Tennis & Padel Courts, Outdoor Areas, Smart Home Technology, Private Parking, Reception, Missoni Interiors, PGA Golf Course | AH61: Primeiro grande projeto com uma marca de lifestyle/moda em Portugal - Missoni; Localização de excelência dentro da Herdade da Aroeira, a 30' de Lisboa e 10' das melhores praias do país; Design com contributo de arquitetos de renome; Excelente oportunidade de investimento; Junto ao campo de golfe PGA Aroeira; Diversas amenities como: Piscina interior e exterior, campos de tenis e padel, ginásio, spa e restaurante. | AI61: Ana Costa, João Favila, Pedro Domingos | AJ61: Aroeira Collections
A62: Aroeira - HOTEL APARTMENTS | B62: Center | C62: 232A | D62: Herdade da Aroeira, Almada | E62: 1-BR | F62: 60.2 | H62: 1 | J62: 3.9 | O62: 56.3 | Q62: AVAILABLE | R62: =DATABASE_Table[[#This Row],[Inicial Asking Price (€) (Total)]]-DATABASE_Table[[#This Row],[Vista membership]]-DATABASE_Table[[#This Row],[FF&E]] -> 390000 | S62: 425000 | T62: 425000 | V62: 35000 | W62: =DATABASE_Table[[#This Row],[Current Asking price( Total)]]-DATABASE_Table[[#This Row],[Vista membership]]-DATABASE_Table[[#This Row],[FF&E]] -> 390000 | Z62: =DATABASE_Table[[#This Row],[Sell price (Total)]]-DATABASE_Table[[#This Row],[FF&E]]-DATABASE_Table[[#This Row],[Vista membership]] -> -35000 | AB62: 47118 | AC62: João Gameiro | AD62: Miguel Ribeiro | AE62: https://www.aroeiracollections.com/ | AF62: Aroeira Collections by Missoni: Elegance inspired by iconic design, set beside the renowned PGA golf course — where luxury living meets the rhythm of the coast. | AG62: Gym, Spa, Condo Pool, Private Pools, Tennis & Padel Courts, Outdoor Areas, Smart Home Technology, Private Parking, Reception, Missoni Interiors, PGA Golf Course | AH62: Primeiro grande projeto com uma marca de lifestyle/moda em Portugal - Missoni; Localização de excelência dentro da Herdade da Aroeira, a 30' de Lisboa e 10' das melhores praias do país; Design com contributo de arquitetos de renome; Excelente oportunidade de investimento; Junto ao campo de golfe PGA Aroeira; Diversas amenities como: Piscina interior e exterior, campos de tenis e padel, ginásio, spa e restaurante. | AI62: Ana Costa, João Favila, Pedro Domingos | AJ62: Aroeira Collections
A63: Aroeira - HOTEL APARTMENTS | B63: Center | C63: 233A | D63: Herdade da Aroeira, Almada | E63: 1-BR | F63: 60.2 | H63: 1 | J63: 3.9 | O63: 56.3 | Q63: AVAILABLE | R63: =DATABASE_Table[[#This Row],[Inicial Asking Price (€) (Total)]]-DATABASE_Table[[#This Row],[Vista membership]]-DATABASE_Table[[#This Row],[FF&E]] -> 390000 | S63: 425000 | T63: 425000 | V63: 35000 | W63: =DATABASE_Table[[#This Row],[Current Asking price( Total)]]-DATABASE_Table[[#This Row],[Vista membership]]-DATABASE_Table[[#This Row],[FF&E]] -> 390000 | Z63: =DATABASE_Table[[#This Row],[Sell price (Total)]]-DATABASE_Table[[#This Row],[FF&E]]-DATABASE_Table[[#This Row],[Vista membership]] -> -35000 | AB63: 47118 | AC63: João Gameiro | AD63: Miguel Ribeiro | AE63: https://www.aroeiracollections.com/ | AF63: Aroeira Collections by Missoni: Elegance inspired by iconic design, set beside the renowned PGA golf course — where luxury living meets the rhythm of the coast. | AG63: Gym, Spa, Condo Pool, Private Pools, Tennis & Padel Courts, Outdoor Areas, Smart Home Technology, Private Parking, Reception, Missoni Interiors, PGA Golf Course | AH63: Primeiro grande projeto com uma marca de lifestyle/moda em Portugal - Missoni; Localização de excelência dentro da Herdade da Aroeira, a 30' de Lisboa e 10' das melhores praias do país; Design com contributo de arquitetos de renome; Excelente oportunidade de investimento; Junto ao campo de golfe PGA Aroeira; Diversas amenities como: Piscina interior e exterior, campos de tenis e padel, ginásio, spa e restaurante. | AI63: Ana Costa, João Favila, Pedro Domingos | AJ63: Aroeira Collections
A64: Aroeira - HOUSES | B64: Center | C64: 06B | D64: Herdade da Aroeira, Almada | E64: T2 | F64: 196.4 | H64: 1 | M64: 33 | N64: 26 | O64: 137.4 | Q64: PSPA | R64: =DATABASE_Table[[#This Row],[Inicial Asking Price (€) (Total)]]-DATABASE_Table[[#This Row],[Vista membership]]-DATABASE_Table[[#This Row],[FF&E]] -> 1100000 | S64: 1100000 | T64: 1100000 | V64: 0 | W64: =DATABASE_Table[[#This Row],[Current Asking price( Total)]]-DATABASE_Table[[#This Row],[Vista membership]]-DATABASE_Table[[#This Row],[FF&E]] -> 1100000 | X64: 0 | Y64: 1100000 | Z64: =DATABASE_Table[[#This Row],[Sell price (Total)]]-DATABASE_Table[[#This Row],[FF&E]]-DATABASE_Table[[#This Row],[Vista membership]] -> 1100000 | AA64: 46038 | AB64: 47118 | AC64: João Gameiro | AD64: Miguel Ribeiro | AE64: https://www.aroeiracollections.com/ | AF64: Aroeira Collections by Missoni: Elegance inspired by iconic design, set beside the renowned PGA golf course — where luxury living meets the rhythm of the coast. | AG64: Gym, Spa, Condo Pool, Private Pools, Tennis & Padel Courts, Outdoor Areas, Smart Home Technology, Private Parking, Reception, Missoni Interiors, PGA Golf Course | AH64: Primeiro grande projeto com uma marca de lifestyle/moda em Portugal - Missoni; Localização de excelência dentro da Herdade da Aroeira, a 30' de Lisboa e 10' das melhores praias do país; Design com contributo de arquitetos de renome; Excelente oportunidade de investimento; Junto ao campo de golfe PGA Aroeira; Diversas amenities como: Piscina interior e exterior, campos de tenis e padel, ginásio, spa e restaurante. | AI64: Ana Costa, João Favila, Pedro Domingos | AJ64: Aroeira Collections
A65: Aroeira - HOUSES | B65: Center | C65: 07B | D65: Herdade da Aroeira, Almada | E65: T2 | F65: 167 | H65: 1 | M65: 31 | N65: 20 | O65: 116 | Q65: PSPA | R65: =DATABASE_Table[[#This Row],[Inicial Asking Price (€) (Total)]]-DATABASE_Table[[#This Row],[Vista membership]]-DATABASE_Table[[#This Row],[FF&E]] -> 910000 | S65: 910000 | T65: 940000 | V65: 0 | W65: =DATABASE_Table[[#This Row],[Current Asking price( Total)]]-DATABASE_Table[[#This Row],[Vista membership]]-DATABASE_Table[[#This Row],[FF&E]] -> 940000 | X65: 0 | Y65: 940000 | Z65: =DATABASE_Table[[#This Row],[Sell price (Total)]]-DATABASE_Table[[#This Row],[FF&E]]-DATABASE_Table[[#This Row],[Vista membership]] -> 940000 | AA65: 45989 | AB65: 47118 | AC65: João Gameiro | AD65: Miguel Ribeiro | AE65: https://www.aroeiracollections.com/ | AF65: Aroeira Collections by Missoni: Elegance inspired by iconic design, set beside the renowned PGA golf course — where luxury living meets the rhythm of the coast. | AG65: Gym, Spa, Condo Pool, Private Pools, Tennis & Padel Courts, Outdoor Areas, Smart Home Technology, Private Parking, Reception, Missoni Interiors, PGA Golf Course | AH65: Primeiro grande projeto com uma marca de lifestyle/moda em Portugal - Missoni; Localização de excelência dentro da Herdade da Aroeira, a 30' de Lisboa e 10' das melhores praias do país; Design com contributo de arquitetos de renome; Excelente oportunidade de investimento; Junto ao campo de golfe PGA Aroeira; Diversas amenities como: Piscina interior e exterior, campos de tenis e padel, ginásio, spa e restaurante. | AI65: Ana Costa, João Favila, Pedro Domingos | AJ65: Aroeira Collections
A66: Aroeira - HOTEL APARTMENTS | B66: Center | C66: 121A | D66: Herdade da Aroeira, Almada | E66: 1-BR | F66: 65 | H66: 1 | J66: 8.7 | O66: 56.3 | Q66: RESERVED | R66: =DATABASE_Table[[#This Row],[Inicial Asking Price (€) (Total)]]-DATABASE_Table[[#This Row],[Vista membership]]-DATABASE_Table[[#This Row],[FF&E]] -> 395000 | S66: 430000 | T66: 430000 | V66: 35000 | W66: =DATABASE_Table[[#This Row],[Current Asking price( Total)]]-DATABASE_Table[[#This Row],[Vista membership]]-DATABASE_Table[[#This Row],[FF&E]] -> 395000 | X66: 0 | Y66: 430000 | Z66: =DATABASE_Table[[#This Row],[Sell price (Total)]]-DATABASE_Table[[#This Row],[FF&E]]-DATABASE_Table[[#This Row],[Vista membership]] -> 395000 | AA66: 46136 | AB66: 47118 | AC66: João Gameiro | AD66: Miguel Ribeiro | AE66: https://www.aroeiracollections.com/ | AF66: Aroeira Collections by Missoni: Elegance inspired by iconic design, set beside the renowned PGA golf course — where luxury living meets the rhythm of the coast. | AG66: Gym, Spa, Condo Pool, Private Pools, Tennis & Padel Courts, Outdoor Areas, Smart Home Technology, Private Parking, Reception, Missoni Interiors, PGA Golf Course | AH66: Primeiro grande projeto com uma marca de lifestyle/moda em Portugal - Missoni; Localização de excelência dentro da Herdade da Aroeira, a 30' de Lisboa e 10' das melhores praias do país; Design com contributo de arquitetos de renome; Excelente oportunidade de investimento; Junto ao campo de golfe PGA Aroeira; Diversas amenities como: Piscina interior e exterior, campos de tenis e padel, ginásio, spa e restaurante. | AI66: Ana Costa, João Favila, Pedro Domingos | AJ66: Aroeira Collections
A67: Aroeira - HOTEL APARTMENTS | B67: Center | C67: 117A | D67: Herdade da Aroeira, Almada | E67: 1-BR | F67: 65 | H67: 1 | J67: 8.7 | O67: 56.3 | Q67: AVAILABLE | R67: =DATABASE_Table[[#This Row],[Inicial Asking Price (€) (Total)]]-DATABASE_Table[[#This Row],[Vista membership]]-DATABASE_Table[[#This Row],[FF&E]] -> 395000 | S67: 430000 | T67: 430000 | V67: 35000 | W67: =DATABASE_Table[[#This Row],[Current Asking price( Total)]]-DATABASE_Table[[#This Row],[Vista membership]]-DATABASE_Table[[#This Row],[FF&E]] -> 395000 | Z67: =DATABASE_Table[[#This Row],[Sell price (Total)]]-DATABASE_Table[[#This Row],[FF&E]]-DATABASE_Table[[#This Row],[Vista membership]] -> -35000 | AB67: 47118 | AC67: João Gameiro | AD67: Miguel Ribeiro | AE67: https://www.aroeiracollections.com/ | AF67: Aroeira Collections by Missoni: Elegance inspired by iconic design, set beside the renowned PGA golf course — where luxury living meets the rhythm of the coast. | AG67: Gym, Spa, Condo Pool, Private Pools, Tennis & Padel Courts, Outdoor Areas, Smart Home Technology, Private Parking, Reception, Missoni Interiors, PGA Golf Course | AH67: Primeiro grande projeto com uma marca de lifestyle/moda em Portugal - Missoni; Localização de excelência dentro da Herdade da Aroeira, a 30' de Lisboa e 10' das melhores praias do país; Design com contributo de arquitetos de renome; Excelente oportunidade de investimento; Junto ao campo de golfe PGA Aroeira; Diversas amenities como: Piscina interior e exterior, campos de tenis e padel, ginásio, spa e restaurante. | AI67: Ana Costa, João Favila, Pedro Domingos | AJ67: Aroeira Collections
A68: Aroeira - HOTEL APARTMENTS | B68: Center | C68: 118A | D68: Herdade da Aroeira, Almada | E68: 1-BR | F68: 65 | H68: 1 | J68: 8.7 | O68: 56.3 | Q68: AVAILABLE | R68: =DATABASE_Table[[#This Row],[Inicial Asking Price (€) (Total)]]-DATABASE_Table[[#This Row],[Vista membership]]-DATABASE_Table[[#This Row],[FF&E]] -> 395000 | S68: 430000 | T68: 430000 | V68: 35000 | W68: =DATABASE_Table[[#This Row],[Current Asking price( Total)]]-DATABASE_Table[[#This Row],[Vista membership]]-DATABASE_Table[[#This Row],[FF&E]] -> 395000 | Z68: =DATABASE_Table[[#This Row],[Sell price (Total)]]-DATABASE_Table[[#This Row],[FF&E]]-DATABASE_Table[[#This Row],[Vista membership]] -> -35000 | AB68: 47118 | AC68: João Gameiro | AD68: Miguel Ribeiro | AE68: https://www.aroeiracollections.com/ | AF68: Aroeira Collections by Missoni: Elegance inspired by iconic design, set beside the renowned PGA golf course — where luxury living meets the rhythm of the coast. | AG68: Gym, Spa, Condo Pool, Private Pools, Tennis & Padel Courts, Outdoor Areas, Smart Home Technology, Private Parking, Reception, Missoni Interiors, PGA Golf Course | AH68: Primeiro grande projeto com uma marca de lifestyle/moda em Portugal - Missoni; Localização de excelência dentro da Herdade da Aroeira, a 30' de Lisboa e 10' das melhores praias do país; Design com contributo de arquitetos de renome; Excelente oportunidade de investimento; Junto ao campo de golfe PGA Aroeira; Diversas amenities como: Piscina interior e exterior, campos de tenis e padel, ginásio, spa e restaurante. | AI68: Ana Costa, João Favila, Pedro Domingos | AJ68: Aroeira Collections
A69: Aroeira - HOTEL APARTMENTS | B69: Center | C69: 120A | D69: Herdade da Aroeira, Almada | E69: 1-BR | F69: 65 | H69: 1 | J69: 8.7 | O69: 56.3 | Q69: AVAILABLE | R69: =DATABASE_Table[[#This Row],[Inicial Asking Price (€) (Total)]]-DATABASE_Table[[#This Row],[Vista membership]]-DATABASE_Table[[#This Row],[FF&E]] -> 395000 | S69: 430000 | T69: 430000 | V69: 35000 | W69: =DATABASE_Table[[#This Row],[Current Asking price( Total)]]-DATABASE_Table[[#This Row],[Vista membership]]-DATABASE_Table[[#This Row],[FF&E]] -> 395000 | Z69: =DATABASE_Table[[#This Row],[Sell price (Total)]]-DATABASE_Table[[#This Row],[FF&E]]-DATABASE_Table[[#This Row],[Vista membership]] -> -35000 | AB69: 47118 | AC69: João Gameiro | AD69: Miguel Ribeiro | AE69: https://www.aroeiracollections.com/ | AF69: Aroeira Collections by Missoni: Elegance inspired by iconic design, set beside the renowned PGA golf course — where luxury living meets the rhythm of the coast. | AG69: Gym, Spa, Condo Pool, Private Pools, Tennis & Padel Courts, Outdoor Areas, Smart Home Technology, Private Parking, Reception, Missoni Interiors, PGA Golf Course | AH69: Primeiro grande projeto com uma marca de lifestyle/moda em Portugal - Missoni; Localização de excelência dentro da Herdade da Aroeira, a 30' de Lisboa e 10' das melhores praias do país; Design com contributo de arquitetos de renome; Excelente oportunidade de investimento; Junto ao campo de golfe PGA Aroeira; Diversas amenities como: Piscina interior e exterior, campos de tenis e padel, ginásio, spa e restaurante. | AI69: Ana Costa, João Favila, Pedro Domingos | AJ69: Aroeira Collections
A70: Aroeira - HOTEL APARTMENTS | B70: Center | C70: 122A | D70: Herdade da Aroeira, Almada | E70: 1-BR | F70: 65 | H70: 1 | J70: 8.7 | O70: 56.3 | Q70: AVAILABLE | R70: =DATABASE_Table[[#This Row],[Inicial Asking Price (€) (Total)]]-DATABASE_Table[[#This Row],[Vista membership]]-DATABASE_Table[[#This Row],[FF&E]] -> 395000 | S70: 430000 | T70: 430000 | V70: 35000 | W70: =DATABASE_Table[[#This Row],[Current Asking price( Total)]]-DATABASE_Table[[#This Row],[Vista membership]]-DATABASE_Table[[#This Row],[FF&E]] -> 395000 | Z70: =DATABASE_Table[[#This Row],[Sell price (Total)]]-DATABASE_Table[[#This Row],[FF&E]]-DATABASE_Table[[#This Row],[Vista membership]] -> -35000 | AB70: 47118 | AC70: João Gameiro | AD70: Miguel Ribeiro | AE70: https://www.aroeiracollections.com/ | AF70: Aroeira Collections by Missoni: Elegance inspired by iconic design, set beside the renowned PGA golf course — where luxury living meets the rhythm of the coast. | AG70: Gym, Spa, Condo Pool, Private Pools, Tennis & Padel Courts, Outdoor Areas, Smart Home Technology, Private Parking, Reception, Missoni Interiors, PGA Golf Course | AH70: Primeiro grande projeto com uma marca de lifestyle/moda em Portugal - Missoni; Localização de excelência dentro da Herdade da Aroeira, a 30' de Lisboa e 10' das melhores praias do país; Design com contributo de arquitetos de renome; Excelente oportunidade de investimento; Junto ao campo de golfe PGA Aroeira; Diversas amenities como: Piscina interior e exterior, campos de tenis e padel, ginásio, spa e restaurante. | AI70: Ana Costa, João Favila, Pedro Domingos | AJ70: Aroeira Collections
A71: Aroeira - HOTEL APARTMENTS | B71: Center | C71: 338A | D71: Herdade da Aroeira, Almada | E71: 1-BR | F71: 60.2 | H71: 1 | J71: 3.9 | O71: 56.3 | Q71: AVAILABLE | R71: =DATABASE_Table[[#This Row],[Inicial Asking Price (€) (Total)]]-DATABASE_Table[[#This Row],[Vista membership]]-DATABASE_Table[[#This Row],[FF&E]] -> 395000 | S71: 430000 | T71: 430000 | V71: 35000 | W71: =DATABASE_Table[[#This Row],[Current Asking price( Total)]]-DATABASE_Table[[#This Row],[Vista membership]]-DATABASE_Table[[#This Row],[FF&E]] -> 395000 | Z71: =DATABASE_Table[[#This Row],[Sell price (Total)]]-DATABASE_Table[[#This Row],[FF&E]]-DATABASE_Table[[#This Row],[Vista membership]] -> -35000 | AB71: 47118 | AC71: João Gameiro | AD71: Miguel Ribeiro | AE71: https://www.aroeiracollections.com/ | AF71: Aroeira Collections by Missoni: Elegance inspired by iconic design, set beside the renowned PGA golf course — where luxury living meets the rhythm of the coast. | AG71: Gym, Spa, Condo Pool, Private Pools, Tennis & Padel Courts, Outdoor Areas, Smart Home Technology, Private Parking, Reception, Missoni Interiors, PGA Golf Course | AH71: Primeiro grande projeto com uma marca de lifestyle/moda em Portugal - Missoni; Localização de excelência dentro da Herdade da Aroeira, a 30' de Lisboa e 10' das melhores praias do país; Design com contributo de arquitetos de renome; Excelente oportunidade de investimento; Junto ao campo de golfe PGA Aroeira; Diversas amenities como: Piscina interior e exterior, campos de tenis e padel, ginásio, spa e restaurante. | AI71: Ana Costa, João Favila, Pedro Domingos | AJ71: Aroeira Collections
A72: Aroeira - HOTEL APARTMENTS | B72: Center | C72: 339A | D72: Herdade da Aroeira, Almada | E72: 1-BR | F72: 60.2 | H72: 1 | J72: 3.9 | O72: 56.3 | Q72: AVAILABLE | R72: =DATABASE_Table[[#This Row],[Inicial Asking Price (€) (Total)]]-DATABASE_Table[[#This Row],[Vista membership]]-DATABASE_Table[[#This Row],[FF&E]] -> 395000 | S72: 430000 | T72: 430000 | V72: 35000 | W72: =DATABASE_Table[[#This Row],[Current Asking price( Total)]]-DATABASE_Table[[#This Row],[Vista membership]]-DATABASE_Table[[#This Row],[FF&E]] -> 395000 | Z72: =DATABASE_Table[[#This Row],[Sell price (Total)]]-DATABASE_Table[[#This Row],[FF&E]]-DATABASE_Table[[#This Row],[Vista membership]] -> -35000 | AB72: 47118 | AC72: João Gameiro | AD72: Miguel Ribeiro | AE72: https://www.aroeiracollections.com/ | AF72: Aroeira Collections by Missoni: Elegance inspired by iconic design, set beside the renowned PGA golf course — where luxury living meets the rhythm of the coast. | AG72: Gym, Spa, Condo Pool, Private Pools, Tennis & Padel Courts, Outdoor Areas, Smart Home Technology, Private Parking, Reception, Missoni Interiors, PGA Golf Course | AH72: Primeiro grande projeto com uma marca de lifestyle/moda em Portugal - Missoni; Localização de excelência dentro da Herdade da Aroeira, a 30' de Lisboa e 10' das melhores praias do país; Design com contributo de arquitetos de renome; Excelente oportunidade de investimento; Junto ao campo de golfe PGA Aroeira; Diversas amenities como: Piscina interior e exterior, campos de tenis e padel, ginásio, spa e restaurante. | AI72: Ana Costa, João Favila, Pedro Domingos | AJ72: Aroeira Collections
A73: Aroeira - HOTEL APARTMENTS | B73: Center | C73: 340A | D73: Herdade da Aroeira, Almada | E73: 1-BR | F73: 60.2 | H73: 1 | J73: 3.9 | O73: 56.3 | Q73: AVAILABLE | R73: =DATABASE_Table[[#This Row],[Inicial Asking Price (€) (Total)]]-DATABASE_Table[[#This Row],[Vista membership]]-DATABASE_Table[[#This Row],[FF&E]] -> 395000 | S73: 430000 | T73: 430000 | V73: 35000 | W73: =DATABASE_Table[[#This Row],[Current Asking price( Total)]]-DATABASE_Table[[#This Row],[Vista membership]]-DATABASE_Table[[#This Row],[FF&E]] -> 395000 | Z73: =DATABASE_Table[[#This Row],[Sell price (Total)]]-DATABASE_Table[[#This Row],[FF&E]]-DATABASE_Table[[#This Row],[Vista membership]] -> -35000 | AB73: 47118 | AC73: João Gameiro | AD73: Miguel Ribeiro | AE73: https://www.aroeiracollections.com/ | AF73: Aroeira Collections by Missoni: Elegance inspired by iconic design, set beside the renowned PGA golf course — where luxury living meets the rhythm of the coast. | AG73: Gym, Spa, Condo Pool, Private Pools, Tennis & Padel Courts, Outdoor Areas, Smart Home Technology, Private Parking, Reception, Missoni Interiors, PGA Golf Course | AH73: Primeiro grande projeto com uma marca de lifestyle/moda em Portugal - Missoni; Localização de excelência dentro da Herdade da Aroeira, a 30' de Lisboa e 10' das melhores praias do país; Design com contributo de arquitetos de renome; Excelente oportunidade de investimento; Junto ao campo de golfe PGA Aroeira; Diversas amenities como: Piscina interior e exterior, campos de tenis e padel, ginásio, spa e restaurante. | AI73: Ana Costa, João Favila, Pedro Domingos | AJ73: Aroeira Collections
A74: Aroeira - HOTEL APARTMENTS | B74: Center | C74: 341A | D74: Herdade da Aroeira, Almada | E74: 1-BR | F74: 60.2 | H74: 1 | J74: 3.9 | O74: 56.3 | Q74: AVAILABLE | R74: =DATABASE_Table[[#This Row],[Inicial Asking Price (€) (Total)]]-DATABASE_Table[[#This Row],[Vista membership]]-DATABASE_Table[[#This Row],[FF&E]] -> 395000 | S74: 430000 | T74: 430000 | V74: 35000 | W74: =DATABASE_Table[[#This Row],[Current Asking price( Total)]]-DATABASE_Table[[#This Row],[Vista membership]]-DATABASE_Table[[#This Row],[FF&E]] -> 395000 | Z74: =DATABASE_Table[[#This Row],[Sell price (Total)]]-DATABASE_Table[[#This Row],[FF&E]]-DATABASE_Table[[#This Row],[Vista membership]] -> -35000 | AB74: 47118 | AC74: João Gameiro | AD74: Miguel Ribeiro | AE74: https://www.aroeiracollections.com/ | AF74: Aroeira Collections by Missoni: Elegance inspired by iconic design, set beside the renowned PGA golf course — where luxury living meets the rhythm of the coast. | AG74: Gym, Spa, Condo Pool, Private Pools, Tennis & Padel Courts, Outdoor Areas, Smart Home Technology, Private Parking, Reception, Missoni Interiors, PGA Golf Course | AH74: Primeiro grande projeto com uma marca de lifestyle/moda em Portugal - Missoni; Localização de excelência dentro da Herdade da Aroeira, a 30' de Lisboa e 10' das melhores praias do país; Design com contributo de arquitetos de renome; Excelente oportunidade de investimento; Junto ao campo de golfe PGA Aroeira; Diversas amenities como: Piscina interior e exterior, campos de tenis e padel, ginásio, spa e restaurante. | AI74: Ana Costa, João Favila, Pedro Domingos | AJ74: Aroeira Collections
A75: Aroeira - HOTEL APARTMENTS | B75: Center | C75: 342A | D75: Herdade da Aroeira, Almada | E75: 1-BR | F75: 60.2 | H75: 1 | J75: 3.9 | O75: 56.3 | Q75: AVAILABLE | R75: =DATABASE_Table[[#This Row],[Inicial Asking Price (€) (Total)]]-DATABASE_Table[[#This Row],[Vista membership]]-DATABASE_Table[[#This Row],[FF&E]] -> 395000 | S75: 430000 | T75: 430000 | V75: 35000 | W75: =DATABASE_Table[[#This Row],[Current Asking price( Total)]]-DATABASE_Table[[#This Row],[Vista membership]]-DATABASE_Table[[#This Row],[FF&E]] -> 395000 | Z75: =DATABASE_Table[[#This Row],[Sell price (Total)]]-DATABASE_Table[[#This Row],[FF&E]]-DATABASE_Table[[#This Row],[Vista membership]] -> -35000 | AB75: 47118 | AC75: João Gameiro | AD75: Miguel Ribeiro | AE75: https://www.aroeiracollections.com/ | AF75: Aroeira Collections by Missoni: Elegance inspired by iconic design, set beside the renowned PGA golf course — where luxury living meets the rhythm of the coast. | AG75: Gym, Spa, Condo Pool, Private Pools, Tennis & Padel Courts, Outdoor Areas, Smart Home Technology, Private Parking, Reception, Missoni Interiors, PGA Golf Course | AH75: Primeiro grande projeto com uma marca de lifestyle/moda em Portugal - Missoni; Localização de excelência dentro da Herdade da Aroeira, a 30' de Lisboa e 10' das melhores praias do país; Design com contributo de arquitetos de renome; Excelente oportunidade de investimento; Junto ao campo de golfe PGA Aroeira; Diversas amenities como: Piscina interior e exterior, campos de tenis e padel, ginásio, spa e restaurante. | AI75: Ana Costa, João Favila, Pedro Domingos | AJ75: Aroeira Collections
A76: Aroeira - HOTEL APARTMENTS | B76: Center | C76: 202A | D76: Herdade da Aroeira, Almada | E76: 1-BR | F76: 65 | H76: 1 | J76: 8.7 | O76: 56.3 | Q76: AVAILABLE | R76: =DATABASE_Table[[#This Row],[Inicial Asking Price (€) (Total)]]-DATABASE_Table[[#This Row],[Vista membership]]-DATABASE_Table[[#This Row],[FF&E]] -> 400000 | S76: 435000 | T76: 435000 | V76: 35000 | W76: =DATABASE_Table[[#This Row],[Current Asking price( Total)]]-DATABASE_Table[[#This Row],[Vista membership]]-DATABASE_Table[[#This Row],[FF&E]] -> 400000 | Z76: =DATABASE_Table[[#This Row],[Sell price (Total)]]-DATABASE_Table[[#This Row],[FF&E]]-DATABASE_Table[[#This Row],[Vista membership]] -> -35000 | AB76: 47118 | AC76: João Gameiro | AD76: Miguel Ribeiro | AE76: https://www.aroeiracollections.com/ | AF76: Aroeira Collections by Missoni: Elegance inspired by iconic design, set beside the renowned PGA golf course — where luxury living meets the rhythm of the coast. | AG76: Gym, Spa, Condo Pool, Private Pools, Tennis & Padel Courts, Outdoor Areas, Smart Home Technology, Private Parking, Reception, Missoni Interiors, PGA Golf Course | AH76: Primeiro grande projeto com uma marca de lifestyle/moda em Portugal - Missoni; Localização de excelência dentro da Herdade da Aroeira, a 30' de Lisboa e 10' das melhores praias do país; Design com contributo de arquitetos de renome; Excelente oportunidade de investimento; Junto ao campo de golfe PGA Aroeira; Diversas amenities como: Piscina interior e exterior, campos de tenis e padel, ginásio, spa e restaurante. | AI76: Ana Costa, João Favila, Pedro Domingos | AJ76: Aroeira Collections
A77: Aroeira - HOTEL APARTMENTS | B77: Center | C77: 203A | D77: Herdade da Aroeira, Almada | E77: 1-BR | F77: 65 | H77: 1 | J77: 8.7 | O77: 56.3 | Q77: AVAILABLE | R77: =DATABASE_Table[[#This Row],[Inicial Asking Price (€) (Total)]]-DATABASE_Table[[#This Row],[Vista membership]]-DATABASE_Table[[#This Row],[FF&E]] -> 400000 | S77: 435000 | T77: 435000 | V77: 35000 | W77: =DATABASE_Table[[#This Row],[Current Asking price( Total)]]-DATABASE_Table[[#This Row],[Vista membership]]-DATABASE_Table[[#This Row],[FF&E]] -> 400000 | Z77: =DATABASE_Table[[#This Row],[Sell price (Total)]]-DATABASE_Table[[#This Row],[FF&E]]-DATABASE_Table[[#This Row],[Vista membership]] -> -35000 | AB77: 47118 | AC77: João Gameiro | AD77: Miguel Ribeiro | AE77: https://www.aroeiracollections.com/ | AF77: Aroeira Collections by Missoni: Elegance inspired by iconic design, set beside the renowned PGA golf course — where luxury living meets the rhythm of the coast. | AG77: Gym, Spa, Condo Pool, Private Pools, Tennis & Padel Courts, Outdoor Areas, Smart Home Technology, Private Parking, Reception, Missoni Interiors, PGA Golf Course | AH77: Primeiro grande projeto com uma marca de lifestyle/moda em Portugal - Missoni; Localização de excelência dentro da Herdade da Aroeira, a 30' de Lisboa e 10' das melhores praias do país; Design com contributo de arquitetos de renome; Excelente oportunidade de investimento; Junto ao campo de golfe PGA Aroeira; Diversas amenities como: Piscina interior e exterior, campos de tenis e padel, ginásio, spa e restaurante. | AI77: Ana Costa, João Favila, Pedro Domingos | AJ77: Aroeira Collections
A78: Aroeira - HOTEL APARTMENTS | B78: Center | C78: 204A | D78: Herdade da Aroeira, Almada | E78: 1-BR | F78: 65 | H78: 1 | J78: 8.7 | O78: 56.3 | Q78: AVAILABLE | R78: =DATABASE_Table[[#This Row],[Inicial Asking Price (€) (Total)]]-DATABASE_Table[[#This Row],[Vista membership]]-DATABASE_Table[[#This Row],[FF&E]] -> 400000 | S78: 435000 | T78: 435000 | V78: 35000 | W78: =DATABASE_Table[[#This Row],[Current Asking price( Total)]]-DATABASE_Table[[#This Row],[Vista membership]]-DATABASE_Table[[#This Row],[FF&E]] -> 400000 | Z78: =DATABASE_Table[[#This Row],[Sell price (Total)]]-DATABASE_Table[[#This Row],[FF&E]]-DATABASE_Table[[#This Row],[Vista membership]] -> -35000 | AB78: 47118 | AC78: João Gameiro | AD78: Miguel Ribeiro | AE78: https://www.aroeiracollections.com/ | AF78: Aroeira Collections by Missoni: Elegance inspired by iconic design, set beside the renowned PGA golf course — where luxury living meets the rhythm of the coast. | AG78: Gym, Spa, Condo Pool, Private Pools, Tennis & Padel Courts, Outdoor Areas, Smart Home Technology, Private Parking, Reception, Missoni Interiors, PGA Golf Course | AH78: Primeiro grande projeto com uma marca de lifestyle/moda em Portugal - Missoni; Localização de excelência dentro da Herdade da Aroeira, a 30' de Lisboa e 10' das melhores praias do país; Design com contributo de arquitetos de renome; Excelente oportunidade de investimento; Junto ao campo de golfe PGA Aroeira; Diversas amenities como: Piscina interior e exterior, campos de tenis e padel, ginásio, spa e restaurante. | AI78: Ana Costa, João Favila, Pedro Domingos | AJ78: Aroeira Collections
... A82: Aroeira - HOTEL APARTMENTS | B82: Center | C82: 208A | D82: Herdade da Aroeira, Almada | E82: 1-BR | F82: 65 | H82: 1 | J82: 8.7 | O82: 56.3 | Q82: AVAILABLE | R82: =DATABASE_Table[[#This Row],[Inicial Asking Price (€) (Total)]]-DATABASE_Table[[#This Row],[Vista membership]]-DATABASE_Table[[#This Row],[FF&E]] -> 400000 | S82: 435000 | T82: 435000 | V82: 35000 | W82: =DATABASE_Table[[#This Row],[Current Asking price( Total)]]-DATABASE_Table[[#This Row],[Vista membership]]-DATABASE_Table[[#This Row],[FF&E]] -> 400000 | Z82: =DATABASE_Table[[#This Row],[Sell price (Total)]]-DATABASE_Table[[#This Row],[FF&E]]-DATABASE_Table[[#This Row],[Vista membership]] -> -35000 | AB82: 47118 | AC82: João Gameiro | AD82: Miguel Ribeiro | AE82: https://www.aroeiracollections.com/ | AF82: Aroeira Collections by Missoni: Elegance inspired by iconic design, set beside the renowned PGA golf course — where luxury living meets the rhythm of the coast. | AG82: Gym, Spa, Condo Pool, Private Pools, Tennis & Padel Courts, Outdoor Areas, Smart Home Technology, Private Parking, Reception, Missoni Interiors, PGA Golf Course | AH82: Primeiro grande projeto com uma marca de lifestyle/moda em Portugal - Missoni; Localização de excelência dentro da Herdade da Aroeira, a 30' de Lisboa e 10' das melhores praias do país; Design com contributo de arquitetos de renome; Excelente oportunidade de investimento; Junto ao campo de golfe PGA Aroeira; Diversas amenities como: Piscina interior e exterior, campos de tenis e padel, ginásio, spa e restaurante. | AI82: Ana Costa, João Favila, Pedro Domingos | AJ82: Aroeira Collections
A83: THE UNCOMMON | B83: Vilamoura | C83: 102 | D83: Vilamoura, Algarve | E83: T2 | F83: 129.4 | H83: 1 | J83: 25.5 | O83: 103.9 | Q83: AVAILABLE | R83: =DATABASE_Table[[#This Row],[Inicial Asking Price (€) (Total)]]-DATABASE_Table[[#This Row],[Vista membership]]-DATABASE_Table[[#This Row],[FF&E]] -> 1007000 | S83: 1080000 | T83: 1150000 | U83: 50000 | V83: 23000 | W83: =DATABASE_Table[[#This Row],[Current Asking price( Total)]]-DATABASE_Table[[#This Row],[Vista membership]]-DATABASE_Table[[#This Row],[FF&E]] -> 1077000 | Y83: 1150000 | Z83: =DATABASE_Table[[#This Row],[Sell price (Total)]]-DATABASE_Table[[#This Row],[FF&E]]-DATABASE_Table[[#This Row],[Vista membership]] -> 1077000 | AC83: Ana Damásio | AD83: Eduardo Lopes | AE83: TBD | AF83: The Uncommon is a front-row sea view masterpiece in Vilamoura, where vibrant energy meets serene coastal living. With an exclusive design and elevated services, in this touristic and residential project every moment feels uniquely exceptional. | AG83: Condo Pool, Outdoor Areas, Underground Parking, Reception, Concierge, Vista Membership | AH83: Apartamentos com exploração turística profissional e possibilidade de uso pelos proprietários; Amenities de excelência; Vistas excepcionais e em primeira linha de mar; Rooftops com plunge pool privativos. | AI83: NLA | AJ83: The Uncommon
A84: THE UNCOMMON | B84: Vilamoura | C84: 103 | D84: Vilamoura, Algarve | E84: T2 | F84: 129.4 | H84: 1 | J84: 25.5 | O84: 103.9 | Q84: AVAILABLE | R84: =DATABASE_Table[[#This Row],[Inicial Asking Price (€) (Total)]]-DATABASE_Table[[#This Row],[Vista membership]]-DATABASE_Table[[#This Row],[FF&E]] -> 927000 | S84: 1000000 | T84: 1060000 | U84: 50000 | V84: 23000 | W84: =DATABASE_Table[[#This Row],[Current Asking price( Total)]]-DATABASE_Table[[#This Row],[Vista membership]]-DATABASE_Table[[#This Row],[FF&E]] -> 987000 | Y84: 1060000 | Z84: =DATABASE_Table[[#This Row],[Sell price (Total)]]-DATABASE_Table[[#This Row],[FF&E]]-DATABASE_Table[[#This Row],[Vista membership]] -> 987000 | AC84: Ana Damásio | AD84: Eduardo Lopes | AE84: TBD | AF84: The Uncommon is a front-row sea view masterpiece in Vilamoura, where vibrant energy meets serene coastal living. With an exclusive design and elevated services, in this touristic and residential project every moment feels uniquely exceptional. | AG84: Condo Pool, Outdoor Areas, Underground Parking, Reception, Concierge, Vista Membership | AH84: Apartamentos com exploração turística profissional e possibilidade de uso pelos proprietários; Amenities de excelência; Vistas excepcionais e em primeira linha de mar; Rooftops com plunge pool privativos. | AI84: NLA | AJ84: The Uncommon
A85: Palmares - Signature Residences | B85: Algarve | C85: 12B | E85: T2 + 1 Duplex | F85: 342.39 | I85: 15.13 | M85: 84.04 | O85: 243.22 | Q85: AVAILABLE | R85: =DATABASE_Table[[#This Row],[Inicial Asking Price (€) (Total)]]-DATABASE_Table[[#This Row],[Vista membership]]-DATABASE_Table[[#This Row],[FF&E]] -> 2050000 | S85: 2050000 | T85: 2050000 | W85: =DATABASE_Table[[#This Row],[Current Asking price( Total)]]-DATABASE_Table[[#This Row],[Vista membership]]-DATABASE_Table[[#This Row],[FF&E]] -> 2050000 | Y85: 2050000 | Z85: =DATABASE_Table[[#This Row],[Sell price (Total)]]-DATABASE_Table[[#This Row],[FF&E]]-DATABASE_Table[[#This Row],[Vista membership]] -> 2050000 | AB85: 46843 | AJ85: Palmares
A86: Palmares - Signature Residences | B86: Algarve | C86: 13B | E86: T2 + 1 Duplex | F86: 345.12 | I86: 15.13 | M86: 83.71 | O86: 246.28 | Q86: AVAILABLE | R86: =DATABASE_Table[[#This Row],[Inicial Asking Price (€) (Total)]]-DATABASE_Table[[#This Row],[Vista membership]]-DATABASE_Table[[#This Row],[FF&E]] -> 1990000 | S86: 1990000 | T86: 1990000 | W86: =DATABASE_Table[[#This Row],[Current Asking price( Total)]]-DATABASE_Table[[#This Row],[Vista membership]]-DATABASE_Table[[#This Row],[FF&E]] -> 1990000 | Y86: 1990000 | Z86: =DATABASE_Table[[#This Row],[Sell price (Total)]]-DATABASE_Table[[#This Row],[FF&E]]-DATABASE_Table[[#This Row],[Vista membership]] -> 1990000 | AB86: 46843 | AJ86: Palmares
A87: Palmares - Signature Residences | B87: Algarve | C87: 14B | E87: T2 + 1Duplex | F87: 342.3 | I87: 15.13 | M87: 84.04 | O87: 243.13 | Q87: AVAILABLE | R87: =DATABASE_Table[[#This Row],[Inicial Asking Price (€) (Total)]]-DATABASE_Table[[#This Row],[Vista membership]]-DATABASE_Table[[#This Row],[FF&E]] -> 1980000 | S87: 1980000 | T87: 1980000 | W87: =DATABASE_Table[[#This Row],[Current Asking price( Total)]]-DATABASE_Table[[#This Row],[Vista membership]]-DATABASE_Table[[#This Row],[FF&E]] -> 1980000 | Y87: 1980000 | Z87: =DATABASE_Table[[#This Row],[Sell price (Total)]]-DATABASE_Table[[#This Row],[FF&E]]-DATABASE_Table[[#This Row],[Vista membership]] -> 1980000 | AB87: 46843 | AJ87: Palmares
A88: Palmares - Signature Residences | B88: Algarve | C88: 15B | E88: T2Duplex | F88: 290.99 | I88: 15.28 | M88: 83.84 | O88: 191.87 | Q88: RESERVED | R88: =DATABASE_Table[[#This Row],[Inicial Asking Price (€) (Total)]]-DATABASE_Table[[#This Row],[Vista membership]]-DATABASE_Table[[#This Row],[FF&E]] -> 1470000 | S88: 1470000 | T88: 1470000 | W88: =DATABASE_Table[[#This Row],[Current Asking price( Total)]]-DATABASE_Table[[#This Row],[Vista membership]]-DATABASE_Table[[#This Row],[FF&E]] -> 1470000 | Y88: 1470000 | Z88: =DATABASE_Table[[#This Row],[Sell price (Total)]]-DATABASE_Table[[#This Row],[FF&E]]-DATABASE_Table[[#This Row],[Vista membership]] -> 1470000 | AA88: 46144 | AB88: 46843 | AJ88: Palmares
A89: Palmares - Signature Residences | B89: Algarve | C89: 16C | E89: T1 + 1Accesible | F89: 162.69 | I89: 6.19 | M89: 57.46 | O89: 99.04 | Q89: RESERVED | R89: =DATABASE_Table[[#This Row],[Inicial Asking Price (€) (Total)]]-DATABASE_Table[[#This Row],[Vista membership]]-DATABASE_Table[[#This Row],[FF&E]] -> 730000 | S89: 730000 | T89: 730000 | W89: =DATABASE_Table[[#This Row],[Current Asking price( Total)]]-DATABASE_Table[[#This Row],[Vista membership]]-DATABASE_Table[[#This Row],[FF&E]] -> 730000 | Y89: 730000 | Z89: =DATABASE_Table[[#This Row],[Sell price (Total)]]-DATABASE_Table[[#This Row],[FF&E]]-DATABASE_Table[[#This Row],[Vista membership]] -> 730000 | AA89: 46141 | AB89: 46843 | AJ89: Palmares
A90: Palmares - Signature Residences | B90: Algarve | C90: 17D | E90: T3 + 1 Duplex | F90: 568.55 | I90: 28.24 | M90: 209.11 | O90: 331.2 | Q90: AVAILABLE | R90: =DATABASE_Table[[#This Row],[Inicial Asking Price (€) (Total)]]-DATABASE_Table[[#This Row],[Vista membership]]-DATABASE_Table[[#This Row],[FF&E]] -> 2880000 | S90: 2880000 | T90: 2880000 | W90: =DATABASE_Table[[#This Row],[Current Asking price( Total)]]-DATABASE_Table[[#This Row],[Vista membership]]-DATABASE_Table[[#This Row],[FF&E]] -> 2880000 | Y90: 2880000 | Z90: =DATABASE_Table[[#This Row],[Sell price (Total)]]-DATABASE_Table[[#This Row],[FF&E]]-DATABASE_Table[[#This Row],[Vista membership]] -> 2880000 | AB90: 46843 | AJ90: Palmares
A91: THE UNCOMMON | B91: Vilamoura | C91: 104 | D91: Vilamoura, Algarve | E91: T2 | F91: 130 | H91: 1 | J91: 25.4 | O91: 104.6 | Q91: AVAILABLE | R91: =DATABASE_Table[[#This Row],[Inicial Asking Price (€) (Total)]]-DATABASE_Table[[#This Row],[Vista membership]]-DATABASE_Table[[#This Row],[FF&E]] -> 847000 | S91: 920000 | T91: 980000 | U91: 50000 | V91: 23000 | W91: =DATABASE_Table[[#This Row],[Current Asking price( Total)]]-DATABASE_Table[[#This Row],[Vista membership]]-DATABASE_Table[[#This Row],[FF&E]] -> 907000 | Y91: 980000 | Z91: =DATABASE_Table[[#This Row],[Sell price (Total)]]-DATABASE_Table[[#This Row],[FF&E]]-DATABASE_Table[[#This Row],[Vista membership]] -> 907000 | AC91: Ana Damásio | AD91: Eduardo Lopes | AE91: TBD | AF91: The Uncommon is a front-row sea view masterpiece in Vilamoura, where vibrant energy meets serene coastal living. With an exclusive design and elevated services, in this touristic and residential project every moment feels uniquely exceptional. | AG91: Condo Pool, Outdoor Areas, Underground Parking, Reception, Concierge, Vista Membership | AH91: Apartamentos com exploração turística profissional e possibilidade de uso pelos proprietários; Amenities de excelência; Vistas excepcionais e em primeira linha de mar; Rooftops com plunge pool privativos. | AI91: NLA | AJ91: The Uncommon
A92: THE UNCOMMON | B92: Vilamoura | C92: 105 | D92: Vilamoura, Algarve | E92: T2 | F92: 130.1 | H92: 1 | J92: 25.5 | O92: 104.6 | Q92: AVAILABLE | R92: =DATABASE_Table[[#This Row],[Inicial Asking Price (€) (Total)]]-DATABASE_Table[[#This Row],[Vista membership]]-DATABASE_Table[[#This Row],[FF&E]] -> 927000 | S92: 1000000 | T92: 1060000 | U92: 50000 | V92: 23000 | W92: =DATABASE_Table[[#This Row],[Current Asking price( Total)]]-DATABASE_Table[[#This Row],[Vista membership]]-DATABASE_Table[[#This Row],[FF&E]] -> 987000 | Y92: 1060000 | Z92: =DATABASE_Table[[#This Row],[Sell price (Total)]]-DATABASE_Table[[#This Row],[FF&E]]-DATABASE_Table[[#This Row],[Vista membership]] -> 987000 | AC92: Ana Damásio | AD92: Eduardo Lopes | AE92: TBD | AF92: The Uncommon is a front-row sea view masterpiece in Vilamoura, where vibrant energy meets serene coastal living. With an exclusive design and elevated services, in this touristic and residential project every moment feels uniquely exceptional. | AG92: Condo Pool, Outdoor Areas, Underground Parking, Reception, Concierge, Vista Membership | AH92: Apartamentos com exploração turística profissional e possibilidade de uso pelos proprietários; Amenities de excelência; Vistas excepcionais e em primeira linha de mar; Rooftops com plunge pool privativos. | AI92: NLA | AJ92: The Uncommon
A93: THE UNCOMMON | B93: Vilamoura | C93: 106 | D93: Vilamoura, Algarve | E93: T2 | F93: 129.4 | H93: 1 | J93: 25.5 | O93: 103.9 | Q93: AVAILABLE | R93: =DATABASE_Table[[#This Row],[Inicial Asking Price (€) (Total)]]-DATABASE_Table[[#This Row],[Vista membership]]-DATABASE_Table[[#This Row],[FF&E]] -> 1007000 | S93: 1080000 | T93: 1150000 | U93: 50000 | V93: 23000 | W93: =DATABASE_Table[[#This Row],[Current Asking price( Total)]]-DATABASE_Table[[#This Row],[Vista membership]]-DATABASE_Table[[#This Row],[FF&E]] -> 1077000 | Y93: 1150000 | Z93: =DATABASE_Table[[#This Row],[Sell price (Total)]]-DATABASE_Table[[#This Row],[FF&E]]-DATABASE_Table[[#This Row],[Vista membership]] -> 1077000 | AC93: Ana Damásio | AD93: Eduardo Lopes | AE93: TBD | AF93: The Uncommon is a front-row sea view masterpiece in Vilamoura, where vibrant energy meets serene coastal living. With an exclusive design and elevated services, in this touristic and residential project every moment feels uniquely exceptional. | AG93: Condo Pool, Outdoor Areas, Underground Parking, Reception, Concierge, Vista Membership | AH93: Apartamentos com exploração turística profissional e possibilidade de uso pelos proprietários; Amenities de excelência; Vistas excepcionais e em primeira linha de mar; Rooftops com plunge pool privativos. | AI93: NLA | AJ93: The Uncommon
A94: THE UNCOMMON | B94: Vilamoura | C94: 107 | D94: Vilamoura, Algarve | E94: T2 | F94: 129.4 | H94: 1 | J94: 25.5 | O94: 103.9 | Q94: AVAILABLE | R94: =DATABASE_Table[[#This Row],[Inicial Asking Price (€) (Total)]]-DATABASE_Table[[#This Row],[Vista membership]]-DATABASE_Table[[#This Row],[FF&E]] -> 1087000 | S94: 1160000 | T94: 1230000 | U94: 50000 | V94: 23000 | W94: =DATABASE_Table[[#This Row],[Current Asking price( Total)]]-DATABASE_Table[[#This Row],[Vista membership]]-DATABASE_Table[[#This Row],[FF&E]] -> 1157000 | Y94: 1230000 | Z94: =DATABASE_Table[[#This Row],[Sell price (Total)]]-DATABASE_Table[[#This Row],[FF&E]]-DATABASE_Table[[#This Row],[Vista membership]] -> 1157000 | AC94: Ana Damásio | AD94: Eduardo Lopes | AE94: TBD | AF94: The Uncommon is a front-row sea view masterpiece in Vilamoura, where vibrant energy meets serene coastal living. With an exclusive design and elevated services, in this touristic and residential project every moment feels uniquely exceptional. | AG94: Condo Pool, Outdoor Areas, Underground Parking, Reception, Concierge, Vista Membership | AH94: Apartamentos com exploração turística profissional e possibilidade de uso pelos proprietários; Amenities de excelência; Vistas excepcionais e em primeira linha de mar; Rooftops com plunge pool privativos. | AI94: NLA | AJ94: The Uncommon
A95: THE UNCOMMON | B95: Vilamoura | C95: 108 | D95: Vilamoura, Algarve | E95: T2 | F95: 129.4 | H95: 1 | J95: 25.5 | O95: 103.9 | Q95: AVAILABLE | R95: =DATABASE_Table[[#This Row],[Inicial Asking Price (€) (Total)]]-DATABASE_Table[[#This Row],[Vista membership]]-DATABASE_Table[[#This Row],[FF&E]] -> 1147000 | S95: 1220000 | T95: 1290000 | U95: 50000 | V95: 23000 | W95: =DATABASE_Table[[#This Row],[Current Asking price( Total)]]-DATABASE_Table[[#This Row],[Vista membership]]-DATABASE_Table[[#This Row],[FF&E]] -> 1217000 | Y95: 1290000 | Z95: =DATABASE_Table[[#This Row],[Sell price (Total)]]-DATABASE_Table[[#This Row],[FF&E]]-DATABASE_Table[[#This Row],[Vista membership]] -> 1217000 | AC95: Ana Damásio | AD95: Eduardo Lopes | AE95: TBD | AF95: The Uncommon is a front-row sea view masterpiece in Vilamoura, where vibrant energy meets serene coastal living. With an exclusive design and elevated services, in this touristic and residential project every moment feels uniquely exceptional. | AG95: Condo Pool, Outdoor Areas, Underground Parking, Reception, Concierge, Vista Membership | AH95: Apartamentos com exploração turística profissional e possibilidade de uso pelos proprietários; Amenities de excelência; Vistas excepcionais e em primeira linha de mar; Rooftops com plunge pool privativos. | AI95: NLA | AJ95: The Uncommon
A96: THE UNCOMMON | B96: Vilamoura | C96: 109 | D96: Vilamoura, Algarve | E96: T2 | F96: 129.4 | H96: 1 | J96: 25.5 | O96: 103.9 | Q96: AVAILABLE | R96: =DATABASE_Table[[#This Row],[Inicial Asking Price (€) (Total)]]-DATABASE_Table[[#This Row],[Vista membership]]-DATABASE_Table[[#This Row],[FF&E]] -> 1207000 | S96: 1280000 | T96: 1350000 | U96: 50000 | V96: 23000 | W96: =DATABASE_Table[[#This Row],[Current Asking price( Total)]]-DATABASE_Table[[#This Row],[Vista membership]]-DATABASE_Table[[#This Row],[FF&E]] -> 1277000 | Y96: 1350000 | Z96: =DATABASE_Table[[#This Row],[Sell price (Total)]]-DATABASE_Table[[#This Row],[FF&E]]-DATABASE_Table[[#This Row],[Vista membership]] -> 1277000 | AC96: Ana Damásio | AD96: Eduardo Lopes | AE96: TBD | AF96: The Uncommon is a front-row sea view masterpiece in Vilamoura, where vibrant energy meets serene coastal living. With an exclusive design and elevated services, in this touristic and residential project every moment feels uniquely exceptional. | AG96: Condo Pool, Outdoor Areas, Underground Parking, Reception, Concierge, Vista Membership | AH96: Apartamentos com exploração turística profissional e possibilidade de uso pelos proprietários; Amenities de excelência; Vistas excepcionais e em primeira linha de mar; Rooftops com plunge pool privativos. | AI96: NLA | AJ96: The Uncommon
A97: Aroeira - HOTEL APARTMENTS | B97: Center | C97: 329A | D97: Herdade da Aroeira, Almada | E97: 1-BR | F97: 60.2 | H97: 1 | J97: 3.9 | O97: 56.3 | Q97: AVAILABLE | R97: =DATABASE_Table[[#This Row],[Inicial Asking Price (€) (Total)]]-DATABASE_Table[[#This Row],[Vista membership]]-DATABASE_Table[[#This Row],[FF&E]] -> 410000 | S97: 445000 | T97: 445000 | V97: 35000 | W97: =DATABASE_Table[[#This Row],[Current Asking price( Total)]]-DATABASE_Table[[#This Row],[Vista membership]]-DATABASE_Table[[#This Row],[FF&E]] -> 410000 | Z97: =DATABASE_Table[[#This Row],[Sell price (Total)]]-DATABASE_Table[[#This Row],[FF&E]]-DATABASE_Table[[#This Row],[Vista membership]] -> -35000 | AB97: 47118 | AC97: João Gameiro | AD97: Miguel Ribeiro | AE97: https://www.aroeiracollections.com/ | AF97: Aroeira Collections by Missoni: Elegance inspired by iconic design, set beside the renowned PGA golf course — where luxury living meets the rhythm of the coast. | AG97: Gym, Spa, Condo Pool, Private Pools, Tennis & Padel Courts, Outdoor Areas, Smart Home Technology, Private Parking, Reception, Missoni Interiors, PGA Golf Course | AH97: Primeiro grande projeto com uma marca de lifestyle/moda em Portugal - Missoni; Localização de excelência dentro da Herdade da Aroeira, a 30' de Lisboa e 10' das melhores praias do país; Design com contributo de arquitetos de renome; Excelente oportunidade de investimento; Junto ao campo de golfe PGA Aroeira; Diversas amenities como: Piscina interior e exterior, campos de tenis e padel, ginásio, spa e restaurante. | AI97: Ana Costa, João Favila, Pedro Domingos | AJ97: Aroeira Collections
A98: Aroeira - HOTEL APARTMENTS | B98: Center | C98: 330A | D98: Herdade da Aroeira, Almada | E98: 1-BR | F98: 60.2 | H98: 1 | J98: 3.9 | O98: 56.3 | Q98: AVAILABLE | R98: =DATABASE_Table[[#This Row],[Inicial Asking Price (€) (Total)]]-DATABASE_Table[[#This Row],[Vista membership]]-DATABASE_Table[[#This Row],[FF&E]] -> 410000 | S98: 445000 | T98: 445000 | V98: 35000 | W98: =DATABASE_Table[[#This Row],[Current Asking price( Total)]]-DATABASE_Table[[#This Row],[Vista membership]]-DATABASE_Table[[#This Row],[FF&E]] -> 410000 | Z98: =DATABASE_Table[[#This Row],[Sell price (Total)]]-DATABASE_Table[[#This Row],[FF&E]]-DATABASE_Table[[#This Row],[Vista membership]] -> -35000 | AB98: 47118 | AC98: João Gameiro | AD98: Miguel Ribeiro | AE98: https://www.aroeiracollections.com/ | AF98: Aroeira Collections by Missoni: Elegance inspired by iconic design, set beside the renowned PGA golf course — where luxury living meets the rhythm of the coast. | AG98: Gym, Spa, Condo Pool, Private Pools, Tennis & Padel Courts, Outdoor Areas, Smart Home Technology, Private Parking, Reception, Missoni Interiors, PGA Golf Course | AH98: Primeiro grande projeto com uma marca de lifestyle/moda em Portugal - Missoni; Localização de excelência dentro da Herdade da Aroeira, a 30' de Lisboa e 10' das melhores praias do país; Design com contributo de arquitetos de renome; Excelente oportunidade de investimento; Junto ao campo de golfe PGA Aroeira; Diversas amenities como: Piscina interior e exterior, campos de tenis e padel, ginásio, spa e restaurante. | AI98: Ana Costa, João Favila, Pedro Domingos | AJ98: Aroeira Collections
A99: Aroeira - HOTEL APARTMENTS | B99: Center | C99: 331A | D99: Herdade da Aroeira, Almada | E99: 1-BR | F99: 60.2 | H99: 1 | J99: 3.9 | O99: 56.3 | Q99: AVAILABLE | R99: =DATABASE_Table[[#This Row],[Inicial Asking Price (€) (Total)]]-DATABASE_Table[[#This Row],[Vista membership]]-DATABASE_Table[[#This Row],[FF&E]] -> 410000 | S99: 445000 | T99: 445000 | V99: 35000 | W99: =DATABASE_Table[[#This Row],[Current Asking price( Total)]]-DATABASE_Table[[#This Row],[Vista membership]]-DATABASE_Table[[#This Row],[FF&E]] -> 410000 | Z99: =DATABASE_Table[[#This Row],[Sell price (Total)]]-DATABASE_Table[[#This Row],[FF&E]]-DATABASE_Table[[#This Row],[Vista membership]] -> -35000 | AB99: 47118 | AC99: João Gameiro | AD99: Miguel Ribeiro | AE99: https://www.aroeiracollections.com/ | AF99: Aroeira Collections by Missoni: Elegance inspired by iconic design, set beside the renowned PGA golf course — where luxury living meets the rhythm of the coast. | AG99: Gym, Spa, Condo Pool, Private Pools, Tennis & Padel Courts, Outdoor Areas, Smart Home Technology, Private Parking, Reception, Missoni Interiors, PGA Golf Course | AH99: Primeiro grande projeto com uma marca de lifestyle/moda em Portugal - Missoni; Localização de excelência dentro da Herdade da Aroeira, a 30' de Lisboa e 10' das melhores praias do país; Design com contributo de arquitetos de renome; Excelente oportunidade de investimento; Junto ao campo de golfe PGA Aroeira; Diversas amenities como: Piscina interior e exterior, campos de tenis e padel, ginásio, spa e restaurante. | AI99: Ana Costa, João Favila, Pedro Domingos | AJ99: Aroeira Collections
A100: Aroeira - HOTEL APARTMENTS | B100: Center | C100: 332A | D100: Herdade da Aroeira, Almada | E100: 1-BR | F100: 60.2 | H100: 1 | J100: 3.9 | O100: 56.3 | Q100: AVAILABLE | R100: =DATABASE_Table[[#This Row],[Inicial Asking Price (€) (Total)]]-DATABASE_Table[[#This Row],[Vista membership]]-DATABASE_Table[[#This Row],[FF&E]] -> 410000 | S100: 445000 | T100: 445000 | V100: 35000 | W100: =DATABASE_Table[[#This Row],[Current Asking price( Total)]]-DATABASE_Table[[#This Row],[Vista membership]]-DATABASE_Table[[#This Row],[FF&E]] -> 410000 | Z100: =DATABASE_Table[[#This Row],[Sell price (Total)]]-DATABASE_Table[[#This Row],[FF&E]]-DATABASE_Table[[#This Row],[Vista membership]] -> -35000 | AB100: 47118 | AC100: João Gameiro | AD100: Miguel Ribeiro | AE100: https://www.aroeiracollections.com/ | AF100: Aroeira Collections by Missoni: Elegance inspired by iconic design, set beside the renowned PGA golf course — where luxury living meets the rhythm of the coast. | AG100: Gym, Spa, Condo Pool, Private Pools, Tennis & Padel Courts, Outdoor Areas, Smart Home Technology, Private Parking, Reception, Missoni Interiors, PGA Golf Course | AH100: Primeiro grande projeto com uma marca de lifestyle/moda em Portugal - Missoni; Localização de excelência dentro da Herdade da Aroeira, a 30' de Lisboa e 10' das melhores praias do país; Design com contributo de arquitetos de renome; Excelente oportunidade de investimento; Junto ao campo de golfe PGA Aroeira; Diversas amenities como: Piscina interior e exterior, campos de tenis e padel, ginásio, spa e restaurante. | AI100: Ana Costa, João Favila, Pedro Domingos | AJ100: Aroeira Collections
A101: Aroeira - HOTEL APARTMENTS | B101: Center | C101: 333A | D101: Herdade da Aroeira, Almada | E101: 1-BR | F101: 60.2 | H101: 1 | J101: 3.9 | O101: 56.3 | Q101: AVAILABLE | R101: =DATABASE_Table[[#This Row],[Inicial Asking Price (€) (Total)]]-DATABASE_Table[[#This Row],[Vista membership]]-DATABASE_Table[[#This Row],[FF&E]] -> 410000 | S101: 445000 | T101: 445000 | V101: 35000 | W101: =DATABASE_Table[[#This Row],[Current Asking price( Total)]]-DATABASE_Table[[#This Row],[Vista membership]]-DATABASE_Table[[#This Row],[FF&E]] -> 410000 | Z101: =DATABASE_Table[[#This Row],[Sell price (Total)]]-DATABASE_Table[[#This Row],[FF&E]]-DATABASE_Table[[#This Row],[Vista membership]] -> -35000 | AB101: 47118 | AC101: João Gameiro | AD101: Miguel Ribeiro | AE101: https://www.aroeiracollections.com/ | AF101: Aroeira Collections by Missoni: Elegance inspired by iconic design, set beside the renowned PGA golf course — where luxury living meets the rhythm of the coast. | AG101: Gym, Spa, Condo Pool, Private Pools, Tennis & Padel Courts, Outdoor Areas, Smart Home Technology, Private Parking, Reception, Missoni Interiors, PGA Golf Course | AH101: Primeiro grande projeto com uma marca de lifestyle/moda em Portugal - Missoni; Localização de excelência dentro da Herdade da Aroeira, a 30' de Lisboa e 10' das melhores praias do país; Design com contributo de arquitetos de renome; Excelente oportunidade de investimento; Junto ao campo de golfe PGA Aroeira; Diversas amenities como: Piscina interior e exterior, campos de tenis e padel, ginásio, spa e restaurante. | AI101: Ana Costa, João Favila, Pedro Domingos | AJ101: Aroeira Collections
A102: Aroeira - HOUSES | B102: Center | C102: 09B | D102: Herdade da Aroeira, Almada | E102: T2 | F102: 166 | H102: 1 | M102: 30 | N102: 20 | O102: 116 | Q102: PSPA | R102: =DATABASE_Table[[#This Row],[Inicial Asking Price (€) (Total)]]-DATABASE_Table[[#This Row],[Vista membership]]-DATABASE_Table[[#This Row],[FF&E]] -> 910000 | S102: 910000 | T102: 910000 | V102: 0 | W102: =DATABASE_Table[[#This Row],[Current Asking price( Total)]]-DATABASE_Table[[#This Row],[Vista membership]]-DATABASE_Table[[#This Row],[FF&E]] -> 910000 | X102: 0.010989011 | Y102: 900000 | Z102: =DATABASE_Table[[#This Row],[Sell price (Total)]]-DATABASE_Table[[#This Row],[FF&E]]-DATABASE_Table[[#This Row],[Vista membership]] -> 900000 | AA102: 45915 | AB102: 47118 | AC102: João Gameiro | AD102: Miguel Ribeiro | AE102: https://www.aroeiracollections.com/ | AF102: Aroeira Collections by Missoni: Elegance inspired by iconic design, set beside the renowned PGA golf course — where luxury living meets the rhythm of the coast. | AG102: Gym, Spa, Condo Pool, Private Pools, Tennis & Padel Courts, Outdoor Areas, Smart Home Technology, Private Parking, Reception, Missoni Interiors, PGA Golf Course | AH102: Primeiro grande projeto com uma marca de lifestyle/moda em Portugal - Missoni; Localização de excelência dentro da Herdade da Aroeira, a 30' de Lisboa e 10' das melhores praias do país; Design com contributo de arquitetos de renome; Excelente oportunidade de investimento; Junto ao campo de golfe PGA Aroeira; Diversas amenities como: Piscina interior e exterior, campos de tenis e padel, ginásio, spa e restaurante. | AI102: Ana Costa, João Favila, Pedro Domingos | AJ102: Aroeira Collections
A103: Aroeira - HOTEL APARTMENTS | B103: Center | C103: 216A | D103: Herdade da Aroeira, Almada | E103: 1-BR | F103: 65 | H103: 1 | J103: 8.7 | O103: 56.3 | Q103: AVAILABLE | R103: =DATABASE_Table[[#This Row],[Inicial Asking Price (€) (Total)]]-DATABASE_Table[[#This Row],[Vista membership]]-DATABASE_Table[[#This Row],[FF&E]] -> 415000 | S103: 450000 | T103: 450000 | V103: 35000 | W103: =DATABASE_Table[[#This Row],[Current Asking price( Total)]]-DATABASE_Table[[#This Row],[Vista membership]]-DATABASE_Table[[#This Row],[FF&E]] -> 415000 | Z103: =DATABASE_Table[[#This Row],[Sell price (Total)]]-DATABASE_Table[[#This Row],[FF&E]]-DATABASE_Table[[#This Row],[Vista membership]] -> -35000 | AB103: 47118 | AC103: João Gameiro | AD103: Miguel Ribeiro | AE103: https://www.aroeiracollections.com/ | AF103: Aroeira Collections by Missoni: Elegance inspired by iconic design, set beside the renowned PGA golf course — where luxury living meets the rhythm of the coast. | AG103: Gym, Spa, Condo Pool, Private Pools, Tennis & Padel Courts, Outdoor Areas, Smart Home Technology, Private Parking, Reception, Missoni Interiors, PGA Golf Course | AH103: Primeiro grande projeto com uma marca de lifestyle/moda em Portugal - Missoni; Localização de excelência dentro da Herdade da Aroeira, a 30' de Lisboa e 10' das melhores praias do país; Design com contributo de arquitetos de renome; Excelente oportunidade de investimento; Junto ao campo de golfe PGA Aroeira; Diversas amenities como: Piscina interior e exterior, campos de tenis e padel, ginásio, spa e restaurante. | AI103: Ana Costa, João Favila, Pedro Domingos | AJ103: Aroeira Collections
...

Sheet Natura Village 
A1: Commercial ID | B1: Local | C1: Unit PH | D1: Typology | E1: Area Total [sqm] | F1: Storage [sqm] | G1: Parking Lots [#] | H1: Pool [#] | I1: Balconies [sqm] | J1: Garden [sqm] | K1: Patio [sqm] | L1: Terrace [sqm] | M1: Rooftop [sqm] | N1: Interior | O1: Exterior | P1: Selling Status | Q1: Inicial Asking Price (€) (RE Asset) | R1: Inicial Asking Price (€) (Total) | S1: Current Asking price( Total) | T1: Vista membership | U1: FF&E | V1: Current Asking price (RE Asset) | W1: Total Discunt (%) | X1: Sell price (Total) | Y1: Sell price (RE Asset) | Z1: Launch Date | AA1: Pre Reservation Date | AB1: Conclusion Expected
A2: =DATABASE!A2 -> MR - Linked Villas | B2: =DATABASE!B2 -> Algarve | C2: =DATABASE!C2 -> T | D2: =DATABASE!E2 -> T3 | E2: =DATABASE!F2 -> 422.36 | F2: =DATABASE!G2 -> 45.06 | G2: =DATABASE!H2 | H2: =DATABASE!I2 | I2: =DATABASE!J2 -> 131.68 | J2: =DATABASE!K2 -> 0 | K2: =DATABASE!L2 -> 0 | ... Y2: =DATABASE!Z2 -> 0 | Z2: =DATABASE!#REF! -> #REF! | AA2: =DATABASE!AA2 -> 0 | AB2: =DATABASE!AB2 -> TBD
A3: =DATABASE!A3 -> Aroeira - HOUSES | B3: =DATABASE!B3 -> Center | C3: =DATABASE!C3 -> 01B | D3: =DATABASE!E3 -> T2 | E3: =DATABASE!F3 -> 167 | F3: =DATABASE!G3 -> 0 | G3: =DATABASE!H3 -> 1 | H3: =DATABASE!I3 | I3: =DATABASE!J3 -> 0 | J3: =DATABASE!K3 -> 0 | K3: =DATABASE!L3 -> 0 | ... Y3: =DATABASE!Z3 -> 925000 | Z3: =DATABASE!#REF! -> #REF! | AA3: =DATABASE!#REF! -> #REF! | AB3: =DATABASE!AB3 -> 47118
A4: =DATABASE!A4 -> Aroeira - HOUSES | B4: =DATABASE!B4 -> Center | C4: =DATABASE!C4 -> 02B | D4: =DATABASE!E4 -> T2 | E4: =DATABASE!F4 -> 194.4 | F4: =DATABASE!G4 -> 0 | G4: =DATABASE!H4 -> 1 | H4: =DATABASE!I4 | I4: =DATABASE!J4 -> 0 | J4: =DATABASE!K4 -> 0 | K4: =DATABASE!L4 -> 0 | ... Y4: =DATABASE!Z4 -> 1105000 | Z4: =DATABASE!#REF! -> #REF! | AA4: =DATABASE!#REF! -> #REF! | AB4: =DATABASE!AB4 -> 47118
A5: =DATABASE!A5 -> Aroeira - HOUSES | B5: =DATABASE!B5 -> Center | C5: =DATABASE!C5 -> 03B | D5: =DATABASE!E5 -> T2 | E5: =DATABASE!F5 -> 167 | F5: =DATABASE!G5 -> 0 | G5: =DATABASE!H5 -> 1 | H5: =DATABASE!I5 | I5: =DATABASE!J5 -> 0 | J5: =DATABASE!K5 -> 0 | K5: =DATABASE!L5 -> 0 | ... Y5: =DATABASE!Z5 -> 925000 | Z5: =DATABASE!#REF! -> #REF! | AA5: =DATABASE!#REF! -> #REF! | AB5: =DATABASE!AB5 -> 47118
A6: =DATABASE!A6 -> Aroeira - HOUSES | B6: =DATABASE!B6 -> Center | C6: =DATABASE!C6 -> 04B | D6: =DATABASE!E6 -> T2 | E6: =DATABASE!F6 -> 167 | F6: =DATABASE!G6 -> 0 | G6: =DATABASE!H6 -> 1 | H6: =DATABASE!I6 | I6: =DATABASE!J6 -> 0 | J6: =DATABASE!K6 -> 0 | K6: =DATABASE!L6 -> 0 | ... Y6: =DATABASE!Z6 -> 925000 | Z6: =DATABASE!#REF! -> #REF! | AA6: =DATABASE!#REF! -> #REF! | AB6: =DATABASE!AB6 -> 47118
A7: =DATABASE!A7 -> Aroeira - HOTEL APARTMENTS | B7: =DATABASE!B7 -> Center | C7: =DATABASE!C7 -> 143A | D7: =DATABASE!E7 -> 1-BR | E7: =DATABASE!F7 -> 56.5 | F7: =DATABASE!G7 -> 0 | G7: =DATABASE!H7 -> 1 | H7: =DATABASE!I7 | I7: =DATABASE!J7 -> 5 | J7: =DATABASE!K7 -> 0 | K7: =DATABASE!L7 -> 0 | ... Y7: =DATABASE!Z7 -> 335000 | Z7: =DATABASE!#REF! -> #REF! | AA7: =DATABASE!AA7 -> 46104 | AB7: =DATABASE!AB7 -> 47118
A8: =DATABASE!A8 -> Aroeira - HOTEL APARTMENTS | B8: =DATABASE!B8 -> Center | C8: =DATABASE!C8 -> 144A | D8: =DATABASE!E8 -> 1-BR | E8: =DATABASE!F8 -> 56.5 | F8: =DATABASE!G8 -> 0 | G8: =DATABASE!H8 -> 1 | H8: =DATABASE!I8 | I8: =DATABASE!J8 -> 5 | J8: =DATABASE!K8 -> 0 | K8: =DATABASE!L8 -> 0 | ... Y8: =DATABASE!Z8 -> 335000 | Z8: =DATABASE!#REF! -> #REF! | AA8: =DATABASE!AA8 -> 46052 | AB8: =DATABASE!AB8 -> 47118
A9: =DATABASE!A9 -> Aroeira - HOTEL APARTMENTS | B9: =DATABASE!B9 -> Center | C9: =DATABASE!C9 -> 134A | D9: =DATABASE!E9 -> 1-BR | E9: =DATABASE!F9 -> 56.5 | F9: =DATABASE!G9 -> 0 | G9: =DATABASE!H9 -> 1 | H9: =DATABASE!I9 | I9: =DATABASE!J9 -> 5 | J9: =DATABASE!K9 -> 0 | K9: =DATABASE!L9 -> 0 | ... Y9: =DATABASE!Z9 -> 327600 | Z9: =DATABASE!#REF! -> #REF! | AA9: =DATABASE!AA9 -> 46118 | AB9: =DATABASE!AB9 -> 47118
A10: =DATABASE!A10 -> Aroeira - HOTEL APARTMENTS | B10: =DATABASE!B10 -> Center | C10: =DATABASE!C10 -> 137A | D10: =DATABASE!E10 -> 1-BR | E10: =DATABASE!F10 -> 56.5 | F10: =DATABASE!G10 -> 0 | G10: =DATABASE!H10 -> 1 | H10: =DATABASE!I10 | I10: =DATABASE!J10 -> 5 | J10: =DATABASE!K10 -> 0 | K10: =DATABASE!L10 -> 0 | ... Y10: =DATABASE!Z10 -> 327600 | Z10: =DATABASE!#REF! -> #REF! | AA10: =DATABASE!AA10 -> 46118 | AB10: =DATABASE!AB10 -> 47118
A11: =DATABASE!A11 -> Aroeira - HOTEL APARTMENTS | B11: =DATABASE!B11 -> Center | C11: =DATABASE!C11 -> 236A | D11: =DATABASE!E11 -> 1-BR | E11: =DATABASE!F11 -> 56.5 | F11: =DATABASE!G11 -> 0 | G11: =DATABASE!H11 -> 1 | H11: =DATABASE!I11 | I11: =DATABASE!J11 -> 5 | J11: =DATABASE!K11 -> 0 | K11: =DATABASE!L11 -> 0 | ... Y11: =DATABASE!Z11 -> 355000 | Z11: =DATABASE!#REF! -> #REF! | AA11: =DATABASE!AA11 -> 46142 | AB11: =DATABASE!AB11 -> 47118
A12: =DATABASE!A12 -> Aroeira - HOTEL APARTMENTS | B12: =DATABASE!B12 -> Center | C12: =DATABASE!C12 -> 139A | D12: =DATABASE!E12 -> 1-BR | E12: =DATABASE!F12 -> 60.2 | F12: =DATABASE!G12 -> 0 | G12: =DATABASE!H12 -> 1 | H12: =DATABASE!I12 | I12: =DATABASE!J12 -> 3.9 | J12: =DATABASE!K12 -> 0 | K12: =DATABASE!L12 -> 0 | ... Y12: =DATABASE!Z12 -> 355000 | Z12: =DATABASE!#REF! -> #REF! | AA12: =DATABASE!AA12 -> 46098 | AB12: =DATABASE!AB12 -> 47118
A13: =DATABASE!A13 -> Aroeira - HOTEL APARTMENTS | B13: =DATABASE!B13 -> Center | C13: =DATABASE!C13 -> 140A | D13: =DATABASE!E13 -> 1-BR | E13: =DATABASE!F13 -> 60.2 | F13: =DATABASE!G13 -> 0 | G13: =DATABASE!H13 -> 1 | H13: =DATABASE!I13 | I13: =DATABASE!J13 -> 3.9 | J13: =DATABASE!K13 -> 0 | K13: =DATABASE!L13 -> 0 | ... Y13: =DATABASE!Z13 -> 355000 | Z13: =DATABASE!#REF! -> #REF! | AA13: =DATABASE!AA13 -> 46085 | AB13: =DATABASE!AB13 -> 47118
A14: =DATABASE!A14 -> Aroeira - HOTEL APARTMENTS | B14: =DATABASE!B14 -> Center | C14: =DATABASE!C14 -> 141A | D14: =DATABASE!E14 -> 1-BR | E14: =DATABASE!F14 -> 60.2 | F14: =DATABASE!G14 -> 0 | G14: =DATABASE!H14 -> 1 | H14: =DATABASE!I14 | I14: =DATABASE!J14 -> 3.9 | J14: =DATABASE!K14 -> 0 | K14: =DATABASE!L14 -> 0 | ... Y14: =DATABASE!Z14 -> 355000 | Z14: =DATABASE!#REF! -> #REF! | AA14: =DATABASE!AA14 -> 46129 | AB14: =DATABASE!AB14 -> 47118
A15: =DATABASE!A15 -> Aroeira - HOTEL APARTMENTS | B15: =DATABASE!B15 -> Center | C15: =DATABASE!C15 -> 142A | D15: =DATABASE!E15 -> 1-BR | E15: =DATABASE!F15 -> 60.2 | F15: =DATABASE!G15 -> 0 | G15: =DATABASE!H15 -> 1 | H15: =DATABASE!I15 | I15: =DATABASE!J15 -> 3.9 | J15: =DATABASE!K15 -> 0 | K15: =DATABASE!L15 -> 0 | ... Y15: =DATABASE!Z15 -> 355000 | Z15: =DATABASE!#REF! -> #REF! | AA15: =DATABASE!AA15 -> 46129 | AB15: =DATABASE!AB15 -> 47118
A16: =DATABASE!A16 -> Aroeira - HOTEL APARTMENTS | B16: =DATABASE!B16 -> Center | C16: =DATABASE!C16 -> 235A | D16: =DATABASE!E16 -> 1-BR | E16: =DATABASE!F16 -> 56.5 | F16: =DATABASE!G16 -> 0 | G16: =DATABASE!H16 -> 1 | H16: =DATABASE!I16 | I16: =DATABASE!J16 -> 5 | J16: =DATABASE!K16 -> 0 | K16: =DATABASE!L16 -> 0 | ... Y16: =DATABASE!Z16 -> 355000 | Z16: =DATABASE!#REF! -> #REF! | AA16: =DATABASE!AA16 -> 46126 | AB16: =DATABASE!AB16 -> 47118
A17: =DATABASE!A17 -> Aroeira - HOTEL APARTMENTS | B17: =DATABASE!B17 -> Center | C17: =DATABASE!C17 -> 138A | D17: =DATABASE!E17 -> 1-BR | E17: =DATABASE!F17 -> 60.2 | F17: =DATABASE!G17 -> 0 | G17: =DATABASE!H17 -> 1 | H17: =DATABASE!I17 | I17: =DATABASE!J17 -> 3.9 | J17: =DATABASE!K17 -> 0 | K17: =DATABASE!L17 -> 0 | ... Y17: =DATABASE!Z17 -> -35000 | Z17: =DATABASE!#REF! -> #REF! | AA17: =DATABASE!AA17 -> 0 | AB17: =DATABASE!AB17 -> 47118
A18: =DATABASE!A18 -> Aroeira - HOTEL APARTMENTS | B18: =DATABASE!B18 -> Center | C18: =DATABASE!C18 -> 234A | D18: =DATABASE!E18 -> 1-BR | E18: =DATABASE!F18 -> 56.5 | F18: =DATABASE!G18 -> 0 | G18: =DATABASE!H18 -> 1 | H18: =DATABASE!I18 | I18: =DATABASE!J18 -> 5 | J18: =DATABASE!K18 -> 0 | K18: =DATABASE!L18 -> 0 | ... Y18: =DATABASE!Z18 -> -35000 | Z18: =DATABASE!#REF! -> #REF! | AA18: =DATABASE!AA18 -> 0 | AB18: =DATABASE!AB18 -> 47118
... A39: =DATABASE!A39 -> Aroeira - HOTEL APARTMENTS | B39: =DATABASE!B39 -> Center | C39: =DATABASE!C39 -> 240A | D39: =DATABASE!E39 -> 1-BR | E39: =DATABASE!F39 -> 60.2 | F39: =DATABASE!G39 -> 0 | G39: =DATABASE!H39 -> 1 | H39: =DATABASE!I39 | I39: =DATABASE!J39 -> 3.9 | J39: =DATABASE!K39 -> 0 | K39: =DATABASE!L39 -> 0 | ... Y39: =DATABASE!Z39 -> -35000 | Z39: =DATABASE!#REF! -> #REF! | AA39: =DATABASE!AA39 -> 0 | AB39: =DATABASE!AB39 -> 47118

Sheet The Nine
A1: Commercial ID | B1: Local | C1: Unit PH | D1: Typology | E1: Area Total [sqm] | F1: Storage [sqm] | G1: Parking Lots [#] | H1: Pool [#] | I1: Balconies [sqm] | J1: Garden [sqm] | K1: Patio [sqm] | L1: Terrace [sqm] | M1: Rooftop [sqm] | N1: Interior | O1: Exterior | P1: Selling Status | Q1: Inicial Asking Price (€) (RE Asset) | R1: Inicial Asking Price (€) (Total) | S1: Current Asking price( Total) | T1: Vista membership | U1: FF&E | V1: Current Asking price (RE Asset) | W1: Total Discunt (%) | X1: Sell price (Total) | Y1: Sell price (RE Asset) | Z1: Launch Date | AA1: Pre Reservation Date | AB1: Conclusion Expected
A2: =DATABASE!A40 -> Aroeira - HOTEL APARTMENTS | B2: =DATABASE!B40 -> Center | C2: =DATABASE!C40 -> 241A | D2: =DATABASE!E40 -> 1-BR | E2: =DATABASE!F40 -> 60.2 | F2: =DATABASE!G40 -> 0 | G2: =DATABASE!H40 -> 1 | H2: =DATABASE!I40 | I2: =DATABASE!J40 -> 3.9 | J2: =DATABASE!K40 -> 0 | K2: =DATABASE!L40 -> 0 | ... Y2: =DATABASE!Z40 -> -35000 | Z2: =DATABASE!#REF! -> #REF! | AA2: =DATABASE!AA40 -> 0 | AB2: =DATABASE!AB40 -> 47118
A3: =DATABASE!A41 -> Aroeira - HOTEL APARTMENTS | B3: =DATABASE!B41 -> Center | C3: =DATABASE!C41 -> 242A | D3: =DATABASE!E41 -> 1-BR | E3: =DATABASE!F41 -> 60.2 | F3: =DATABASE!G41 -> 0 | G3: =DATABASE!H41 -> 1 | H3: =DATABASE!I41 | I3: =DATABASE!J41 -> 3.9 | J3: =DATABASE!K41 -> 0 | K3: =DATABASE!L41 -> 0 | ... Y3: =DATABASE!Z41 -> -35000 | Z3: =DATABASE!#REF! -> #REF! | AA3: =DATABASE!AA41 -> 0 | AB3: =DATABASE!AB41 -> 47118
A4: =DATABASE!A42 -> Aroeira - VILLAS | B4: =DATABASE!B42 -> Center | C4: =DATABASE!C42 -> 05D | D4: =DATABASE!E42 -> T4 | E4: =DATABASE!F42 -> 559 | F4: =DATABASE!G42 -> 0 | G4: =DATABASE!H42 -> 2 | H4: =DATABASE!I42 -> 1 | I4: =DATABASE!J42 -> 0 | J4: =DATABASE!K42 -> 0 | K4: =DATABASE!L42 -> 0 | ... Y4: =DATABASE!Z42 -> 2500000 | Z4: =DATABASE!#REF! -> #REF! | AA4: =DATABASE!#REF! -> #REF! | AB4: =DATABASE!AB42 -> 47118
